Workbook

Sheet Dashboard
A1: Ops2EBITDA
A2: Add-On Synergy Excel Model
A3: Integration value capture dashboard for tuck-in acquisitions and post-close synergy execution.
A5: Gross Synergy Target | C5: Net Synergy Target | E5: Validated EBITDA | G5: Validation % | I5: EV Uplift
A6: =Workstream_Detail!E12 -> 12590000 | C6: =Workstream_Detail!F12 -> 10158800 | E6: =Workstream_Detail!H12 -> 2826655 | G6: =Workstream_Detail!I12 -> 0.27824694 | I6: =Workstream_Detail!J12 -> 32506532
A8: Current Read
A9: ="Current read: "&TEXT(Workstream_Detail!H12,"$0.0,,\M")&" of validated EBITDA captured, representing "&TEXT(Workstream_Detail!I12,"0.0%")&" of net target. Focus on at-risk workstreams and the largest gaps to target." -> Current read: $2.8M of validated EBITDA captured, representing 27.8% of net target. Focus on at-risk workstreams and the largest gaps to target.
A11: Priority Integration Workstreams
A12: Workstream | B12: Initiatives | C12: # At Risk | D12: Net Target ($) | E12: Run-Rate Captured ($) | F12: Validated EBITDA ($) | G12: Validation % | H12: Exit Value ($) | I12: Status | J12: Gap to Target ($) | K12: Management Action
A13: =Workstream_Detail!A4 -> Procurement | B13: =Workstream_Detail!B4 -> 3 | C13: =Workstream_Detail!D4 -> 0 | D13: =Workstream_Detail!F4 -> 2198000 | E13: =Workstream_Detail!G4 -> 622750 | F13: =Workstream_Detail!H4 -> 371862.5 | G13: =Workstream_Detail!I4 -> 0.16918221 | H13: =Workstream_Detail!J4 -> 4276418.8 | I13: =Workstream_Detail!K4 -> Behind | J13: =Workstream_Detail!F4-Workstream_Detail!H4 -> 1826137.5 | K13: =IF(J13>1000000,"Escalate owner and rebuild recovery plan",IF(G13<0.5,"Improve evidence and validation","Monitor")) -> Escalate owner and rebuild recovery plan
A14: =Workstream_Detail!A5 -> Supply Chain / Logistics | B14: =Workstream_Detail!B5 -> 2 | C14: =Workstream_Detail!D5 -> 1 | D14: =Workstream_Detail!F5 -> 1102800 | E14: =Workstream_Detail!G5 -> 444680 | F14: =Workstream_Detail!H5 -> 416470 | G14: =Workstream_Detail!I5 -> 0.37764781 | H14: =Workstream_Detail!J5 -> 4789405 | I14: =Workstream_Detail!K5 -> Behind | J14: =Workstream_Detail!F5-Workstream_Detail!H5 -> 686330 | K14: =IF(J14>1000000,"Escalate owner and rebuild recovery plan",IF(G14<0.5,"Improve evidence and validation","Monitor")) -> Improve evidence and validation
A15: =Workstream_Detail!A6 -> G&A / SG&A | B15: =Workstream_Detail!B6 -> 4 | C15: =Workstream_Detail!D6 -> 0 | D15: =Workstream_Detail!F6 -> 1724000 | E15: =Workstream_Detail!G6 -> 1019700 | F15: =Workstream_Detail!H6 -> 940050 | G15: =Workstream_Detail!I6 -> 0.54527262 | H15: =Workstream_Detail!J6 -> 10810575 | I15: =Workstream_Detail!K6 -> Behind | J15: =Workstream_Detail!F6-Workstream_Detail!H6 -> 783950 | K15: =IF(J15>1000000,"Escalate owner and rebuild recovery plan",IF(G15<0.5,"Improve evidence and validation","Monitor")) -> Monitor
A16: =Workstream_Detail!A7 -> Systems / IT | B16: =Workstream_Detail!B7 -> 3 | C16: =Workstream_Detail!D7 -> 1 | D16: =Workstream_Detail!F7 -> 982500 | E16: =Workstream_Detail!G7 -> 328040 | F16: =Workstream_Detail!H7 -> 285192.5 | G16: =Workstream_Detail!I7 -> 0.29027226 | H16: =Workstream_Detail!J7 -> 3279713.8 | I16: =Workstream_Detail!K7 -> Behind | J16: =Workstream_Detail!F7-Workstream_Detail!H7 -> 697307.5 | K16: =IF(J16>1000000,"Escalate owner and rebuild recovery plan",IF(G16<0.5,"Improve evidence and validation","Monitor")) -> Improve evidence and validation
A17: =Workstream_Detail!A8 -> Facilities / Footprint | B17: =Workstream_Detail!B8 -> 2 | C17: =Workstream_Detail!D8 -> 0 | D17: =Workstream_Detail!F8 -> 746000 | E17: =Workstream_Detail!G8 -> 20800 | F17: =Workstream_Detail!H8 -> 7280 | G17: =Workstream_Detail!I8 -> 0.0097587131 | H17: =Workstream_Detail!J8 -> 83720 | I17: =Workstream_Detail!K8 -> Behind | J17: =Workstream_Detail!F8-Workstream_Detail!H8 -> 738720 | K17: =IF(J17>1000000,"Escalate owner and rebuild recovery plan",IF(G17<0.5,"Improve evidence and validation","Monitor")) -> Improve evidence and validation
A18: =Workstream_Detail!A9 -> Finance / Back Office | B18: =Workstream_Detail!B9 -> 2 | C18: =Workstream_Detail!D9 -> 0 | D18: =Workstream_Detail!F9 -> 691400 | E18: =Workstream_Detail!G9 -> 207680 | F18: =Workstream_Detail!H9 -> 155760 | G18: =Workstream_Detail!I9 -> 0.22528204 | H18: =Workstream_Detail!J9 -> 1791240 | I18: =Workstream_Detail!K9 -> Behind | J18: =Workstream_Detail!F9-Workstream_Detail!H9 -> 535640 | K18: =IF(J18>1000000,"Escalate owner and rebuild recovery plan",IF(G18<0.5,"Improve evidence and validation","Monitor")) -> Improve evidence and validation
A19: =Workstream_Detail!A10 -> Revenue / Cross-sell | B19: =Workstream_Detail!B10 -> 2 | C19: =Workstream_Detail!D10 -> 0 | D19: =Workstream_Detail!F10 -> 1677500 | E19: =Workstream_Detail!G10 -> 147300 | F19: =Workstream_Detail!H10 -> 51555 | G19: =Workstream_Detail!I10 -> 0.030733234 | H19: =Workstream_Detail!J10 -> 592882.5 | I19: =Workstream_Detail!K10 -> Behind | J19: =Workstream_Detail!F10-Workstream_Detail!H10 -> 1625945 | K19: =IF(J19>1000000,"Escalate owner and rebuild recovery plan",IF(G19<0.5,"Improve evidence and validation","Monitor")) -> Escalate owner and rebuild recovery plan
A20: =Workstream_Detail!A11 -> Revenue Leakage | B20: =Workstream_Detail!B11 -> 2 | C20: =Workstream_Detail!D11 -> 0 | D20: =Workstream_Detail!F11 -> 1036600 | E20: =Workstream_Detail!G11 -> 672860 | F20: =Workstream_Detail!H11 -> 598485 | G20: =Workstream_Detail!I11 -> 0.57735385 | H20: =Workstream_Detail!J11 -> 6882577.5 | I20: =Workstream_Detail!K11 -> Watch | J20: =Workstream_Detail!F11-Workstream_Detail!H11 -> 438115 | K20: =IF(J20>1000000,"Escalate owner and rebuild recovery plan",IF(G20<0.5,"Improve evidence and validation","Monitor")) -> Monitor
A22: Value Capture Visualization
A23: Workstream | B23: Net Target ($) | C23: Validated EBITDA ($) | D23: Gap to Target ($) | E23: Validation % | F23: Target Bar | G23: Validated Bar | H23: Gap Bar | I23: Status | J23: Evidence Focus | K23: Owner Action
A24: =A13 -> Procurement | B24: =D13 -> 2198000 | C24: =F13 -> 371862.5 | D24: =J13 -> 1826137.5 | E24: =G13 -> 0.16918221 | F24: =B24 -> 2198000 | G24: =C24 -> 371862.5 | H24: =D24 -> 1826137.5 | I24: =I13 -> Behind | J24: =IF(E24<50%,"Low validation",IF(E24<75%,"Validate evidence","On track")) -> Low validation | K24: =K13 -> Escalate owner and rebuild recovery plan
A25: =A14 -> Supply Chain / Logistics | B25: =D14 -> 1102800 | C25: =F14 -> 416470 | D25: =J14 -> 686330 | E25: =G14 -> 0.37764781 | F25: =B25 -> 1102800 | G25: =C25 -> 416470 | H25: =D25 -> 686330 | I25: =I14 -> Behind | J25: =IF(E25<50%,"Low validation",IF(E25<75%,"Validate evidence","On track")) -> Low validation | K25: =K14 -> Improve evidence and validation
A26: =A15 -> G&A / SG&A | B26: =D15 -> 1724000 | C26: =F15 -> 940050 | D26: =J15 -> 783950 | E26: =G15 -> 0.54527262 | F26: =B26 -> 1724000 | G26: =C26 -> 940050 | H26: =D26 -> 783950 | I26: =I15 -> Behind | J26: =IF(E26<50%,"Low validation",IF(E26<75%,"Validate evidence","On track")) -> Validate evidence | K26: =K15 -> Monitor
A27: =A16 -> Systems / IT | B27: =D16 -> 982500 | C27: =F16 -> 285192.5 | D27: =J16 -> 697307.5 | E27: =G16 -> 0.29027226 | F27: =B27 -> 982500 | G27: =C27 -> 285192.5 | H27: =D27 -> 697307.5 | I27: =I16 -> Behind | J27: =IF(E27<50%,"Low validation",IF(E27<75%,"Validate evidence","On track")) -> Low validation | K27: =K16 -> Improve evidence and validation
A28: =A17 -> Facilities / Footprint | B28: =D17 -> 746000 | C28: =F17 -> 7280 | D28: =J17 -> 738720 | E28: =G17 -> 0.0097587131 | F28: =B28 -> 746000 | G28: =C28 -> 7280 | H28: =D28 -> 738720 | I28: =I17 -> Behind | J28: =IF(E28<50%,"Low validation",IF(E28<75%,"Validate evidence","On track")) -> Low validation | K28: =K17 -> Improve evidence and validation
A29: =A18 -> Finance / Back Office | B29: =D18 -> 691400 | C29: =F18 -> 155760 | D29: =J18 -> 535640 | E29: =G18 -> 0.22528204 | F29: =B29 -> 691400 | G29: =C29 -> 155760 | H29: =D29 -> 535640 | I29: =I18 -> Behind | J29: =IF(E29<50%,"Low validation",IF(E29<75%,"Validate evidence","On track")) -> Low validation | K29: =K18 -> Improve evidence and validation
A30: =A19 -> Revenue / Cross-sell | B30: =D19 -> 1677500 | C30: =F19 -> 51555 | D30: =J19 -> 1625945 | E30: =G19 -> 0.030733234 | F30: =B30 -> 1677500 | G30: =C30 -> 51555 | H30: =D30 -> 1625945 | I30: =I19 -> Behind | J30: =IF(E30<50%,"Low validation",IF(E30<75%,"Validate evidence","On track")) -> Low validation | K30: =K19 -> Escalate owner and rebuild recovery plan
A31: =A20 -> Revenue Leakage | B31: =D20 -> 1036600 | C31: =F20 -> 598485 | D31: =J20 -> 438115 | E31: =G20 -> 0.57735385 | F31: =B31 -> 1036600 | G31: =C31 -> 598485 | H31: =D31 -> 438115 | I31: =I20 -> Watch | J31: =IF(E31<50%,"Low validation",IF(E31<75%,"Validate evidence","On track")) -> Validate evidence | K31: =K20 -> Monitor

Sheet Instructions
B1: How to Use This Model
B3: Step | C3: Action | D3: Details | F3: Workbook Flow
B4: 1 | C4: Update Inputs | D4: Edit blue-font assumptions in the Inputs sheet. Update close date, current month, multiples, haircut, and financial baselines. | F4: Inputs | G4: Set assumptions and deal baseline
B5: 2 | C5: Replace sample synergy initiatives | D5: Use Synergy_Tracker to enter each cost, revenue, systems, footprint, and back-office synergy. Keep one initiative per row. | F5: Target_Financials | G5: Review target cost base and entry economics
B6: 3 | C6: Validate one-time costs | D6: Add integration costs by initiative so the EBITDA and value bridge separates run-rate value from implementation cost. | F6: Synergy_Tracker | G6: Enter initiatives, target values, risk haircuts, realization, evidence quality
B7: 4 | C7: Track milestones | D7: Use Integration_Milestones to manage Day 1, Day 30, Day 100, Month 6, and Month 12 execution. | F7: Integration_Milestones | G7: Track integration execution and due dates
B8: 5 | C8: Review Workstream Detail | D8: Use Workstream_Detail to identify which workstreams are behind plan, under-validated, or at risk. | F8: Workstream_Detail | G8: Summarize target/capture/validation by workstream
B9: 6 | C9: Use Dashboard for executive readout | D9: Use Dashboard for board/management discussion: total synergy target, captured run-rate, validated EBITDA, EV uplift, and priority actions. | F9: EBITDA_Bridge | G9: Translate synergies into post-synergy EBITDA and enterprise value
B10: 7 | C10: Refresh evidence quality | D10: Validated EBITDA is risk-weighted by evidence quality. Increase evidence quality only when savings are visible in budget, invoices, headcount, contracts, or booked contribution margin. | F10: Dashboard | G10: Use as executive summary and management action page

Sheet Inputs
A1: Ops2EBITDA — Add-On Synergy & Integration Value Capture Model
A3: Editable Assumptions
A4: Assumption | B4: Value | C4: Units / Format | D4: Notes
A5: Platform Revenue | B5: 250000000 | C5: $ | D5: Standalone platform revenue
A6: Platform EBITDA | B6: 37500000 | C6: $ | D6: Standalone platform EBITDA
A7: Target Revenue | B7: 50000000 | C7: $ | D7: Acquired target annual revenue
A8: Target EBITDA | B8: 6500000 | C8: $ | D8: Acquired target standalone EBITDA
A9: Platform Exit Multiple | B9: 11.5 | C9: x | D9: Valuation multiple for value capture
A10: Target Purchase Multiple | B10: 7 | C10: x | D10: Entry multiple paid for target EBITDA
A11: Tax / Leakage Rate | B11: 0 | C11: % | D11: Optional leakage rate for net value
A12: Synergy Realization Haircut | B12: 0.15 | C12: % | D12: Default risk haircut for savings realization
A13: One-Time Integration Cost Multiple | B13: 1.2 | C13: x | D13: Default one-time cost as multiple of Year 1 gross run-rate synergy
A14: Integration Start Date | B14: 46174 | C14: date | D14: Expected Day 1 / close date
A15: Current Month | B15: 46265 | C15: date | D15: Used for status and run-rate tracking
A16: EBITDA Validation Threshold | B16: 0.8 | C16: % | D16: Minimum validated / target threshold for green status
A17: Run-Rate Threshold | B17: 0.6 | C17: % | D17: Minimum run-rate / target threshold for watchlist
A18: Currency | B18: USD | C18: text | D18: Model currency
A20: Workstream Benchmarks / Default Realization Curves
A21: Workstream | B21: Default Owner | C21: Realization Month 3 | D21: Realization Month 6 | E21: Realization Month 12 | F21: Risk Level | G21: Typical Evidence Required
A22: Procurement | B22: CPO / CFO | C22: 0.25 | D22: 0.55 | E22: 0.9 | F22: Medium | G22: Signed vendor contract, invoice proof, purchase order compliance
A23: G&A / SG&A | B23: CFO / COO | C23: 0.35 | D23: 0.7 | E23: 1 | F23: Medium | G23: Org changes, eliminated run-rate spend, budget removal
A24: Systems / IT | B24: CIO / Integration Lead | C24: 0.1 | D24: 0.35 | E24: 0.75 | F24: High | G24: System decommissioning, license termination, support cost removal
A25: Revenue / Cross-sell | B25: CRO | C25: 0.05 | D25: 0.2 | E25: 0.55 | F25: High | G25: Booked revenue, retained margin, CRM opportunity proof
A26: Facilities / Footprint | B26: COO | C26: 0.15 | D26: 0.45 | E26: 0.85 | F26: High | G26: Lease exit, utilization evidence, cost baseline
A27: Finance / Back Office | B27: CFO | C27: 0.25 | D27: 0.6 | E27: 0.95 | F27: Medium | G27: Closed process migration, headcount/vendor cost removal
A28: Supply Chain / Logistics | B28: COO / VP Supply Chain | C28: 0.2 | D28: 0.5 | E28: 0.9 | F28: Medium | G28: Carrier rate proof, lane-level savings, freight invoices
A29: Revenue Leakage | B29: CRO / CFO | C29: 0.2 | D29: 0.55 | E29: 0.9 | F29: Medium | G29: Contract compliance, billing correction, invoice proof

Sheet Target_Financials
A1: Target + Platform Financial Baseline
A3: Financial Baseline and Entry Value
A4: Metric | B4: Platform | C4: Target | D4: Combined Pre-Synergy | E4: Formula / Notes
A5: Revenue ($) | B5: =Inputs!B5 -> 250000000 | C5: =Inputs!B7 -> 50000000 | D5: =B5+C5 -> 300000000 | E5: Platform + target
A6: EBITDA ($) | B6: =Inputs!B6 -> 37500000 | C6: =Inputs!B8 -> 6500000 | D6: =B6+C6 -> 44000000 | E6: Standalone EBITDA
A7: EBITDA Margin | B7: =B6/B5 -> 0.15 | C7: =C6/C5 -> 0.13 | D7: =D6/D5 -> 0.14666667 | E7: EBITDA / Revenue
A8: Purchase Enterprise Value ($) | C8: =Inputs!B8*Inputs!B10 -> 45500000 | E8: Target EBITDA x purchase multiple
A9: Implied Revenue Multiple | C9: =C8/C5 -> 0.91 | E9: Purchase EV / target revenue
A10: Platform EV at Exit Multiple | B10: =Inputs!B6*Inputs!B9 -> 431250000 | D10: =D6*Inputs!B9 -> 506000000 | E10: EBITDA x platform multiple
A12: Standalone Target P&L by Function / Cost Base
A13: Function / Cost Base | B13: Annual Cost / Revenue ($) | C13: % of Target Revenue | D13: Integration Relevance | E13: Primary Synergy Lever | F13: Notes
A14: Direct Materials / COGS | B14: 21000000 | C14: =B14/Inputs!B7 -> 0.42 | D14: High | E14: Procurement / supply chain | F14: Vendor terms, commodity rates, volume leverage
A15: Freight & Logistics | B15: 3800000 | C15: =B15/Inputs!B7 -> 0.076 | D15: High | E15: Supply Chain / Logistics | F15: Carrier consolidation and lane optimization
A16: Sales & Marketing | B16: 6500000 | C16: =B16/Inputs!B7 -> 0.13 | D16: Medium | E16: G&A / Revenue | F16: Channel overlap, cross-sell, marketing stack
A17: G&A Payroll | B17: 7200000 | C17: =B17/Inputs!B7 -> 0.144 | D17: High | E17: G&A / SG&A | F17: Duplicative finance, HR, admin roles
A18: IT Software & Infrastructure | B18: 2400000 | C18: =B18/Inputs!B7 -> 0.048 | D18: High | E18: Systems / IT | F18: Duplicate systems, licenses, hosting, support
A19: Facilities & Occupancy | B19: 3100000 | C19: =B19/Inputs!B7 -> 0.062 | D19: Medium | E19: Facilities / Footprint | F19: Lease overlap and site consolidation
A20: Finance / Back Office Services | B20: 1800000 | C20: =B20/Inputs!B7 -> 0.036 | D20: High | E20: Finance / Back Office | F20: External accounting, payroll, AP processing
A21: Other OpEx | B21: 3700000 | C21: =B21/Inputs!B7 -> 0.074 | D21: Medium | E21: G&A / SG&A | F21: Professional services and discretionary spend

Sheet Synergy_Tracker
A1: Synergy Tracker — Cost, Revenue, and Integration Value Capture
A3: ID | B3: Workstream | C3: Initiative | D3: Owner | E3: Status | F3: Priority | G3: Start Date | H3: Target Date | I3: Gross Target ($) | J3: Risk Haircut % | K3: Net Target ($) | L3: One-Time Cost ($) | M3: Month 3 Realization % | N3: Month 6 Realization % | O3: Month 12 Realization % | P3: Current Realization % | Q3: Run-Rate Captured ($) | R3: Validated EBITDA ($) | S3: Evidence Quality | T3: Value at Exit ($) | U3: Notes
A4: SYN-001 | B4: Procurement | C4: Consolidate packaging vendors | D4: CPO | E4: In Progress | F4: High | G4: 46183 | H4: 46326 | I4: 950000 | J4: 0.1 | K4: =I4*(1-J4) -> 855000 | L4: 180000 | M4: 0.25 | N4: 0.55 | O4: 0.95 | P4: 0.45 | Q4: =K4*P4 -> 384750 | R4: =IF(S4="High",Q4,IF(S4="Medium",Q4*0.75,Q4*0.35)) -> 288562.5 | S4: Medium | T4: =R4*Inputs!$B$9 -> 3318468.8 | U4: Move target volume to platform preferred supplier
A5: SYN-002 | B5: Procurement | C5: Renegotiate raw material contracts | D5: CPO | E5: Not Started | F5: High | G5: 46204 | H5: 46371 | I5: 1400000 | J5: 0.15 | K5: =I5*(1-J5) -> 1190000 | L5: 220000 | M5: 0.1 | N5: 0.45 | O5: 0.9 | P5: 0.2 | Q5: =K5*P5 -> 238000 | R5: =IF(S5="High",Q5,IF(S5="Medium",Q5*0.75,Q5*0.35)) -> 83300 | S5: Low | T5: =R5*Inputs!$B$9 -> 957950 | U5: RFP required for top three suppliers
A6: SYN-003 | B6: Supply Chain / Logistics | C6: Move freight to platform carrier rates | D6: VP Supply Chain | E6: In Progress | F6: High | G6: 46188 | H6: 46295 | I6: 760000 | J6: 0.12 | K6: =I6*(1-J6) -> 668800 | L6: 120000 | M6: 0.35 | N6: 0.7 | O6: 0.95 | P6: 0.6 | Q6: =K6*P6 -> 401280 | R6: =IF(S6="High",Q6,IF(S6="Medium",Q6*0.75,Q6*0.35)) -> 401280 | S6: High | T6: =R6*Inputs!$B$9 -> 4614720 | U6: Lane-level validation started
A7: SYN-004 | B7: G&A / SG&A | C7: Eliminate duplicate accounting roles | D7: CFO | E7: Complete | F7: High | G7: 46174 | H7: 46265 | I7: 820000 | J7: 0.05 | K7: =I7*(1-J7) -> 779000 | L7: 410000 | M7: 0.5 | N7: 0.85 | O7: 1 | P7: 0.9 | Q7: =K7*P7 -> 701100 | R7: =IF(S7="High",Q7,IF(S7="Medium",Q7*0.75,Q7*0.35)) -> 701100 | S7: High | T7: =R7*Inputs!$B$9 -> 8062650 | U7: Severance included in one-time cost
A8: SYN-005 | B8: G&A / SG&A | C8: Consolidate HR and payroll admin | D8: CHRO | E8: In Progress | F8: Medium | G8: 46193 | H8: 46356 | I8: 430000 | J8: 0.1 | K8: =I8*(1-J8) -> 387000 | L8: 160000 | M8: 0.2 | N8: 0.55 | O8: 0.95 | P8: 0.35 | Q8: =K8*P8 -> 135450 | R8: =IF(S8="High",Q8,IF(S8="Medium",Q8*0.75,Q8*0.35)) -> 101587.5 | S8: Medium | T8: =R8*Inputs!$B$9 -> 1168256.2 | U8: Transition services period through Q4
A9: SYN-006 | B9: Systems / IT | C9: Decommission target ERP licenses | D9: CIO | E9: At Risk | F9: High | G9: 46174 | H9: 46477 | I9: 650000 | J9: 0.25 | K9: =I9*(1-J9) -> 487500 | L9: 780000 | M9: 0 | N9: 0.25 | O9: 0.75 | P9: 0.1 | Q9: =K9*P9 -> 48750 | R9: =IF(S9="High",Q9,IF(S9="Medium",Q9*0.75,Q9*0.35)) -> 17062.5 | S9: Low | T9: =R9*Inputs!$B$9 -> 196218.75 | U9: Migration dependencies delaying savings
A10: SYN-007 | B10: Systems / IT | C10: Consolidate CRM and marketing tools | D10: CIO | E10: In Progress | F10: Medium | G10: 46218 | H10: 46418 | I10: 310000 | J10: 0.2 | K10: =I10*(1-J10) -> 248000 | L10: 250000 | M10: 0.05 | N10: 0.3 | O10: 0.8 | P10: 0.18 | Q10: =K10*P10 -> 44640 | R10: =IF(S10="High",Q10,IF(S10="Medium",Q10*0.75,Q10*0.35)) -> 33480 | S10: Medium | T10: =R10*Inputs!$B$9 -> 385020 | U10: Includes license rationalization
A11: SYN-008 | B11: Facilities / Footprint | C11: Close duplicate regional office | D11: COO | E11: Not Started | F11: Medium | G11: 46235 | H11: 46446 | I11: 520000 | J11: 0.2 | K11: =I11*(1-J11) -> 416000 | L11: 620000 | M11: 0 | N11: 0.2 | O11: 0.85 | P11: 0.05 | Q11: =K11*P11 -> 20800 | R11: =IF(S11="High",Q11,IF(S11="Medium",Q11*0.75,Q11*0.35)) -> 7280 | S11: Low | T11: =R11*Inputs!$B$9 -> 83720 | U11: Lease termination negotiation pending
A12: SYN-009 | B12: Finance / Back Office | C12: Move AP to platform shared service | D12: CFO | E12: In Progress | F12: High | G12: 46193 | H12: 46387 | I12: 590000 | J12: 0.12 | K12: =I12*(1-J12) -> 519200 | L12: 240000 | M12: 0.2 | N12: 0.55 | O12: 0.95 | P12: 0.4 | Q12: =K12*P12 -> 207680 | R12: =IF(S12="High",Q12,IF(S12="Medium",Q12*0.75,Q12*0.35)) -> 155760 | S12: Medium | T12: =R12*Inputs!$B$9 -> 1791240 | U12: PO compliance required
A13: SYN-010 | B13: Revenue / Cross-sell | C13: Cross-sell target product into platform top accounts | D13: CRO | E13: In Progress | F13: High | G13: 46204 | H13: 46568 | I13: 1750000 | J13: 0.35 | K13: =I13*(1-J13) -> 1137500 | L13: 300000 | M13: 0.05 | N13: 0.2 | O13: 0.55 | P13: 0.12 | Q13: =K13*P13 -> 136500 | R13: =IF(S13="High",Q13,IF(S13="Medium",Q13*0.75,Q13*0.35)) -> 47775 | S13: Low | T13: =R13*Inputs!$B$9 -> 549412.5 | U13: Contribution margin savings equivalent
A14: SYN-011 | B14: Revenue / Cross-sell | C14: Bundle platform service into target accounts | D14: CRO | E14: Not Started | F14: Medium | G14: 46266 | H14: 46660 | I14: 900000 | J14: 0.4 | K14: =I14*(1-J14) -> 540000 | L14: 180000 | M14: 0 | N14: 0.1 | O14: 0.45 | P14: 0.02 | Q14: =K14*P14 -> 10800 | R14: =IF(S14="High",Q14,IF(S14="Medium",Q14*0.75,Q14*0.35)) -> 3780 | S14: Low | T14: =R14*Inputs!$B$9 -> 43470 | U14: Requires sales enablement
A15: SYN-012 | B15: Revenue Leakage | C15: Correct under-billed service fees | D15: CFO / CRO | E15: Complete | F15: High | G15: 46178 | H15: 46249 | I15: 480000 | J15: 0.08 | K15: =I15*(1-J15) -> 441600 | L15: 40000 | M15: 0.5 | N15: 0.85 | O15: 1 | P15: 0.85 | Q15: =K15*P15 -> 375360 | R15: =IF(S15="High",Q15,IF(S15="Medium",Q15*0.75,Q15*0.35)) -> 375360 | S15: High | T15: =R15*Inputs!$B$9 -> 4316640 | U15: Contract-to-invoice audit complete
... A23: SYN-020 | B23: G&A / SG&A | C23: Insurance broker consolidation | D23: CFO | E23: In Progress | F23: Low | G23: 46218 | H23: 46371 | I23: 270000 | J23: 0.1 | K23: =I23*(1-J23) -> 243000 | L23: 20000 | M23: 0.1 | N23: 0.5 | O23: 0.95 | P23: 0.3 | Q23: =K23*P23 -> 72900 | R23: =IF(S23="High",Q23,IF(S23="Medium",Q23*0.75,Q23*0.35)) -> 54675 | S23: Medium | T23: =R23*Inputs!$B$9 -> 628762.5 | U23: Benchmark underway

Sheet Integration_Milestones
A1: Integration Milestones — Day 1 to Day 365 Execution Control
A3: Milestone ID | B3: Phase | C3: Workstream | D3: Milestone | E3: Owner | F3: Due Date | G3: Status | H3: Dependency | I3: Criticality | J3: Days Until Due | K3: Late? | L3: Notes
A4: M-001 | B4: Day 1 | C4: Finance / Back Office | D4: Open combined cash reporting process | E4: CFO | F4: 46174 | G4: Complete | H4: Close | I4: High | J4: =F4-Inputs!$B$15 -> -91 | K4: =IF(AND(G4<>"Complete",F4<Inputs!$B$15),"Late","") | L4: Day-1 treasury visibility
A5: M-002 | B5: Day 1 | C5: Management Cadence | D5: Launch integration command center | E5: Integration Lead | F5: 46176 | G5: Complete | H5: Close | I5: High | J5: =F5-Inputs!$B$15 -> -89 | K5: =IF(AND(G5<>"Complete",F5<Inputs!$B$15),"Late","") | L5: Weekly integration review
A6: M-003 | B6: Day 30 | C6: G&A / SG&A | D6: Confirm duplicate role list and severance plan | E6: CFO / CHRO | F6: 46203 | G6: Complete | H6: HR diligence | I6: High | J6: =F6-Inputs!$B$15 -> -62 | K6: =IF(AND(G6<>"Complete",F6<Inputs!$B$15),"Late","") | L6: Needed for run-rate validation
A7: M-004 | B7: Day 30 | C7: Procurement | D7: Load target vendor master into spend cube | E7: CPO | F7: 46203 | G7: Complete | H7: AP extract | I7: High | J7: =F7-Inputs!$B$15 -> -62 | K7: =IF(AND(G7<>"Complete",F7<Inputs!$B$15),"Late","") | L7: Supports quick-win sourcing
A8: M-005 | B8: Day 60 | C8: Revenue Leakage | D8: Complete contract-to-invoice audit | E8: CFO / CRO | F8: 46234 | G8: Complete | H8: Customer contracts | I8: High | J8: =F8-Inputs!$B$15 -> -31 | K8: =IF(AND(G8<>"Complete",F8<Inputs!$B$15),"Late","") | L8: Billing correction workstream
A9: M-006 | B9: Day 60 | C9: Systems / IT | D9: Finalize target ERP migration plan | E9: CIO | F9: 46234 | G9: In Progress | H9: Data mapping | I9: High | J9: =F9-Inputs!$B$15 -> -31 | K9: =IF(AND(G9<>"Complete",F9<Inputs!$B$15),"Late","") -> Late | L9: Delay risk
A10: M-007 | B10: Day 90 | C10: Supply Chain / Logistics | D10: Move freight lanes to platform carriers | E10: VP Supply Chain | F10: 46265 | G10: In Progress | H10: Carrier contracts | I10: High | J10: =F10-Inputs!$B$15 -> 0 | K10: =IF(AND(G10<>"Complete",F10<Inputs!$B$15),"Late","") | L10: Track lane-level compliance
A11: M-008 | B11: Day 90 | C11: Finance / Back Office | D11: Move AP approval workflow to platform standard | E11: CFO | F11: 46265 | G11: In Progress | H11: PO policy | I11: Medium | J11: =F11-Inputs!$B$15 -> 0 | K11: =IF(AND(G11<>"Complete",F11<Inputs!$B$15),"Late","") | L11: Shared service dependency
A12: M-009 | B12: Day 100 | C12: Board / Governance | D12: Approve updated synergy forecast | E12: Integration Lead | F12: 46273 | G12: Not Started | H12: Validated tracker | I12: High | J12: =F12-Inputs!$B$15 -> 8 | K12: =IF(AND(G12<>"Complete",F12<Inputs!$B$15),"Late","") | L12: Board decision point
A13: M-010 | B13: Month 6 | C13: Procurement | D13: Complete top 10 supplier renegotiations | E13: CPO | F13: 46356 | G13: Not Started | H13: RFP launch | I13: High | J13: =F13-Inputs!$B$15 -> 91 | K13: =IF(AND(G13<>"Complete",F13<Inputs!$B$15),"Late","") | L13: Large cost synergy
A14: M-011 | B14: Month 6 | C14: Sales / Revenue | D14: Launch cross-sell playbook with top 50 accounts | E14: CRO | F14: 46356 | G14: In Progress | H14: Sales enablement | I14: High | J14: =F14-Inputs!$B$15 -> 91 | K14: =IF(AND(G14<>"Complete",F14<Inputs!$B$15),"Late","") | L14: Requires account mapping
A15: M-012 | B15: Month 6 | C15: G&A / SG&A | D15: Remove duplicated budget from FY27 plan | E15: CFO | F15: 46371 | G15: Not Started | H15: Budget cycle | I15: High | J15: =F15-Inputs!$B$15 -> 106 | K15: =IF(AND(G15<>"Complete",F15<Inputs!$B$15),"Late","") | L15: Proof of EBITDA capture
... A20: M-017 | B20: Month 12 | C20: Integration Office | D20: Close integration office or transition to BAU owners | E20: Integration Lead | F20: 46568 | G20: Not Started | H20: All workstreams | I20: Medium | J20: =F20-Inputs!$B$15 -> 303 | K20: =IF(AND(G20<>"Complete",F20<Inputs!$B$15),"Late","") | L20: Institutionalize tracking

Sheet Workstream_Detail
A1: Workstream Detail — Target, Capture, Validation, and Status
A3: Workstream | B3: Initiatives | C3: # Complete | D3: # At Risk | E3: Gross Target ($) | F3: Net Target ($) | G3: Run-Rate Captured ($) | H3: Validated EBITDA ($) | I3: Validation % | J3: Exit Value ($) | K3: Status
A4: Procurement | B4: =COUNTIF(Synergy_Tracker!$B$4:$B$23,A4) -> 3 | C4: =COUNTIFS(Synergy_Tracker!$B$4:$B$23,A4,Synergy_Tracker!$E$4:$E$23,"Complete") -> 0 | D4: =COUNTIFS(Synergy_Tracker!$B$4:$B$23,A4,Synergy_Tracker!$E$4:$E$23,"At Risk") -> 0 | E4: =SUMIF(Synergy_Tracker!$B$4:$B$23,A4,Synergy_Tracker!$I$4:$I$23) -> 2530000 | F4: =SUMIF(Synergy_Tracker!$B$4:$B$23,A4,Synergy_Tracker!$K$4:$K$23) -> 2198000 | G4: =SUMIF(Synergy_Tracker!$B$4:$B$23,A4,Synergy_Tracker!$Q$4:$Q$23) -> 622750 | H4: =SUMIF(Synergy_Tracker!$B$4:$B$23,A4,Synergy_Tracker!$R$4:$R$23) -> 371862.5 | I4: =IF(F4=0,0,H4/F4) -> 0.16918221 | J4: =H4*Inputs!$B$9 -> 4276418.8 | K4: =IF(I4>=Inputs!$B$16,"On Track",IF(G4/MAX(F4,1)<Inputs!$B$17,"Behind","Watch")) -> Behind
A5: Supply Chain / Logistics | B5: =COUNTIF(Synergy_Tracker!$B$4:$B$23,A5) -> 2 | C5: =COUNTIFS(Synergy_Tracker!$B$4:$B$23,A5,Synergy_Tracker!$E$4:$E$23,"Complete") -> 0 | D5: =COUNTIFS(Synergy_Tracker!$B$4:$B$23,A5,Synergy_Tracker!$E$4:$E$23,"At Risk") -> 1 | E5: =SUMIF(Synergy_Tracker!$B$4:$B$23,A5,Synergy_Tracker!$I$4:$I$23) -> 1380000 | F5: =SUMIF(Synergy_Tracker!$B$4:$B$23,A5,Synergy_Tracker!$K$4:$K$23) -> 1102800 | G5: =SUMIF(Synergy_Tracker!$B$4:$B$23,A5,Synergy_Tracker!$Q$4:$Q$23) -> 444680 | H5: =SUMIF(Synergy_Tracker!$B$4:$B$23,A5,Synergy_Tracker!$R$4:$R$23) -> 416470 | I5: =IF(F5=0,0,H5/F5) -> 0.37764781 | J5: =H5*Inputs!$B$9 -> 4789405 | K5: =IF(I5>=Inputs!$B$16,"On Track",IF(G5/MAX(F5,1)<Inputs!$B$17,"Behind","Watch")) -> Behind
A6: G&A / SG&A | B6: =COUNTIF(Synergy_Tracker!$B$4:$B$23,A6) -> 4 | C6: =COUNTIFS(Synergy_Tracker!$B$4:$B$23,A6,Synergy_Tracker!$E$4:$E$23,"Complete") -> 1 | D6: =COUNTIFS(Synergy_Tracker!$B$4:$B$23,A6,Synergy_Tracker!$E$4:$E$23,"At Risk") -> 0 | E6: =SUMIF(Synergy_Tracker!$B$4:$B$23,A6,Synergy_Tracker!$I$4:$I$23) -> 1870000 | F6: =SUMIF(Synergy_Tracker!$B$4:$B$23,A6,Synergy_Tracker!$K$4:$K$23) -> 1724000 | G6: =SUMIF(Synergy_Tracker!$B$4:$B$23,A6,Synergy_Tracker!$Q$4:$Q$23) -> 1019700 | H6: =SUMIF(Synergy_Tracker!$B$4:$B$23,A6,Synergy_Tracker!$R$4:$R$23) -> 940050 | I6: =IF(F6=0,0,H6/F6) -> 0.54527262 | J6: =H6*Inputs!$B$9 -> 10810575 | K6: =IF(I6>=Inputs!$B$16,"On Track",IF(G6/MAX(F6,1)<Inputs!$B$17,"Behind","Watch")) -> Behind
A7: Systems / IT | B7: =COUNTIF(Synergy_Tracker!$B$4:$B$23,A7) -> 3 | C7: =COUNTIFS(Synergy_Tracker!$B$4:$B$23,A7,Synergy_Tracker!$E$4:$E$23,"Complete") -> 1 | D7: =COUNTIFS(Synergy_Tracker!$B$4:$B$23,A7,Synergy_Tracker!$E$4:$E$23,"At Risk") -> 1 | E7: =SUMIF(Synergy_Tracker!$B$4:$B$23,A7,Synergy_Tracker!$I$4:$I$23) -> 1220000 | F7: =SUMIF(Synergy_Tracker!$B$4:$B$23,A7,Synergy_Tracker!$K$4:$K$23) -> 982500 | G7: =SUMIF(Synergy_Tracker!$B$4:$B$23,A7,Synergy_Tracker!$Q$4:$Q$23) -> 328040 | H7: =SUMIF(Synergy_Tracker!$B$4:$B$23,A7,Synergy_Tracker!$R$4:$R$23) -> 285192.5 | I7: =IF(F7=0,0,H7/F7) -> 0.29027226 | J7: =H7*Inputs!$B$9 -> 3279713.8 | K7: =IF(I7>=Inputs!$B$16,"On Track",IF(G7/MAX(F7,1)<Inputs!$B$17,"Behind","Watch")) -> Behind
A8: Facilities / Footprint | B8: =COUNTIF(Synergy_Tracker!$B$4:$B$23,A8) -> 2 | C8: =COUNTIFS(Synergy_Tracker!$B$4:$B$23,A8,Synergy_Tracker!$E$4:$E$23,"Complete") -> 0 | D8: =COUNTIFS(Synergy_Tracker!$B$4:$B$23,A8,Synergy_Tracker!$E$4:$E$23,"At Risk") -> 0 | E8: =SUMIF(Synergy_Tracker!$B$4:$B$23,A8,Synergy_Tracker!$I$4:$I$23) -> 960000 | F8: =SUMIF(Synergy_Tracker!$B$4:$B$23,A8,Synergy_Tracker!$K$4:$K$23) -> 746000 | G8: =SUMIF(Synergy_Tracker!$B$4:$B$23,A8,Synergy_Tracker!$Q$4:$Q$23) -> 20800 | H8: =SUMIF(Synergy_Tracker!$B$4:$B$23,A8,Synergy_Tracker!$R$4:$R$23) -> 7280 | I8: =IF(F8=0,0,H8/F8) -> 0.0097587131 | J8: =H8*Inputs!$B$9 -> 83720 | K8: =IF(I8>=Inputs!$B$16,"On Track",IF(G8/MAX(F8,1)<Inputs!$B$17,"Behind","Watch")) -> Behind
A9: Finance / Back Office | B9: =COUNTIF(Synergy_Tracker!$B$4:$B$23,A9) -> 2 | C9: =COUNTIFS(Synergy_Tracker!$B$4:$B$23,A9,Synergy_Tracker!$E$4:$E$23,"Complete") -> 0 | D9: =COUNTIFS(Synergy_Tracker!$B$4:$B$23,A9,Synergy_Tracker!$E$4:$E$23,"At Risk") -> 0 | E9: =SUMIF(Synergy_Tracker!$B$4:$B$23,A9,Synergy_Tracker!$I$4:$I$23) -> 800000 | F9: =SUMIF(Synergy_Tracker!$B$4:$B$23,A9,Synergy_Tracker!$K$4:$K$23) -> 691400 | G9: =SUMIF(Synergy_Tracker!$B$4:$B$23,A9,Synergy_Tracker!$Q$4:$Q$23) -> 207680 | H9: =SUMIF(Synergy_Tracker!$B$4:$B$23,A9,Synergy_Tracker!$R$4:$R$23) -> 155760 | I9: =IF(F9=0,0,H9/F9) -> 0.22528204 | J9: =H9*Inputs!$B$9 -> 1791240 | K9: =IF(I9>=Inputs!$B$16,"On Track",IF(G9/MAX(F9,1)<Inputs!$B$17,"Behind","Watch")) -> Behind
A10: Revenue / Cross-sell | B10: =COUNTIF(Synergy_Tracker!$B$4:$B$23,A10) -> 2 | C10: =COUNTIFS(Synergy_Tracker!$B$4:$B$23,A10,Synergy_Tracker!$E$4:$E$23,"Complete") -> 0 | D10: =COUNTIFS(Synergy_Tracker!$B$4:$B$23,A10,Synergy_Tracker!$E$4:$E$23,"At Risk") -> 0 | E10: =SUMIF(Synergy_Tracker!$B$4:$B$23,A10,Synergy_Tracker!$I$4:$I$23) -> 2650000 | F10: =SUMIF(Synergy_Tracker!$B$4:$B$23,A10,Synergy_Tracker!$K$4:$K$23) -> 1677500 | G10: =SUMIF(Synergy_Tracker!$B$4:$B$23,A10,Synergy_Tracker!$Q$4:$Q$23) -> 147300 | H10: =SUMIF(Synergy_Tracker!$B$4:$B$23,A10,Synergy_Tracker!$R$4:$R$23) -> 51555 | I10: =IF(F10=0,0,H10/F10) -> 0.030733234 | J10: =H10*Inputs!$B$9 -> 592882.5 | K10: =IF(I10>=Inputs!$B$16,"On Track",IF(G10/MAX(F10,1)<Inputs!$B$17,"Behind","Watch")) -> Behind
A11: Revenue Leakage | B11: =COUNTIF(Synergy_Tracker!$B$4:$B$23,A11) -> 2 | C11: =COUNTIFS(Synergy_Tracker!$B$4:$B$23,A11,Synergy_Tracker!$E$4:$E$23,"Complete") -> 1 | D11: =COUNTIFS(Synergy_Tracker!$B$4:$B$23,A11,Synergy_Tracker!$E$4:$E$23,"At Risk") -> 0 | E11: =SUMIF(Synergy_Tracker!$B$4:$B$23,A11,Synergy_Tracker!$I$4:$I$23) -> 1180000 | F11: =SUMIF(Synergy_Tracker!$B$4:$B$23,A11,Synergy_Tracker!$K$4:$K$23) -> 1036600 | G11: =SUMIF(Synergy_Tracker!$B$4:$B$23,A11,Synergy_Tracker!$Q$4:$Q$23) -> 672860 | H11: =SUMIF(Synergy_Tracker!$B$4:$B$23,A11,Synergy_Tracker!$R$4:$R$23) -> 598485 | I11: =IF(F11=0,0,H11/F11) -> 0.57735385 | J11: =H11*Inputs!$B$9 -> 6882577.5 | K11: =IF(I11>=Inputs!$B$16,"On Track",IF(G11/MAX(F11,1)<Inputs!$B$17,"Behind","Watch")) -> Watch
A12: Total | B12: =SUM(B4:B11) -> 20 | C12: =SUM(C4:C11) -> 3 | D12: =SUM(D4:D11) -> 2 | E12: =SUM(E4:E11) -> 12590000 | F12: =SUM(F4:F11) -> 10158800 | G12: =SUM(G4:G11) -> 3463810 | H12: =SUM(H4:H11) -> 2826655 | I12: =IF(F12=0,0,H12/F12) -> 0.27824694 | J12: =SUM(J4:J11) -> 32506532 | K12: =IF(I12>=Inputs!$B$16,"On Track","Watch") -> Watch

Sheet EBITDA_Bridge
A1: EBITDA Bridge — Standalone to Post-Synergy Run-Rate
A3: Bridge Summary
A4: Bridge Item | B4: Amount ($) | C4: Notes
A5: Platform Standalone EBITDA | B5: =Inputs!B6 -> 37500000 | C5: From Inputs
A6: Target Standalone EBITDA | B6: =Inputs!B8 -> 6500000 | C6: From Inputs
A7: Combined Pre-Synergy EBITDA | B7: =B5+B6 -> 44000000 | C7: Platform + target
A8: Validated Cost Synergies | B8: =SUMIFS(Synergy_Tracker!$R$4:$R$23,Synergy_Tracker!$B$4:$B$23,"<>Revenue / Cross-sell") -> 2775100 | C8: Validated non-revenue synergies
A9: Validated Revenue Synergy Contribution | B9: =SUMIFS(Synergy_Tracker!$R$4:$R$23,Synergy_Tracker!$B$4:$B$23,"Revenue / Cross-sell") -> 51555 | C9: Revenue synergy contribution margin equivalent
A10: Post-Synergy Run-Rate EBITDA | B10: =B7+B8+B9 -> 46826655 | C10: Current validated run-rate
A11: Incremental EBITDA vs. Pre-Synergy | B11: =B10-B7 -> 2826655 | C11: Value capture
A12: One-Time Integration Costs | B12: =SUM(Synergy_Tracker!$L$4:$L$23) -> 4390000 | C12: Estimated one-time cost
A13: Enterprise Value Uplift | B13: =B11*Inputs!B9 -> 32506532 | C13: Incremental EBITDA x exit multiple
A14: Net Value After One-Time Costs | B14: =B13-B12 -> 28116532 | C14: EV uplift less one-time integration costs
A17: Value Capture by Workstream
A18: Workstream | B18: Net Target ($) | C18: Validated EBITDA ($) | D18: Gap to Target ($) | E18: Validation % | F18: Exit Value ($)
A19: Procurement | B19: =Workstream_Detail!F4 -> 2198000 | C19: =Workstream_Detail!H4 -> 371862.5 | D19: =B19-C19 -> 1826137.5 | E19: =IF(B19=0,0,C19/B19) -> 0.16918221 | F19: =C19*Inputs!$B$9 -> 4276418.8
A20: Supply Chain / Logistics | B20: =Workstream_Detail!F5 -> 1102800 | C20: =Workstream_Detail!H5 -> 416470 | D20: =B20-C20 -> 686330 | E20: =IF(B20=0,0,C20/B20) -> 0.37764781 | F20: =C20*Inputs!$B$9 -> 4789405
A21: G&A / SG&A | B21: =Workstream_Detail!F6 -> 1724000 | C21: =Workstream_Detail!H6 -> 940050 | D21: =B21-C21 -> 783950 | E21: =IF(B21=0,0,C21/B21) -> 0.54527262 | F21: =C21*Inputs!$B$9 -> 10810575
A22: Systems / IT | B22: =Workstream_Detail!F7 -> 982500 | C22: =Workstream_Detail!H7 -> 285192.5 | D22: =B22-C22 -> 697307.5 | E22: =IF(B22=0,0,C22/B22) -> 0.29027226 | F22: =C22*Inputs!$B$9 -> 3279713.8
A23: Facilities / Footprint | B23: =Workstream_Detail!F8 -> 746000 | C23: =Workstream_Detail!H8 -> 7280 | D23: =B23-C23 -> 738720 | E23: =IF(B23=0,0,C23/B23) -> 0.0097587131 | F23: =C23*Inputs!$B$9 -> 83720
A24: Finance / Back Office | B24: =Workstream_Detail!F9 -> 691400 | C24: =Workstream_Detail!H9 -> 155760 | D24: =B24-C24 -> 535640 | E24: =IF(B24=0,0,C24/B24) -> 0.22528204 | F24: =C24*Inputs!$B$9 -> 1791240
A25: Revenue / Cross-sell | B25: =Workstream_Detail!F10 -> 1677500 | C25: =Workstream_Detail!H10 -> 51555 | D25: =B25-C25 -> 1625945 | E25: =IF(B25=0,0,C25/B25) -> 0.030733234 | F25: =C25*Inputs!$B$9 -> 592882.5
A26: Revenue Leakage | B26: =Workstream_Detail!F11 -> 1036600 | C26: =Workstream_Detail!H11 -> 598485 | D26: =B26-C26 -> 438115 | E26: =IF(B26=0,0,C26/B26) -> 0.57735385 | F26: =C26*Inputs!$B$9 -> 6882577.5
A27: Total | B27: =SUM(B19:B26) -> 10158800 | C27: =SUM(C19:C26) -> 2826655 | D27: =SUM(D19:D26) -> 7332145 | E27: =IF(B27=0,0,C27/B27) -> 0.27824694 | F27: =SUM(F19:F26) -> 32506532
