Workbook

Sheet Dashboard
A1: Ops2EBITDA — Pricing Waterfall & Margin Leakage Model
A2: Operator dashboard · Diagnose discounting, pocket price leakage, margin dispersion, and EBITDA upside
A4: Pocket Revenue | C4: Pocket Gross Margin | E4: Total Leakage | G4: Base Case EBITDA Upside | J4: Step | K4: Amount
A5: =Waterfall!B9 -> 1841936.2 | C5: =Waterfall!B11 -> 816807.2 | E5: =SUM(Customer_SKU_Data!W4:W123) -> 326858.8 | G5: =Scenarios!G5 -> 98059.257 | J5: Gross List Revenue | K5: =Waterfall!B4 -> 2168795
J6: Contract Discounts | K6: =Waterfall!B5 -> -188064.89
J7: Promo Discounts | K7: =Waterfall!B6 -> -74462.767
A8: Customer Priority View | J8: Rebates | K8: =Waterfall!B7 -> -52033.697
A9: Customer | B9: Segment | C9: Net Revenue | D9: Margin % | E9: Leakage $ | F9: Leakage Rate | G9: Action | H9: Priority Rank | J9: Freight Absorption | K9: =Waterfall!B8 -> -12297.45
A10: =Segmentation!A11 -> Harbor Care | B10: =Segmentation!B11 -> Enterprise | C10: =Segmentation!F11 -> 217953.66 | D10: =Segmentation!H11 -> 0.46405121 | E10: =Segmentation!I11 -> 49476.342 | F10: =Segmentation!J11 -> 0.1850067 | G10: =Segmentation!L11 -> Reduce leakage | H10: =_xlfn.RANK.EQ(E10,$E$10:$E$17,0) -> 1 | J10: Pocket Revenue | K10: =Waterfall!B9 -> 1841936.2
A11: =Segmentation!A5 -> Boreal Clinics | B11: =Segmentation!B5 -> Enterprise | C11: =Segmentation!F5 -> 182246.55 | D11: =Segmentation!H5 -> 0.40019167 | E11: =Segmentation!I5 -> 37578.449 | F11: =Segmentation!J5 -> 0.17094711 | G11: =Segmentation!L5 -> Reduce leakage | H11: =_xlfn.RANK.EQ(E11,$E$10:$E$17,0) -> 2 | J11: Pocket Gross Margin | K11: =Waterfall!B11 -> 816807.2
A12: =Segmentation!A6 -> Cobalt Services | B12: =Segmentation!B6 -> Mid-Market | C12: =Segmentation!F6 -> 162236.4 | D12: =Segmentation!H6 -> 0.4346953 | E12: =Segmentation!I6 -> 30838.598 | F12: =Segmentation!J6 -> 0.15972341 | G12: =Segmentation!L6 -> Reduce leakage | H12: =_xlfn.RANK.EQ(E12,$E$10:$E$17,0) -> 3
A13: =Segmentation!A4 -> Acme Health | B13: =Segmentation!B4 -> Enterprise | C13: =Segmentation!F4 -> 139013.69 | D13: =Segmentation!H4 -> 0.44009832 | E13: =Segmentation!I4 -> 30161.307 | F13: =Segmentation!J4 -> 0.17828466 | G13: =Segmentation!L4 -> Reduce leakage | H13: =_xlfn.RANK.EQ(E13,$E$10:$E$17,0) -> 4 | J13: Scenario | K13: Incremental EBITDA
A14: =Segmentation!A8 -> Evergreen Rehab | B14: =Segmentation!B8 -> Mid-Market | C14: =Segmentation!F8 -> 145921.45 | D14: =Segmentation!H8 -> 0.4025827 | E14: =Segmentation!I8 -> 25253.549 | F14: =Segmentation!J8 -> 0.14753059 | G14: =Segmentation!L8 -> Reduce leakage | H14: =_xlfn.RANK.EQ(E14,$E$10:$E$17,0) -> 5 | J14: Conservative | K14: =Scenarios!G4 -> 43993.855
A15: =Segmentation!A10 -> Granite Medical | B15: =Segmentation!B10 -> Mid-Market | C15: =Segmentation!F10 -> 127421.46 | D15: =Segmentation!H10 -> 0.44765193 | E15: =Segmentation!I10 -> 19173.535 | F15: =Segmentation!J10 -> 0.13079256 | G15: =Segmentation!L10 -> Reduce leakage | H15: =_xlfn.RANK.EQ(E15,$E$10:$E$17,0) -> 6 | J15: Base Case | K15: =Scenarios!G5 -> 98059.257
A16: =Segmentation!A7 -> Delta Dental Group | B16: =Segmentation!B7 -> Enterprise | C16: =Segmentation!F7 -> 75029.644 | D16: =Segmentation!H7 -> 0.43059839 | E16: =Segmentation!I7 -> 17970.356 | F16: =Segmentation!J7 -> 0.19322964 | G16: =Segmentation!L7 -> Reduce leakage | H16: =_xlfn.RANK.EQ(E16,$E$10:$E$17,0) -> 7 | J16: Upside | K16: =Scenarios!G6 -> 146669.07
A17: =Segmentation!A9 -> Fulton Labs | B17: =Segmentation!B9 -> SMB | C17: =Segmentation!F9 -> 143895.22 | D17: =Segmentation!H9 -> 0.4624839 | E17: =Segmentation!I9 -> 14044.775 | F17: =Segmentation!J9 -> 0.088924751 | G17: =Segmentation!L9 -> Monitor | H17: =_xlfn.RANK.EQ(E17,$E$10:$E$17,0) -> 8 | J17: Aggressive | K17: =Scenarios!G7 -> 202535.04

Sheet Instructions
A1: Ops2EBITDA — Pricing Waterfall & Margin Leakage Model
A3: Purpose
A4: This workbook helps diagnose pricing leakage across customers, SKUs, discounts, rebates, freight absorption, and pocket margin. It is designed for PE operating teams, value creation analysts, and consultants who need to quantify price upside and translate it into EBITDA impact.
A6: How to Use
A7: 1) Replace sample transaction data in Customer_SKU_Data. 2) Update assumptions in Inputs. 3) Review Waterfall, Segmentation, Scenarios, and Dashboard. 4) Use outputs to prioritize customer/SKU pricing actions and quantify EBITDA uplift.
A10: Workbook Map
A11: Sheet | B11: Use | C11: Editable? | D11: Notes
A12: Inputs | B12: Scenario and pricing assumptions | C12: Yes | D12: Blue-font cells are user inputs; formulas link from these assumptions.
A13: Customer_SKU_Data | B13: Transaction-level sample data | C13: Yes | D13: Replace with customer/SKU transaction export. Formula columns can be preserved or copied down.
A14: Waterfall | B14: Gross-to-pocket revenue waterfall | C14: No | D14: Shows leakage from list revenue to pocket revenue.
A15: Segmentation | B15: Customer-level leakage and margin view | C15: No | D15: Prioritizes customers by leakage dollars and margin performance.
A16: Scenarios | B16: Price and leakage recapture scenarios | C16: Yes | D16: Blue-font assumptions drive incremental EBITDA and enterprise value.
A17: Dashboard | B17: Executive summary | C17: No | D17: Board-ready summary view with KPIs, leakage, and recommended focus areas.
A18: Sources | B18: Source and assumption notes | C18: Yes | D18: Documents that sample data is synthetic and assumptions are illustrative.

Sheet Inputs
A1: Inputs & Scenario Assumptions
A3: Assumption | B3: Value | C3: Unit | D3: Description
A4: Target Price Increase | B4: 0.025 | C4: % | D4: Scenario price increase applied to current invoice price
A5: Volume Retention | B5: 0.985 | C5: % | D5: Expected retention of volume after price action
A6: Contract Discount Recapture | B6: 0.2 | C6: % | D6: Portion of contract discount leakage recovered
A7: Promo Discount Recapture | B7: 0.25 | C7: % | D7: Portion of promotional discount leakage recovered
A8: Rebate Reduction | B8: 0.15 | C8: % | D8: Portion of rebates eliminated or reduced
A9: Freight Recovery | B9: 0.35 | C9: % | D9: Portion of freight absorption passed through
A10: EBITDA Flow-Through | B10: 0.9 | C10: % | D10: Expected contribution of pricing actions to EBITDA
A11: Exit Multiple | B11: 12 | C11: x | D11: Enterprise value multiple applied to incremental EBITDA
A12: Low Margin Threshold | B12: 0.3 | C12: % | D12: Used to flag customers/SKUs below target pocket margin
A13: High Leakage Threshold | B13: 0.12 | C13: % | D13: Used to flag customers/SKUs with excessive leakage rate

Sheet Customer_SKU_Data
A1: Customer / SKU Transaction Data
A3: Txn_ID | B3: Date | C3: Customer | D3: Segment | E3: SKU | F3: Product_Family | G3: Units | H3: List_Price | I3: Unit_Cost | J3: Contract_Discount_% | K3: Promo_Discount_% | L3: Rebate_% | M3: Freight_Absorb_$ | N3: Invoice_Price | O3: Gross_Revenue | P3: Contract_Discount_$ | Q3: Promo_Discount_$ | R3: Rebate_$ | S3: Net_Revenue | T3: Standard_Cost | U3: Gross_Margin | V3: Pocket_Margin_% | W3: Total_Leakage_$ | X3: Leakage_Rate_% | Y3: Suggested_Action
A4: T-0001 | B4: 45937 | C4: Keystone Health | D4: Enterprise | E4: SKU-110 | F4: Core Platform | G4: 8 | H4: 160 | I4: 84 | J4: 0.10860793 | K4: 0.016288261 | L4: 0.030354541 | M4: 152.17201 | N4: =H4*(1-J4)*(1-K4) -> 140.29966 | O4: =G4*H4 -> 1280 | P4: =O4*J4 -> 139.01815 | Q4: =(O4-P4)*K4 -> 18.58461 | R4: =O4*L4 -> 38.853813 | S4: =G4*N4-R4-M4 -> 931.37142 | T4: =G4*I4 -> 672 | U4: =S4-T4 -> 259.37142 | V4: =IFERROR(U4/S4,0) -> 0.27848334 | W4: =P4+Q4+R4+M4 -> 348.62858 | X4: =IFERROR(W4/O4,0) -> 0.27236608 | Y4: =IF(AND(V4<Inputs!$B$12,X4>Inputs!$B$13),"Priority: margin + leakage",IF(V4<Inputs!$B$12,"Margin review",IF(X4>Inputs!$B$13,"Leakage review","Monitor"))) -> Priority: margin + leakage
A5: T-0002 | B5: 45759 | C5: Boreal Clinics | D5: Enterprise | E5: SKU-400 | F5: Premium Module | G5: 9 | H5: 420 | I5: 180 | J5: 0.13415605 | K5: 0.03826866 | L5: 0.020827729 | M5: 119.29779 | N5: =H5*(1-J5)*(1-K5) -> 349.73789 | O5: =G5*H5 -> 3780 | P5: =O5*J5 -> 507.10989 | Q5: =(O5-P5)*K5 -> 125.24912 | R5: =O5*L5 -> 78.728814 | S5: =G5*N5-R5-M5 -> 2949.6144 | T5: =G5*I5 -> 1620 | U5: =S5-T5 -> 1329.6144 | V5: =IFERROR(U5/S5,0) -> 0.45077567 | W5: =P5+Q5+R5+M5 -> 830.38561 | X5: =IFERROR(W5/O5,0) -> 0.21967873 | Y5: =IF(AND(V5<Inputs!$B$12,X5>Inputs!$B$13),"Priority: margin + leakage",IF(V5<Inputs!$B$12,"Margin review",IF(X5>Inputs!$B$13,"Leakage review","Monitor"))) -> Leakage review
A6: T-0003 | B6: 45739 | C6: Lakeside Clinics | D6: SMB | E6: SKU-400 | F6: Premium Module | G6: 33 | H6: 420 | I6: 180 | J6: 0.018165892 | K6: 0.04133329 | L6: 0.045683443 | M6: 8.8970712 | N6: =H6*(1-J6)*(1-K6) -> 395.3257 | O6: =G6*H6 -> 13860 | P6: =O6*J6 -> 251.77926 | Q6: =(O6-P6)*K6 -> 562.47254 | R6: =O6*L6 -> 633.17253 | S6: =G6*N6-R6-M6 -> 12403.679 | T6: =G6*I6 -> 5940 | U6: =S6-T6 -> 6463.6786 | V6: =IFERROR(U6/S6,0) -> 0.52110981 | W6: =P6+Q6+R6+M6 -> 1456.3214 | X6: =IFERROR(W6/O6,0) -> 0.10507369 | Y6: =IF(AND(V6<Inputs!$B$12,X6>Inputs!$B$13),"Priority: margin + leakage",IF(V6<Inputs!$B$12,"Margin review",IF(X6>Inputs!$B$13,"Leakage review","Monitor"))) -> Monitor
A7: T-0004 | B7: 45852 | C7: Lakeside Clinics | D7: SMB | E7: SKU-400 | F7: Premium Module | G7: 48 | H7: 420 | I7: 180 | J7: 0.040753521 | K7: 0.052143187 | L7: 0.025707848 | M7: 78.356897 | N7: =H7*(1-J7)*(1-K7) -> 381.87589 | O7: =G7*H7 -> 20160 | P7: =O7*J7 -> 821.59099 | Q7: =(O7-P7)*K7 -> 1008.3663 | R7: =O7*L7 -> 518.27022 | S7: =G7*N7-R7-M7 -> 17733.416 | T7: =G7*I7 -> 8640 | U7: =S7-T7 -> 9093.4156 | V7: =IFERROR(U7/S7,0) -> 0.51278422 | W7: =P7+Q7+R7+M7 -> 2426.5844 | X7: =IFERROR(W7/O7,0) -> 0.12036629 | Y7: =IF(AND(V7<Inputs!$B$12,X7>Inputs!$B$13),"Priority: margin + leakage",IF(V7<Inputs!$B$12,"Margin review",IF(X7>Inputs!$B$13,"Leakage review","Monitor"))) -> Leakage review
A8: T-0005 | B8: 45721 | C8: Boreal Clinics | D8: Enterprise | E8: SKU-310 | F8: Services | G8: 113 | H8: 260 | I8: 165 | J8: 0.094728033 | K8: 0.051280202 | L8: 0.044225527 | M8: 56.96248 | N8: =H8*(1-J8)*(1-K8) -> 223.30085 | O8: =G8*H8 -> 29380 | P8: =O8*J8 -> 2783.1096 | Q8: =(O8-P8)*K8 -> 1363.8939 | R8: =O8*L8 -> 1299.346 | S8: =G8*N8-R8-M8 -> 23876.688 | T8: =G8*I8 -> 18645 | U8: =S8-T8 -> 5231.688 | V8: =IFERROR(U8/S8,0) -> 0.2191128 | W8: =P8+Q8+R8+M8 -> 5503.312 | X8: =IFERROR(W8/O8,0) -> 0.18731491 | Y8: =IF(AND(V8<Inputs!$B$12,X8>Inputs!$B$13),"Priority: margin + leakage",IF(V8<Inputs!$B$12,"Margin review",IF(X8>Inputs!$B$13,"Leakage review","Monitor"))) -> Priority: margin + leakage
A9: T-0006 | B9: 45756 | C9: Granite Medical | D9: Mid-Market | E9: SKU-110 | F9: Core Platform | G9: 75 | H9: 160 | I9: 84 | J9: 0.061798204 | K9: 0.068901421 | L9: 0.037824634 | M9: 63.790487 | N9: =H9*(1-J9)*(1-K9) -> 139.76934 | O9: =G9*H9 -> 12000 | P9: =O9*J9 -> 741.57845 | Q9: =(O9-P9)*K9 -> 775.72124 | R9: =O9*L9 -> 453.89561 | S9: =G9*N9-R9-M9 -> 9965.0142 | T9: =G9*I9 -> 6300 | U9: =S9-T9 -> 3665.0142 | V9: =IFERROR(U9/S9,0) -> 0.36778816 | W9: =P9+Q9+R9+M9 -> 2034.9858 | X9: =IFERROR(W9/O9,0) -> 0.16958215 | Y9: =IF(AND(V9<Inputs!$B$12,X9>Inputs!$B$13),"Priority: margin + leakage",IF(V9<Inputs!$B$12,"Margin review",IF(X9>Inputs!$B$13,"Leakage review","Monitor"))) -> Leakage review
A10: T-0007 | B10: 45709 | C10: Lakeside Clinics | D10: SMB | E10: SKU-110 | F10: Core Platform | G10: 10 | H10: 160 | I10: 84 | J10: 0.013105668 | K10: 0 | L10: 0.060241356 | M10: 103.59097 | N10: =H10*(1-J10)*(1-K10) -> 157.90309 | O10: =G10*H10 -> 1600 | P10: =O10*J10 -> 20.969068 | Q10: =(O10-P10)*K10 -> 0 | R10: =O10*L10 -> 96.386169 | S10: =G10*N10-R10-M10 -> 1379.0538 | T10: =G10*I10 -> 840 | U10: =S10-T10 -> 539.05379 | V10: =IFERROR(U10/S10,0) -> 0.39088671 | W10: =P10+Q10+R10+M10 -> 220.94621 | X10: =IFERROR(W10/O10,0) -> 0.13809138 | Y10: =IF(AND(V10<Inputs!$B$12,X10>Inputs!$B$13),"Priority: margin + leakage",IF(V10<Inputs!$B$12,"Margin review",IF(X10>Inputs!$B$13,"Leakage review","Monitor"))) -> Leakage review
A11: T-0008 | B11: 45794 | C11: Granite Medical | D11: Mid-Market | E11: SKU-300 | F11: Services | G11: 63 | H11: 125 | I11: 78 | J11: 0.053055509 | K11: 0.017065723 | L11: 0.016540571 | M11: 64.973056 | N11: =H11*(1-J11)*(1-K11) -> 116.34802 | O11: =G11*H11 -> 7875 | P11: =O11*J11 -> 417.81213 | Q11: =(O11-P11)*K11 -> 127.2623 | R11: =O11*L11 -> 130.257 | S11: =G11*N11-R11-M11 -> 7134.6955 | T11: =G11*I11 -> 4914 | U11: =S11-T11 -> 2220.6955 | V11: =IFERROR(U11/S11,0) -> 0.31125302 | W11: =P11+Q11+R11+M11 -> 740.30448 | X11: =IFERROR(W11/O11,0) -> 0.094006919 | Y11: =IF(AND(V11<Inputs!$B$12,X11>Inputs!$B$13),"Priority: margin + leakage",IF(V11<Inputs!$B$12,"Margin review",IF(X11>Inputs!$B$13,"Leakage review","Monitor"))) -> Monitor
A12: T-0009 | B12: 45796 | C12: Lakeside Clinics | D12: SMB | E12: SKU-110 | F12: Core Platform | G12: 82 | H12: 160 | I12: 84 | J12: 0.016386813 | K12: 0.011824024 | L12: 0.025653596 | M12: 220.19723 | N12: =H12*(1-J12)*(1-K12) -> 155.51727 | O12: =G12*H12 -> 13120 | P12: =O12*J12 -> 214.99498 | Q12: =(O12-P12)*K12 -> 152.58909 | R12: =O12*L12 -> 336.57518 | S12: =G12*N12-R12-M12 -> 12195.644 | T12: =G12*I12 -> 6888 | U12: =S12-T12 -> 5307.6435 | V12: =IFERROR(U12/S12,0) -> 0.43520816 | W12: =P12+Q12+R12+M12 -> 924.35649 | X12: =IFERROR(W12/O12,0) -> 0.070454 | Y12: =IF(AND(V12<Inputs!$B$12,X12>Inputs!$B$13),"Priority: margin + leakage",IF(V12<Inputs!$B$12,"Margin review",IF(X12>Inputs!$B$13,"Leakage review","Monitor"))) -> Monitor
A13: T-0010 | B13: 45819 | C13: Keystone Health | D13: Enterprise | E13: SKU-210 | F13: Analytics | G13: 92 | H13: 310 | I13: 142 | J13: 0.083066321 | K13: 0.073181792 | L13: 0.05638842 | M13: 177.54966 | N13: =H13*(1-J13)*(1-K13) -> 263.44756 | O13: =G13*H13 -> 28520 | P13: =O13*J13 -> 2369.0515 | Q13: =(O13-P13)*K13 -> 1913.7733 | R13: =O13*L13 -> 1608.1977 | S13: =G13*N13-R13-M13 -> 22451.428 | T13: =G13*I13 -> 13064 | U13: =S13-T13 -> 9387.4279 | V13: =IFERROR(U13/S13,0) -> 0.41812164 | W13: =P13+Q13+R13+M13 -> 6068.5721 | X13: =IFERROR(W13/O13,0) -> 0.21278303 | Y13: =IF(AND(V13<Inputs!$B$12,X13>Inputs!$B$13),"Priority: margin + leakage",IF(V13<Inputs!$B$12,"Margin review",IF(X13>Inputs!$B$13,"Leakage review","Monitor"))) -> Leakage review
A14: T-0011 | B14: 45993 | C14: Granite Medical | D14: Mid-Market | E14: SKU-300 | F14: Services | G14: 13 | H14: 125 | I14: 78 | J14: 0.095327291 | K14: 0.093035213 | L14: 0.03615942 | M14: 20.623862 | N14: =H14*(1-J14)*(1-K14) -> 102.56329 | O14: =G14*H14 -> 1625 | P14: =O14*J14 -> 154.90685 | Q14: =(O14-P14)*K14 -> 136.77043 | R14: =O14*L14 -> 58.759057 | S14: =G14*N14-R14-M14 -> 1253.9398 | T14: =G14*I14 -> 1014 | U14: =S14-T14 -> 239.9398 | V14: =IFERROR(U14/S14,0) -> 0.19134874 | W14: =P14+Q14+R14+M14 -> 371.0602 | X14: =IFERROR(W14/O14,0) -> 0.22834474 | Y14: =IF(AND(V14<Inputs!$B$12,X14>Inputs!$B$13),"Priority: margin + leakage",IF(V14<Inputs!$B$12,"Margin review",IF(X14>Inputs!$B$13,"Leakage review","Monitor"))) -> Priority: margin + leakage
A15: T-0012 | B15: 45945 | C15: Harbor Care | D15: Enterprise | E15: SKU-400 | F15: Premium Module | G15: 118 | H15: 420 | I15: 180 | J15: 0.14332957 | K15: 0.020829179 | L15: 0.023735306 | M15: 187.43724 | N15: =H15*(1-J15)*(1-K15) -> 352.30721 | O15: =G15*H15 -> 49560 | P15: =O15*J15 -> 7103.4137 | Q15: =(O15-P15)*K15 -> 884.33584 | R15: =O15*L15 -> 1176.3218 | S15: =G15*N15-R15-M15 -> 40208.491 | T15: =G15*I15 -> 21240 | U15: =S15-T15 -> 18968.491 | V15: =IFERROR(U15/S15,0) -> 0.47175337 | W15: =P15+Q15+R15+M15 -> 9351.5086 | X15: =IFERROR(W15/O15,0) -> 0.18869065 | Y15: =IF(AND(V15<Inputs!$B$12,X15>Inputs!$B$13),"Priority: margin + leakage",IF(V15<Inputs!$B$12,"Margin review",IF(X15>Inputs!$B$13,"Leakage review","Monitor"))) -> Leakage review
... A123: T-0120 | B123: 45900 | C123: Lakeside Clinics | D123: SMB | E123: SKU-210 | F123: Analytics | G123: 78 | H123: 310 | I123: 142 | J123: 0 | K123: 0.068017365 | L123: 0.011657902 | M123: 161.88144 | N123: =H123*(1-J123)*(1-K123) -> 288.91462 | O123: =G123*H123 -> 24180 | P123: =O123*J123 -> 0 | Q123: =(O123-P123)*K123 -> 1644.6599 | R123: =O123*L123 -> 281.88807 | S123: =G123*N123-R123-M123 -> 22091.571 | T123: =G123*I123 -> 11076 | U123: =S123-T123 -> 11015.571 | V123: =IFERROR(U123/S123,0) -> 0.4986323 | W123: =P123+Q123+R123+M123 -> 2088.4294 | X123: =IFERROR(W123/O123,0) -> 0.086370116 | Y123: =IF(AND(V123<Inputs!$B$12,X123>Inputs!$B$13),"Priority: margin + leakage",IF(V123<Inputs!$B$12,"Margin review",IF(X123>Inputs!$B$13,"Leakage review","Monitor"))) -> Monitor

Sheet Waterfall
A1: Pricing Waterfall
A3: Waterfall Step | B3: Amount ($) | C3: % of Gross Revenue | D3: Formula / Interpretation
A4: Gross List Revenue | B4: =SUM(Customer_SKU_Data!O4:O123) -> 2168795 | C4: =B4/$B$4 -> 1 | D4: List price × units before discounts and leakage
A5: Contract Discounts | B5: =-SUM(Customer_SKU_Data!P4:P123) -> -188064.89 | C5: =B5/$B$4 -> -0.086714 | D5: Discounts embedded in contract terms
A6: Promo Discounts | B6: =-SUM(Customer_SKU_Data!Q4:Q123) -> -74462.767 | C6: =B6/$B$4 -> -0.034333705 | D6: Temporary or discretionary promotional discounts
A7: Rebates | B7: =-SUM(Customer_SKU_Data!R4:R123) -> -52033.697 | C7: =B7/$B$4 -> -0.023991985 | D7: Customer rebates and credits
A8: Freight Absorption | B8: =-SUM(Customer_SKU_Data!M4:M123) -> -12297.45 | C8: =B8/$B$4 -> -0.0056701764 | D8: Freight / shipping cost absorbed by seller
A9: Pocket Revenue | B9: =SUM(B4:B8) -> 1841936.2 | C9: =B9/$B$4 -> 0.84929013 | D9: Revenue retained after visible leakage
A10: Standard Cost | B10: =-SUM(Customer_SKU_Data!T4:T123) -> -1025129 | C10: =B10/$B$4 -> -0.47267215 | D10: Cost at transaction-level standard cost
A11: Pocket Gross Margin | B11: =B9+B10 -> 816807.2 | C11: =B11/$B$4 -> 0.37661798 | D11: Gross margin after pricing leakage and cost

Sheet Segmentation
A1: Customer Margin & Leakage Segmentation
A3: Customer | B3: Segment | C3: Transactions | D3: Units | E3: Gross Revenue ($) | F3: Net Revenue ($) | G3: Gross Margin ($) | H3: Pocket Margin % | I3: Total Leakage ($) | J3: Leakage Rate % | K3: Avg Contract Discount % | L3: Suggested Action
A4: Acme Health | B4: Enterprise | C4: =COUNTIF(Customer_SKU_Data!$C$4:$C$123,A4) -> 7 | D4: =SUMIF(Customer_SKU_Data!$C$4:$C$123,A4,Customer_SKU_Data!$G$4:$G$123) -> 468 | E4: =SUMIF(Customer_SKU_Data!$C$4:$C$123,A4,Customer_SKU_Data!$O$4:$O$123) -> 169175 | F4: =SUMIF(Customer_SKU_Data!$C$4:$C$123,A4,Customer_SKU_Data!$S$4:$S$123) -> 139013.69 | G4: =SUMIF(Customer_SKU_Data!$C$4:$C$123,A4,Customer_SKU_Data!$U$4:$U$123) -> 61179.693 | H4: =IFERROR(G4/F4,0) -> 0.44009832 | I4: =SUMIF(Customer_SKU_Data!$C$4:$C$123,A4,Customer_SKU_Data!$W$4:$W$123) -> 30161.307 | J4: =IFERROR(I4/E4,0) -> 0.17828466 | K4: =IFERROR(SUMIF(Customer_SKU_Data!$C$4:$C$123,A4,Customer_SKU_Data!$P$4:$P$123)/E4,0) -> 0.11060338 | L4: =IF(AND(H4<Inputs!$B$12,J4>Inputs!$B$13),"Priority pricing review",IF(H4<Inputs!$B$12,"Fix margin",IF(J4>Inputs!$B$13,"Reduce leakage","Monitor"))) -> Reduce leakage
A5: Boreal Clinics | B5: Enterprise | C5: =COUNTIF(Customer_SKU_Data!$C$4:$C$123,A5) -> 12 | D5: =SUMIF(Customer_SKU_Data!$C$4:$C$123,A5,Customer_SKU_Data!$G$4:$G$123) -> 908 | E5: =SUMIF(Customer_SKU_Data!$C$4:$C$123,A5,Customer_SKU_Data!$O$4:$O$123) -> 219825 | F5: =SUMIF(Customer_SKU_Data!$C$4:$C$123,A5,Customer_SKU_Data!$S$4:$S$123) -> 182246.55 | G5: =SUMIF(Customer_SKU_Data!$C$4:$C$123,A5,Customer_SKU_Data!$U$4:$U$123) -> 72933.551 | H5: =IFERROR(G5/F5,0) -> 0.40019167 | I5: =SUMIF(Customer_SKU_Data!$C$4:$C$123,A5,Customer_SKU_Data!$W$4:$W$123) -> 37578.449 | J5: =IFERROR(I5/E5,0) -> 0.17094711 | K5: =IFERROR(SUMIF(Customer_SKU_Data!$C$4:$C$123,A5,Customer_SKU_Data!$P$4:$P$123)/E5,0) -> 0.10818641 | L5: =IF(AND(H5<Inputs!$B$12,J5>Inputs!$B$13),"Priority pricing review",IF(H5<Inputs!$B$12,"Fix margin",IF(J5>Inputs!$B$13,"Reduce leakage","Monitor"))) -> Reduce leakage
A6: Cobalt Services | B6: Mid-Market | C6: =COUNTIF(Customer_SKU_Data!$C$4:$C$123,A6) -> 9 | D6: =SUMIF(Customer_SKU_Data!$C$4:$C$123,A6,Customer_SKU_Data!$G$4:$G$123) -> 690 | E6: =SUMIF(Customer_SKU_Data!$C$4:$C$123,A6,Customer_SKU_Data!$O$4:$O$123) -> 193075 | F6: =SUMIF(Customer_SKU_Data!$C$4:$C$123,A6,Customer_SKU_Data!$S$4:$S$123) -> 162236.4 | G6: =SUMIF(Customer_SKU_Data!$C$4:$C$123,A6,Customer_SKU_Data!$U$4:$U$123) -> 70523.402 | H6: =IFERROR(G6/F6,0) -> 0.4346953 | I6: =SUMIF(Customer_SKU_Data!$C$4:$C$123,A6,Customer_SKU_Data!$W$4:$W$123) -> 30838.598 | J6: =IFERROR(I6/E6,0) -> 0.15972341 | K6: =IFERROR(SUMIF(Customer_SKU_Data!$C$4:$C$123,A6,Customer_SKU_Data!$P$4:$P$123)/E6,0) -> 0.090058388 | L6: =IF(AND(H6<Inputs!$B$12,J6>Inputs!$B$13),"Priority pricing review",IF(H6<Inputs!$B$12,"Fix margin",IF(J6>Inputs!$B$13,"Reduce leakage","Monitor"))) -> Reduce leakage
A7: Delta Dental Group | B7: Enterprise | C7: =COUNTIF(Customer_SKU_Data!$C$4:$C$123,A7) -> 5 | D7: =SUMIF(Customer_SKU_Data!$C$4:$C$123,A7,Customer_SKU_Data!$G$4:$G$123) -> 389 | E7: =SUMIF(Customer_SKU_Data!$C$4:$C$123,A7,Customer_SKU_Data!$O$4:$O$123) -> 93000 | F7: =SUMIF(Customer_SKU_Data!$C$4:$C$123,A7,Customer_SKU_Data!$S$4:$S$123) -> 75029.644 | G7: =SUMIF(Customer_SKU_Data!$C$4:$C$123,A7,Customer_SKU_Data!$U$4:$U$123) -> 32307.644 | H7: =IFERROR(G7/F7,0) -> 0.43059839 | I7: =SUMIF(Customer_SKU_Data!$C$4:$C$123,A7,Customer_SKU_Data!$W$4:$W$123) -> 17970.356 | J7: =IFERROR(I7/E7,0) -> 0.19322964 | K7: =IFERROR(SUMIF(Customer_SKU_Data!$C$4:$C$123,A7,Customer_SKU_Data!$P$4:$P$123)/E7,0) -> 0.12974796 | L7: =IF(AND(H7<Inputs!$B$12,J7>Inputs!$B$13),"Priority pricing review",IF(H7<Inputs!$B$12,"Fix margin",IF(J7>Inputs!$B$13,"Reduce leakage","Monitor"))) -> Reduce leakage
A8: Evergreen Rehab | B8: Mid-Market | C8: =COUNTIF(Customer_SKU_Data!$C$4:$C$123,A8) -> 11 | D8: =SUMIF(Customer_SKU_Data!$C$4:$C$123,A8,Customer_SKU_Data!$G$4:$G$123) -> 807 | E8: =SUMIF(Customer_SKU_Data!$C$4:$C$123,A8,Customer_SKU_Data!$O$4:$O$123) -> 171175 | F8: =SUMIF(Customer_SKU_Data!$C$4:$C$123,A8,Customer_SKU_Data!$S$4:$S$123) -> 145921.45 | G8: =SUMIF(Customer_SKU_Data!$C$4:$C$123,A8,Customer_SKU_Data!$U$4:$U$123) -> 58745.451 | H8: =IFERROR(G8/F8,0) -> 0.4025827 | I8: =SUMIF(Customer_SKU_Data!$C$4:$C$123,A8,Customer_SKU_Data!$W$4:$W$123) -> 25253.549 | J8: =IFERROR(I8/E8,0) -> 0.14753059 | K8: =IFERROR(SUMIF(Customer_SKU_Data!$C$4:$C$123,A8,Customer_SKU_Data!$P$4:$P$123)/E8,0) -> 0.085916588 | L8: =IF(AND(H8<Inputs!$B$12,J8>Inputs!$B$13),"Priority pricing review",IF(H8<Inputs!$B$12,"Fix margin",IF(J8>Inputs!$B$13,"Reduce leakage","Monitor"))) -> Reduce leakage
A9: Fulton Labs | B9: SMB | C9: =COUNTIF(Customer_SKU_Data!$C$4:$C$123,A9) -> 10 | D9: =SUMIF(Customer_SKU_Data!$C$4:$C$123,A9,Customer_SKU_Data!$G$4:$G$123) -> 673 | E9: =SUMIF(Customer_SKU_Data!$C$4:$C$123,A9,Customer_SKU_Data!$O$4:$O$123) -> 157940 | F9: =SUMIF(Customer_SKU_Data!$C$4:$C$123,A9,Customer_SKU_Data!$S$4:$S$123) -> 143895.22 | G9: =SUMIF(Customer_SKU_Data!$C$4:$C$123,A9,Customer_SKU_Data!$U$4:$U$123) -> 66549.225 | H9: =IFERROR(G9/F9,0) -> 0.4624839 | I9: =SUMIF(Customer_SKU_Data!$C$4:$C$123,A9,Customer_SKU_Data!$W$4:$W$123) -> 14044.775 | J9: =IFERROR(I9/E9,0) -> 0.088924751 | K9: =IFERROR(SUMIF(Customer_SKU_Data!$C$4:$C$123,A9,Customer_SKU_Data!$P$4:$P$123)/E9,0) -> 0.023837262 | L9: =IF(AND(H9<Inputs!$B$12,J9>Inputs!$B$13),"Priority pricing review",IF(H9<Inputs!$B$12,"Fix margin",IF(J9>Inputs!$B$13,"Reduce leakage","Monitor"))) -> Monitor
A10: Granite Medical | B10: Mid-Market | C10: =COUNTIF(Customer_SKU_Data!$C$4:$C$123,A10) -> 10 | D10: =SUMIF(Customer_SKU_Data!$C$4:$C$123,A10,Customer_SKU_Data!$G$4:$G$123) -> 667 | E10: =SUMIF(Customer_SKU_Data!$C$4:$C$123,A10,Customer_SKU_Data!$O$4:$O$123) -> 146595 | F10: =SUMIF(Customer_SKU_Data!$C$4:$C$123,A10,Customer_SKU_Data!$S$4:$S$123) -> 127421.46 | G10: =SUMIF(Customer_SKU_Data!$C$4:$C$123,A10,Customer_SKU_Data!$U$4:$U$123) -> 57040.465 | H10: =IFERROR(G10/F10,0) -> 0.44765193 | I10: =SUMIF(Customer_SKU_Data!$C$4:$C$123,A10,Customer_SKU_Data!$W$4:$W$123) -> 19173.535 | J10: =IFERROR(I10/E10,0) -> 0.13079256 | K10: =IFERROR(SUMIF(Customer_SKU_Data!$C$4:$C$123,A10,Customer_SKU_Data!$P$4:$P$123)/E10,0) -> 0.071851654 | L10: =IF(AND(H10<Inputs!$B$12,J10>Inputs!$B$13),"Priority pricing review",IF(H10<Inputs!$B$12,"Fix margin",IF(J10>Inputs!$B$13,"Reduce leakage","Monitor"))) -> Reduce leakage
A11: Harbor Care | B11: Enterprise | C11: =COUNTIF(Customer_SKU_Data!$C$4:$C$123,A11) -> 9 | D11: =SUMIF(Customer_SKU_Data!$C$4:$C$123,A11,Customer_SKU_Data!$G$4:$G$123) -> 782 | E11: =SUMIF(Customer_SKU_Data!$C$4:$C$123,A11,Customer_SKU_Data!$O$4:$O$123) -> 267430 | F11: =SUMIF(Customer_SKU_Data!$C$4:$C$123,A11,Customer_SKU_Data!$S$4:$S$123) -> 217953.66 | G11: =SUMIF(Customer_SKU_Data!$C$4:$C$123,A11,Customer_SKU_Data!$U$4:$U$123) -> 101141.66 | H11: =IFERROR(G11/F11,0) -> 0.46405121 | I11: =SUMIF(Customer_SKU_Data!$C$4:$C$123,A11,Customer_SKU_Data!$W$4:$W$123) -> 49476.342 | J11: =IFERROR(I11/E11,0) -> 0.1850067 | K11: =IFERROR(SUMIF(Customer_SKU_Data!$C$4:$C$123,A11,Customer_SKU_Data!$P$4:$P$123)/E11,0) -> 0.120619 | L11: =IF(AND(H11<Inputs!$B$12,J11>Inputs!$B$13),"Priority pricing review",IF(H11<Inputs!$B$12,"Fix margin",IF(J11>Inputs!$B$13,"Reduce leakage","Monitor"))) -> Reduce leakage
A12: Ironwood Ops | B12: SMB | C12: =COUNTIF(Customer_SKU_Data!$C$4:$C$123,A12) -> 11 | D12: =SUMIF(Customer_SKU_Data!$C$4:$C$123,A12,Customer_SKU_Data!$G$4:$G$123) -> 763 | E12: =SUMIF(Customer_SKU_Data!$C$4:$C$123,A12,Customer_SKU_Data!$O$4:$O$123) -> 175590 | F12: =SUMIF(Customer_SKU_Data!$C$4:$C$123,A12,Customer_SKU_Data!$S$4:$S$123) -> 156072.07 | G12: =SUMIF(Customer_SKU_Data!$C$4:$C$123,A12,Customer_SKU_Data!$U$4:$U$123) -> 72895.066 | H12: =IFERROR(G12/F12,0) -> 0.4670603 | I12: =SUMIF(Customer_SKU_Data!$C$4:$C$123,A12,Customer_SKU_Data!$W$4:$W$123) -> 19517.934 | J12: =IFERROR(I12/E12,0) -> 0.11115629 | K12: =IFERROR(SUMIF(Customer_SKU_Data!$C$4:$C$123,A12,Customer_SKU_Data!$P$4:$P$123)/E12,0) -> 0.045061799 | L12: =IF(AND(H12<Inputs!$B$12,J12>Inputs!$B$13),"Priority pricing review",IF(H12<Inputs!$B$12,"Fix margin",IF(J12>Inputs!$B$13,"Reduce leakage","Monitor"))) -> Monitor
A13: Juniper Partners | B13: Mid-Market | C13: =COUNTIF(Customer_SKU_Data!$C$4:$C$123,A13) -> 15 | D13: =SUMIF(Customer_SKU_Data!$C$4:$C$123,A13,Customer_SKU_Data!$G$4:$G$123) -> 871 | E13: =SUMIF(Customer_SKU_Data!$C$4:$C$123,A13,Customer_SKU_Data!$O$4:$O$123) -> 299775 | F13: =SUMIF(Customer_SKU_Data!$C$4:$C$123,A13,Customer_SKU_Data!$S$4:$S$123) -> 258855.01 | G13: =SUMIF(Customer_SKU_Data!$C$4:$C$123,A13,Customer_SKU_Data!$U$4:$U$123) -> 122816.01 | H13: =IFERROR(G13/F13,0) -> 0.4744587 | I13: =SUMIF(Customer_SKU_Data!$C$4:$C$123,A13,Customer_SKU_Data!$W$4:$W$123) -> 40919.989 | J13: =IFERROR(I13/E13,0) -> 0.13650234 | K13: =IFERROR(SUMIF(Customer_SKU_Data!$C$4:$C$123,A13,Customer_SKU_Data!$P$4:$P$123)/E13,0) -> 0.088842973 | L13: =IF(AND(H13<Inputs!$B$12,J13>Inputs!$B$13),"Priority pricing review",IF(H13<Inputs!$B$12,"Fix margin",IF(J13>Inputs!$B$13,"Reduce leakage","Monitor"))) -> Reduce leakage
A14: Keystone Health | B14: Enterprise | C14: =COUNTIF(Customer_SKU_Data!$C$4:$C$123,A14) -> 11 | D14: =SUMIF(Customer_SKU_Data!$C$4:$C$123,A14,Customer_SKU_Data!$G$4:$G$123) -> 611 | E14: =SUMIF(Customer_SKU_Data!$C$4:$C$123,A14,Customer_SKU_Data!$O$4:$O$123) -> 129260 | F14: =SUMIF(Customer_SKU_Data!$C$4:$C$123,A14,Customer_SKU_Data!$S$4:$S$123) -> 104736.6 | G14: =SUMIF(Customer_SKU_Data!$C$4:$C$123,A14,Customer_SKU_Data!$U$4:$U$123) -> 38003.6 | H14: =IFERROR(G14/F14,0) -> 0.36284928 | I14: =SUMIF(Customer_SKU_Data!$C$4:$C$123,A14,Customer_SKU_Data!$W$4:$W$123) -> 24523.4 | J14: =IFERROR(I14/E14,0) -> 0.18972149 | K14: =IFERROR(SUMIF(Customer_SKU_Data!$C$4:$C$123,A14,Customer_SKU_Data!$P$4:$P$123)/E14,0) -> 0.1165965 | L14: =IF(AND(H14<Inputs!$B$12,J14>Inputs!$B$13),"Priority pricing review",IF(H14<Inputs!$B$12,"Fix margin",IF(J14>Inputs!$B$13,"Reduce leakage","Monitor"))) -> Reduce leakage
A15: Lakeside Clinics | B15: SMB | C15: =COUNTIF(Customer_SKU_Data!$C$4:$C$123,A15) -> 10 | D15: =SUMIF(Customer_SKU_Data!$C$4:$C$123,A15,Customer_SKU_Data!$G$4:$G$123) -> 497 | E15: =SUMIF(Customer_SKU_Data!$C$4:$C$123,A15,Customer_SKU_Data!$O$4:$O$123) -> 145955 | F15: =SUMIF(Customer_SKU_Data!$C$4:$C$123,A15,Customer_SKU_Data!$S$4:$S$123) -> 128554.43 | G15: =SUMIF(Customer_SKU_Data!$C$4:$C$123,A15,Customer_SKU_Data!$U$4:$U$123) -> 62671.429 | H15: =IFERROR(G15/F15,0) -> 0.48750891 | I15: =SUMIF(Customer_SKU_Data!$C$4:$C$123,A15,Customer_SKU_Data!$W$4:$W$123) -> 17400.571 | J15: =IFERROR(I15/E15,0) -> 0.11921874 | K15: =IFERROR(SUMIF(Customer_SKU_Data!$C$4:$C$123,A15,Customer_SKU_Data!$P$4:$P$123)/E15,0) -> 0.035891022 | L15: =IF(AND(H15<Inputs!$B$12,J15>Inputs!$B$13),"Priority pricing review",IF(H15<Inputs!$B$12,"Fix margin",IF(J15>Inputs!$B$13,"Reduce leakage","Monitor"))) -> Monitor

Sheet Scenarios
A1: Pricing Upside Scenarios
A3: Scenario | B3: Price Increase | C3: Volume Retention | D3: Discount Recapture | E3: Rebate Reduction | F3: Freight Recovery | G3: Incremental EBITDA ($) | H3: Enterprise Value Impact ($)
A4: Conservative | B4: 0.01 | C4: 0.995 | D4: 0.1 | E4: 0.05 | F4: 0.15 | G4: =((SUM(Customer_SKU_Data!S4:S123)*B4*C4)+(SUM(Customer_SKU_Data!P4:Q123)*D4*C4)+(SUM(Customer_SKU_Data!R4:R123)*E4*C4)+(SUM(Customer_SKU_Data!M4:M123)*F4))*Inputs!$B$10 -> 43993.855 | H4: =G4*Inputs!$B$11 -> 527926.26
A5: Base Case | B5: 0.025 | C5: 0.985 | D5: 0.2 | E5: 0.15 | F5: 0.35 | G5: =((SUM(Customer_SKU_Data!S5:S124)*B5*C5)+(SUM(Customer_SKU_Data!P5:Q124)*D5*C5)+(SUM(Customer_SKU_Data!R5:R124)*E5*C5)+(SUM(Customer_SKU_Data!M5:M124)*F5))*Inputs!$B$10 -> 98059.257 | H5: =G5*Inputs!$B$11 -> 1176711.1
A6: Upside | B6: 0.04 | C6: 0.97 | D6: 0.3 | E6: 0.2 | F6: 0.45 | G6: =((SUM(Customer_SKU_Data!S6:S125)*B6*C6)+(SUM(Customer_SKU_Data!P6:Q125)*D6*C6)+(SUM(Customer_SKU_Data!R6:R125)*E6*C6)+(SUM(Customer_SKU_Data!M6:M125)*F6))*Inputs!$B$10 -> 146669.07 | H6: =G6*Inputs!$B$11 -> 1760028.8
A7: Aggressive | B7: 0.06 | C7: 0.95 | D7: 0.4 | E7: 0.3 | F7: 0.6 | G7: =((SUM(Customer_SKU_Data!S7:S126)*B7*C7)+(SUM(Customer_SKU_Data!P7:Q126)*D7*C7)+(SUM(Customer_SKU_Data!R7:R126)*E7*C7)+(SUM(Customer_SKU_Data!M7:M126)*F7))*Inputs!$B$10 -> 202535.04 | H7: =G7*Inputs!$B$11 -> 2430420.5
A10: Price Increase / Volume Retention Sensitivity
A11: EBITDA $ | B11: 0.94 | C11: 0.96 | D11: 0.98 | E11: 1 | F11: 1.02
A12: 0.01 | B12: =((SUM(Customer_SKU_Data!S4:S123)*$A12*B$11)+(SUM(Customer_SKU_Data!P4:Q123)*Inputs!$B$6*B$11)+(SUM(Customer_SKU_Data!R4:R123)*Inputs!$B$8*B$11)+(SUM(Customer_SKU_Data!M4:M123)*Inputs!$B$9))*Inputs!$B$10 -> 70479.233 | C12: =((SUM(Customer_SKU_Data!S4:S123)*$A12*C$11)+(SUM(Customer_SKU_Data!P4:Q123)*Inputs!$B$6*C$11)+(SUM(Customer_SKU_Data!R4:R123)*Inputs!$B$8*C$11)+(SUM(Customer_SKU_Data!M4:M123)*Inputs!$B$9))*Inputs!$B$10 -> 71896.372 | D12: =((SUM(Customer_SKU_Data!S4:S123)*$A12*D$11)+(SUM(Customer_SKU_Data!P4:Q123)*Inputs!$B$6*D$11)+(SUM(Customer_SKU_Data!R4:R123)*Inputs!$B$8*D$11)+(SUM(Customer_SKU_Data!M4:M123)*Inputs!$B$9))*Inputs!$B$10 -> 73313.511 | E12: =((SUM(Customer_SKU_Data!S4:S123)*$A12*E$11)+(SUM(Customer_SKU_Data!P4:Q123)*Inputs!$B$6*E$11)+(SUM(Customer_SKU_Data!R4:R123)*Inputs!$B$8*E$11)+(SUM(Customer_SKU_Data!M4:M123)*Inputs!$B$9))*Inputs!$B$10 -> 74730.65 | F12: =((SUM(Customer_SKU_Data!S4:S123)*$A12*F$11)+(SUM(Customer_SKU_Data!P4:Q123)*Inputs!$B$6*F$11)+(SUM(Customer_SKU_Data!R4:R123)*Inputs!$B$8*F$11)+(SUM(Customer_SKU_Data!M4:M123)*Inputs!$B$9))*Inputs!$B$10 -> 76147.789
A13: 0.02 | B13: =((SUM(Customer_SKU_Data!S4:S123)*$A13*B$11)+(SUM(Customer_SKU_Data!P4:Q123)*Inputs!$B$6*B$11)+(SUM(Customer_SKU_Data!R4:R123)*Inputs!$B$8*B$11)+(SUM(Customer_SKU_Data!M4:M123)*Inputs!$B$9))*Inputs!$B$10 -> 86062.013 | C13: =((SUM(Customer_SKU_Data!S4:S123)*$A13*C$11)+(SUM(Customer_SKU_Data!P4:Q123)*Inputs!$B$6*C$11)+(SUM(Customer_SKU_Data!R4:R123)*Inputs!$B$8*C$11)+(SUM(Customer_SKU_Data!M4:M123)*Inputs!$B$9))*Inputs!$B$10 -> 87810.701 | D13: =((SUM(Customer_SKU_Data!S4:S123)*$A13*D$11)+(SUM(Customer_SKU_Data!P4:Q123)*Inputs!$B$6*D$11)+(SUM(Customer_SKU_Data!R4:R123)*Inputs!$B$8*D$11)+(SUM(Customer_SKU_Data!M4:M123)*Inputs!$B$9))*Inputs!$B$10 -> 89559.388 | E13: =((SUM(Customer_SKU_Data!S4:S123)*$A13*E$11)+(SUM(Customer_SKU_Data!P4:Q123)*Inputs!$B$6*E$11)+(SUM(Customer_SKU_Data!R4:R123)*Inputs!$B$8*E$11)+(SUM(Customer_SKU_Data!M4:M123)*Inputs!$B$9))*Inputs!$B$10 -> 91308.076 | F13: =((SUM(Customer_SKU_Data!S4:S123)*$A13*F$11)+(SUM(Customer_SKU_Data!P4:Q123)*Inputs!$B$6*F$11)+(SUM(Customer_SKU_Data!R4:R123)*Inputs!$B$8*F$11)+(SUM(Customer_SKU_Data!M4:M123)*Inputs!$B$9))*Inputs!$B$10 -> 93056.763
A14: 0.03 | B14: =((SUM(Customer_SKU_Data!S4:S123)*$A14*B$11)+(SUM(Customer_SKU_Data!P4:Q123)*Inputs!$B$6*B$11)+(SUM(Customer_SKU_Data!R4:R123)*Inputs!$B$8*B$11)+(SUM(Customer_SKU_Data!M4:M123)*Inputs!$B$9))*Inputs!$B$10 -> 101644.79 | C14: =((SUM(Customer_SKU_Data!S4:S123)*$A14*C$11)+(SUM(Customer_SKU_Data!P4:Q123)*Inputs!$B$6*C$11)+(SUM(Customer_SKU_Data!R4:R123)*Inputs!$B$8*C$11)+(SUM(Customer_SKU_Data!M4:M123)*Inputs!$B$9))*Inputs!$B$10 -> 103725.03 | D14: =((SUM(Customer_SKU_Data!S4:S123)*$A14*D$11)+(SUM(Customer_SKU_Data!P4:Q123)*Inputs!$B$6*D$11)+(SUM(Customer_SKU_Data!R4:R123)*Inputs!$B$8*D$11)+(SUM(Customer_SKU_Data!M4:M123)*Inputs!$B$9))*Inputs!$B$10 -> 105805.27 | E14: =((SUM(Customer_SKU_Data!S4:S123)*$A14*E$11)+(SUM(Customer_SKU_Data!P4:Q123)*Inputs!$B$6*E$11)+(SUM(Customer_SKU_Data!R4:R123)*Inputs!$B$8*E$11)+(SUM(Customer_SKU_Data!M4:M123)*Inputs!$B$9))*Inputs!$B$10 -> 107885.5 | F14: =((SUM(Customer_SKU_Data!S4:S123)*$A14*F$11)+(SUM(Customer_SKU_Data!P4:Q123)*Inputs!$B$6*F$11)+(SUM(Customer_SKU_Data!R4:R123)*Inputs!$B$8*F$11)+(SUM(Customer_SKU_Data!M4:M123)*Inputs!$B$9))*Inputs!$B$10 -> 109965.74
A15: 0.04 | B15: =((SUM(Customer_SKU_Data!S4:S123)*$A15*B$11)+(SUM(Customer_SKU_Data!P4:Q123)*Inputs!$B$6*B$11)+(SUM(Customer_SKU_Data!R4:R123)*Inputs!$B$8*B$11)+(SUM(Customer_SKU_Data!M4:M123)*Inputs!$B$9))*Inputs!$B$10 -> 117227.57 | C15: =((SUM(Customer_SKU_Data!S4:S123)*$A15*C$11)+(SUM(Customer_SKU_Data!P4:Q123)*Inputs!$B$6*C$11)+(SUM(Customer_SKU_Data!R4:R123)*Inputs!$B$8*C$11)+(SUM(Customer_SKU_Data!M4:M123)*Inputs!$B$9))*Inputs!$B$10 -> 119639.36 | D15: =((SUM(Customer_SKU_Data!S4:S123)*$A15*D$11)+(SUM(Customer_SKU_Data!P4:Q123)*Inputs!$B$6*D$11)+(SUM(Customer_SKU_Data!R4:R123)*Inputs!$B$8*D$11)+(SUM(Customer_SKU_Data!M4:M123)*Inputs!$B$9))*Inputs!$B$10 -> 122051.14 | E15: =((SUM(Customer_SKU_Data!S4:S123)*$A15*E$11)+(SUM(Customer_SKU_Data!P4:Q123)*Inputs!$B$6*E$11)+(SUM(Customer_SKU_Data!R4:R123)*Inputs!$B$8*E$11)+(SUM(Customer_SKU_Data!M4:M123)*Inputs!$B$9))*Inputs!$B$10 -> 124462.93 | F15: =((SUM(Customer_SKU_Data!S4:S123)*$A15*F$11)+(SUM(Customer_SKU_Data!P4:Q123)*Inputs!$B$6*F$11)+(SUM(Customer_SKU_Data!R4:R123)*Inputs!$B$8*F$11)+(SUM(Customer_SKU_Data!M4:M123)*Inputs!$B$9))*Inputs!$B$10 -> 126874.71
A16: 0.05 | B16: =((SUM(Customer_SKU_Data!S4:S123)*$A16*B$11)+(SUM(Customer_SKU_Data!P4:Q123)*Inputs!$B$6*B$11)+(SUM(Customer_SKU_Data!R4:R123)*Inputs!$B$8*B$11)+(SUM(Customer_SKU_Data!M4:M123)*Inputs!$B$9))*Inputs!$B$10 -> 132810.35 | C16: =((SUM(Customer_SKU_Data!S4:S123)*$A16*C$11)+(SUM(Customer_SKU_Data!P4:Q123)*Inputs!$B$6*C$11)+(SUM(Customer_SKU_Data!R4:R123)*Inputs!$B$8*C$11)+(SUM(Customer_SKU_Data!M4:M123)*Inputs!$B$9))*Inputs!$B$10 -> 135553.69 | D16: =((SUM(Customer_SKU_Data!S4:S123)*$A16*D$11)+(SUM(Customer_SKU_Data!P4:Q123)*Inputs!$B$6*D$11)+(SUM(Customer_SKU_Data!R4:R123)*Inputs!$B$8*D$11)+(SUM(Customer_SKU_Data!M4:M123)*Inputs!$B$9))*Inputs!$B$10 -> 138297.02 | E16: =((SUM(Customer_SKU_Data!S4:S123)*$A16*E$11)+(SUM(Customer_SKU_Data!P4:Q123)*Inputs!$B$6*E$11)+(SUM(Customer_SKU_Data!R4:R123)*Inputs!$B$8*E$11)+(SUM(Customer_SKU_Data!M4:M123)*Inputs!$B$9))*Inputs!$B$10 -> 141040.35 | F16: =((SUM(Customer_SKU_Data!S4:S123)*$A16*F$11)+(SUM(Customer_SKU_Data!P4:Q123)*Inputs!$B$6*F$11)+(SUM(Customer_SKU_Data!R4:R123)*Inputs!$B$8*F$11)+(SUM(Customer_SKU_Data!M4:M123)*Inputs!$B$9))*Inputs!$B$10 -> 143783.69
