Workbook

Sheet Dashboard
A1: Ops2EBITDA · Customer Retention / NRR Cohort Model
A2: Diagnose GRR, NRR, logo churn, expansion, renewal risk, and retention-driven EBITDA impact.
A4: Beginning ARR | D4: Ending ARR | G4: GRR | J4: NRR
A5: =SUM(Customer_MRR_Data!$H:$H) -> 6395000 | D5: =SUM(Customer_MRR_Data!$I:$I) -> 5826000 | G5: =SUM(Customer_MRR_Data!$M:$M)/SUM(Customer_MRR_Data!$H:$H) -> 0.87724785 | J5: =SUM(Customer_MRR_Data!$N:$N)/SUM(Customer_MRR_Data!$H:$H) -> 0.91102424
A8: Logo Retention | D8: At-Risk ARR | G8: Churned ARR | J8: Base EV Upside
A9: =COUNTIFS(Customer_MRR_Data!$Q:$Q,"Active")/COUNTA(Customer_MRR_Data!$A$2:$A$37) -> 0.83333333 | D9: =SUMIFS(Customer_MRR_Data!$H:$H,Customer_MRR_Data!$W:$W,"High") -> 924000 | G9: =SUM(Customer_MRR_Data!$L:$L) -> 707000 | J9: =Scenarios!H6 -> 2148720
A12: At-Risk Renewal Priorities
A13: Rank | B13: Customer | C13: Segment | D13: CSM | E13: Renewal Date | F13: Health | G13: Usage | H13: ARR at Risk | I13: Risk | J13: Action
A14: =Renewal_Risk!A5 -> 1 | B14: =Renewal_Risk!B5 -> Apex Claims | C14: =Renewal_Risk!C5 -> Mid-Market | D14: =Renewal_Risk!D5 -> Maya Singh | E14: =Renewal_Risk!E5 -> 46231 | F14: =Renewal_Risk!F5 -> 52 | G14: =Renewal_Risk!G5 -> 0.41 | H14: =Renewal_Risk!H5 -> 132000 | ... J14: =Renewal_Risk!J5 -> Executive save plan + adoption intervention
A15: =Renewal_Risk!A6 -> 2 | B15: =Renewal_Risk!B6 -> Horizon Parts | C15: =Renewal_Risk!C6 -> Mid-Market | D15: =Renewal_Risk!D6 -> Nora Patel | E15: =Renewal_Risk!E6 -> 46081 | F15: =Renewal_Risk!F6 -> 55 | G15: =Renewal_Risk!G6 -> 0.42 | H15: =Renewal_Risk!H6 -> 142000 | ... J15: =Renewal_Risk!J6 -> Executive save plan + adoption intervention
A16: =Renewal_Risk!A7 -> 3 | B16: =Renewal_Risk!B7 -> Cedar Logistics | C16: =Renewal_Risk!C7 -> Enterprise | D16: =Renewal_Risk!D7 -> Jordan Chen | E16: =Renewal_Risk!E7 -> 46241 | F16: =Renewal_Risk!F7 -> 61 | G16: =Renewal_Risk!G7 -> 0.49 | H16: =Renewal_Risk!H7 -> 310000 | ... J16: =Renewal_Risk!J7 -> Executive save plan + adoption intervention
A17: =Renewal_Risk!A8 -> 4 | B17: =Renewal_Risk!B8 -> Pioneer Freight | C17: =Renewal_Risk!C8 -> Enterprise | D17: =Renewal_Risk!D8 -> Nora Patel | E17: =Renewal_Risk!E8 -> 46285 | F17: =Renewal_Risk!F8 -> 54 | G17: =Renewal_Risk!G8 -> 0.39 | H17: =Renewal_Risk!H8 -> 340000 | ... J17: =Renewal_Risk!J8 -> Executive save plan + adoption intervention
A18: =Renewal_Risk!A9 -> 5 | B18: =Renewal_Risk!B9 -> Union Billing | C18: =Renewal_Risk!C9 -> SMB | D18: =Renewal_Risk!D9 -> Leo Park | E18: =Renewal_Risk!E9 -> 46078 | F18: =Renewal_Risk!F9 -> 59 | G18: =Renewal_Risk!G9 -> 0.46 | H18: =Renewal_Risk!H9 -> 66000 | ... J18: =Renewal_Risk!J9 -> CSM action plan before renewal
A19: =Renewal_Risk!A10 -> 6 | B19: =Renewal_Risk!B10 -> BlueRiver Health | C19: =Renewal_Risk!C10 -> Mid-Market | D19: =Renewal_Risk!D10 -> Maya Singh | E19: =Renewal_Risk!E10 -> 46209 | F19: =Renewal_Risk!F10 -> 68 | G19: =Renewal_Risk!G10 -> 0.58 | H19: =Renewal_Risk!H10 -> 155000 | ... J19: =Renewal_Risk!J10 -> CSM action plan before renewal
A20: =Renewal_Risk!A11 -> 7 | B20: =Renewal_Risk!B11 -> Keystone Plastics | C20: =Renewal_Risk!C11 -> Enterprise | D20: =Renewal_Risk!D11 -> Jordan Chen | E20: =Renewal_Risk!E11 -> 46127 | F20: =Renewal_Risk!F11 -> 66 | G20: =Renewal_Risk!G11 -> 0.56 | H20: =Renewal_Risk!H11 -> 260000 | ... J20: =Renewal_Risk!J11 -> CSM action plan before renewal
A21: =Renewal_Risk!A12 -> 8 | B21: =Renewal_Risk!B12 -> Yardline Medical | C21: =Renewal_Risk!C12 -> SMB | D21: =Renewal_Risk!D12 -> Leo Park | E21: =Renewal_Risk!E12 -> 46170 | F21: =Renewal_Risk!F12 -> 64 | G21: =Renewal_Risk!G12 -> 0.55 | H21: =Renewal_Risk!H12 -> 52000 | ... J21: =Renewal_Risk!J12 -> CSM action plan before renewal
A22: =Renewal_Risk!A13 -> 9 | B22: =Renewal_Risk!B13 -> Ivy Claims | C22: =Renewal_Risk!C13 -> SMB | D22: =Renewal_Risk!D13 -> Leo Park | E22: =Renewal_Risk!E13 -> 46109 | F22: =Renewal_Risk!F13 -> 67 | G22: =Renewal_Risk!G13 -> 0.54 | H22: =Renewal_Risk!H13 -> 45000 | ... J22: =Renewal_Risk!J13 -> CSM action plan before renewal
A23: =Renewal_Risk!A14 -> 10 | B23: =Renewal_Risk!B14 -> Lakeview Supply | C23: =Renewal_Risk!C14 -> SMB | D23: =Renewal_Risk!D14 -> Leo Park | E23: =Renewal_Risk!E14 -> 46158 | F23: =Renewal_Risk!F14 -> 69 | G23: =Renewal_Risk!G14 -> 0.57 | H23: =Renewal_Risk!H14 -> 54000 | ... J23: =Renewal_Risk!J14 -> CSM action plan before renewal

Sheet Instructions
A1: How to Use This Model
A2: Workflow, data requirements, and interpretation guide.
A4: Step | B4: Action | C4: Notes
A5: 1 | B5: Replace sample customer data | C5: Paste customer-level ARR / MRR, renewal, health, support, and churn data into Customer_MRR_Data.
A6: 2 | B6: Review Inputs | C6: Update target NRR, contribution margin, exit multiple, and risk thresholds on Inputs.
A7: 3 | B7: Read retention output | C7: Use Cohort_Retention, NRR_Bridge, and Churn_Analysis to diagnose where retention leakage lives.
A8: 4 | B8: Prioritize accounts | C8: Use Renewal_Risk and Dashboard to identify high-risk ARR and recommended save actions.
A9: 5 | B9: Size value impact | C9: Use Scenarios and EBITDA_Impact to translate retention improvement into EBITDA and enterprise value impact.
A10: 6 | B10: Turn into management actions | C10: Move high-risk accounts into a customer success save plan with owners, dates, and weekly review cadence.

Sheet Inputs
A1: Ops2EBITDA · Customer Retention / NRR Cohort Model
A2: Editable assumptions for retention, churn, expansion, and valuation impact.
A4: Assumption | B4: Value | C4: Units / Notes | E4: Validation Lists | F4: Values
A5: Analysis Start Date | B5: 46023 | C5: Start of performance period | E5: Segment | F5: Enterprise
A6: Analysis End Date | B6: 46387 | C6: End of performance period | E6: Segment | F6: Mid-Market
A7: Target NRR | B7: 1.08 | C7: Management case target | E7: Segment | F7: SMB
A8: Target GRR | B8: 0.92 | C8: Gross retention target | E8: Region | F8: North America
A9: Contribution Margin | B9: 0.7 | C9: Incremental ARR drop-through to EBITDA | E9: Region | F9: EMEA
A10: Exit Multiple | B10: 12 | C10: EBITDA multiple | E10: Region | F10: APAC
A11: High Risk Health Score Threshold | B11: 55 | C11: Below threshold = high risk | E11: Logo Status | F11: Active
A12: Medium Risk Health Score Threshold | B12: 70 | C12: Below threshold = medium risk | E12: Logo Status | F12: Churned
A13: High Risk Usage Threshold | B13: 0.4 | C13: Below threshold = high risk | E13: Risk | F13: Low
A14: Medium Risk Usage Threshold | B14: 0.6 | C14: Below threshold = medium risk | E14: Risk | F14: Medium
A15: High Ticket Threshold | B15: 12 | C15: Above threshold = high risk | E15: Risk | F15: High
A16: Medium Ticket Threshold | B16: 8 | C16: Above threshold = medium risk | E16: Risk | F16: Lost
A17: Renewal Window Days | B17: 90 | C17: Renewals inside window get risk premium

Sheet Customer_MRR_Data
A1: Customer_ID | B1: Customer | C1: Cohort_Month | D1: Segment | E1: Industry | F1: Region | G1: CSM | H1: Beginning_ARR_$ | I1: Ending_ARR_$ | J1: Expansion_$ | K1: Contraction_$ | L1: Churned_ARR_$ | M1: Gross_Retained_ARR_$ | N1: Net_Retained_ARR_$ | O1: GRR_% | P1: NRR_% | Q1: Logo_Status | R1: Churn_Reason | S1: Renewal_Date | T1: Health_Score | U1: Usage_% | V1: Support_Tickets | W1: Renewal_Risk | X1: Recommended_Action | Y1: Priority_Score
A2: C001 | B2: Atlas Industrial | C2: 46023 | D2: Enterprise | E2: Manufacturing | F2: North America | G2: Jordan Chen | H2: 240000 | I2: 240000 | J2: 0 | K2: 0 | L2: 0 | M2: =MAX(H2-L2-K2,0) -> 240000 | N2: =M2+J2 -> 240000 | O2: =IFERROR(M2/H2,0) -> 1 | P2: =IFERROR(N2/H2,0) -> 1 | Q2: Active | R2: No Churn | S2: 46178 | T2: 82 | U2: 0.78 | V2: 3 | W2: =IF(Q2="Churned","Lost",IF(OR(T2<Inputs!$B$11,U2<Inputs!$B$13,V2>Inputs!$B$15),"High",IF(OR(T2<Inputs!$B$12,U2<Inputs!$B$14,V2>Inputs!$B$16),"Medium","Low"))) -> Low | X2: =IF(W2="Lost","Document root cause and replace ARR",IF(W2="High","Executive save plan + adoption intervention",IF(W2="Medium","CSM action plan before renewal","Monitor / expansion candidate"))) -> Monitor / expansion candidate | Y2: =IF(W2="Lost",0,(100-T2)*0.35+(1-U2)*100*0.3+V2*2+IF(S2-TODAY()<=Inputs!$B$17,20,0)+IF(W2="High",25,IF(W2="Medium",10,0))) -> 38.9
A3: C002 | B3: BlueRiver Health | C3: 46054 | D3: Mid-Market | E3: Healthcare | F3: North America | G3: Maya Singh | H3: 155000 | I3: 154000 | J3: 5000 | K3: 6000 | L3: 0 | M3: =MAX(H3-L3-K3,0) -> 149000 | N3: =M3+J3 -> 154000 | O3: =IFERROR(M3/H3,0) -> 0.96129032 | P3: =IFERROR(N3/H3,0) -> 0.99354839 | Q3: Active | R3: No Churn | S3: 46209 | T3: 68 | U3: 0.58 | V3: 9 | W3: =IF(Q3="Churned","Lost",IF(OR(T3<Inputs!$B$11,U3<Inputs!$B$13,V3>Inputs!$B$15),"High",IF(OR(T3<Inputs!$B$12,U3<Inputs!$B$14,V3>Inputs!$B$16),"Medium","Low"))) -> Medium | X3: =IF(W3="Lost","Document root cause and replace ARR",IF(W3="High","Executive save plan + adoption intervention",IF(W3="Medium","CSM action plan before renewal","Monitor / expansion candidate"))) -> CSM action plan before renewal | Y3: =IF(W3="Lost",0,(100-T3)*0.35+(1-U3)*100*0.3+V3*2+IF(S3-TODAY()<=Inputs!$B$17,20,0)+IF(W3="High",25,IF(W3="Medium",10,0))) -> 71.8
A4: C003 | B4: Cedar Logistics | C4: 46082 | D4: Enterprise | E4: Distribution | F4: North America | G4: Jordan Chen | H4: 310000 | I4: 304000 | J4: 0 | K4: 6000 | L4: 0 | M4: =MAX(H4-L4-K4,0) -> 304000 | N4: =M4+J4 -> 304000 | O4: =IFERROR(M4/H4,0) -> 0.98064516 | P4: =IFERROR(N4/H4,0) -> 0.98064516 | Q4: Active | R4: No Churn | S4: 46241 | T4: 61 | U4: 0.49 | V4: 14 | W4: =IF(Q4="Churned","Lost",IF(OR(T4<Inputs!$B$11,U4<Inputs!$B$13,V4>Inputs!$B$15),"High",IF(OR(T4<Inputs!$B$12,U4<Inputs!$B$14,V4>Inputs!$B$16),"Medium","Low"))) -> High | X4: =IF(W4="Lost","Document root cause and replace ARR",IF(W4="High","Executive save plan + adoption intervention",IF(W4="Medium","CSM action plan before renewal","Monitor / expansion candidate"))) -> Executive save plan + adoption intervention | Y4: =IF(W4="Lost",0,(100-T4)*0.35+(1-U4)*100*0.3+V4*2+IF(S4-TODAY()<=Inputs!$B$17,20,0)+IF(W4="High",25,IF(W4="Medium",10,0))) -> 101.95
A5: C004 | B5: Dover Claims | C5: 46113 | D5: SMB | E5: Insurance | F5: North America | G5: Leo Park | H5: 48000 | I5: 0 | J5: 0 | K5: 0 | L5: 48000 | M5: =MAX(H5-L5-K5,0) -> 0 | N5: =M5+J5 -> 0 | O5: =IFERROR(M5/H5,0) -> 0 | P5: =IFERROR(N5/H5,0) -> 0 | Q5: Churned | R5: Poor onboarding | S5: 46273 | T5: 31 | U5: 0.22 | V5: 18 | W5: =IF(Q5="Churned","Lost",IF(OR(T5<Inputs!$B$11,U5<Inputs!$B$13,V5>Inputs!$B$15),"High",IF(OR(T5<Inputs!$B$12,U5<Inputs!$B$14,V5>Inputs!$B$16),"Medium","Low"))) -> Lost | X5: =IF(W5="Lost","Document root cause and replace ARR",IF(W5="High","Executive save plan + adoption intervention",IF(W5="Medium","CSM action plan before renewal","Monitor / expansion candidate"))) -> Document root cause and replace ARR | Y5: =IF(W5="Lost",0,(100-T5)*0.35+(1-U5)*100*0.3+V5*2+IF(S5-TODAY()<=Inputs!$B$17,20,0)+IF(W5="High",25,IF(W5="Medium",10,0))) -> 0
A6: C005 | B6: Eastfield Dental | C6: 46143 | D6: Mid-Market | E6: Healthcare | F6: North America | G6: Maya Singh | H6: 120000 | I6: 123000 | J6: 4000 | K6: 1000 | L6: 0 | M6: =MAX(H6-L6-K6,0) -> 119000 | N6: =M6+J6 -> 123000 | O6: =IFERROR(M6/H6,0) -> 0.99166667 | P6: =IFERROR(N6/H6,0) -> 1.025 | Q6: Active | R6: No Churn | S6: 46304 | T6: 76 | U6: 0.71 | V6: 5 | W6: =IF(Q6="Churned","Lost",IF(OR(T6<Inputs!$B$11,U6<Inputs!$B$13,V6>Inputs!$B$15),"High",IF(OR(T6<Inputs!$B$12,U6<Inputs!$B$14,V6>Inputs!$B$16),"Medium","Low"))) -> Low | X6: =IF(W6="Lost","Document root cause and replace ARR",IF(W6="High","Executive save plan + adoption intervention",IF(W6="Medium","CSM action plan before renewal","Monitor / expansion candidate"))) -> Monitor / expansion candidate | Y6: =IF(W6="Lost",0,(100-T6)*0.35+(1-U6)*100*0.3+V6*2+IF(S6-TODAY()<=Inputs!$B$17,20,0)+IF(W6="High",25,IF(W6="Medium",10,0))) -> 27.1
A7: C006 | B7: Falcon Components | C7: 46174 | D7: Enterprise | E7: Manufacturing | F7: EMEA | G7: Nora Patel | H7: 285000 | I7: 282000 | J7: 0 | K7: 3000 | L7: 0 | M7: =MAX(H7-L7-K7,0) -> 282000 | N7: =M7+J7 -> 282000 | O7: =IFERROR(M7/H7,0) -> 0.98947368 | P7: =IFERROR(N7/H7,0) -> 0.98947368 | Q7: Active | R7: No Churn | S7: 46336 | T7: 88 | U7: 0.81 | V7: 2 | W7: =IF(Q7="Churned","Lost",IF(OR(T7<Inputs!$B$11,U7<Inputs!$B$13,V7>Inputs!$B$15),"High",IF(OR(T7<Inputs!$B$12,U7<Inputs!$B$14,V7>Inputs!$B$16),"Medium","Low"))) -> Low | X7: =IF(W7="Lost","Document root cause and replace ARR",IF(W7="High","Executive save plan + adoption intervention",IF(W7="Medium","CSM action plan before renewal","Monitor / expansion candidate"))) -> Monitor / expansion candidate | Y7: =IF(W7="Lost",0,(100-T7)*0.35+(1-U7)*100*0.3+V7*2+IF(S7-TODAY()<=Inputs!$B$17,20,0)+IF(W7="High",25,IF(W7="Medium",10,0))) -> 13.9
A8: C007 | B8: Granite Payroll | C8: 46023 | D8: SMB | E8: Business Services | F8: North America | G8: Leo Park | H8: 62000 | I8: 64000 | J8: 2000 | K8: 0 | L8: 0 | M8: =MAX(H8-L8-K8,0) -> 62000 | N8: =M8+J8 -> 64000 | O8: =IFERROR(M8/H8,0) -> 1 | P8: =IFERROR(N8/H8,0) -> 1.0322581 | Q8: Active | R8: No Churn | S8: 46367 | T8: 57 | U8: 0.44 | V8: 11 | W8: =IF(Q8="Churned","Lost",IF(OR(T8<Inputs!$B$11,U8<Inputs!$B$13,V8>Inputs!$B$15),"High",IF(OR(T8<Inputs!$B$12,U8<Inputs!$B$14,V8>Inputs!$B$16),"Medium","Low"))) -> Medium | X8: =IF(W8="Lost","Document root cause and replace ARR",IF(W8="High","Executive save plan + adoption intervention",IF(W8="Medium","CSM action plan before renewal","Monitor / expansion candidate"))) -> CSM action plan before renewal | Y8: =IF(W8="Lost",0,(100-T8)*0.35+(1-U8)*100*0.3+V8*2+IF(S8-TODAY()<=Inputs!$B$17,20,0)+IF(W8="High",25,IF(W8="Medium",10,0))) -> 63.85
A9: C008 | B9: Harbor Foods | C9: 46054 | D9: Mid-Market | E9: Distribution | F9: North America | G9: Jordan Chen | H9: 175000 | I9: 0 | J9: 0 | K9: 0 | L9: 175000 | M9: =MAX(H9-L9-K9,0) -> 0 | N9: =M9+J9 -> 0 | O9: =IFERROR(M9/H9,0) -> 0 | P9: =IFERROR(N9/H9,0) -> 0 | Q9: Churned | R9: Price / value mismatch | S9: 46034 | T9: 45 | U9: 0.33 | V9: 10 | W9: =IF(Q9="Churned","Lost",IF(OR(T9<Inputs!$B$11,U9<Inputs!$B$13,V9>Inputs!$B$15),"High",IF(OR(T9<Inputs!$B$12,U9<Inputs!$B$14,V9>Inputs!$B$16),"Medium","Low"))) -> Lost | X9: =IF(W9="Lost","Document root cause and replace ARR",IF(W9="High","Executive save plan + adoption intervention",IF(W9="Medium","CSM action plan before renewal","Monitor / expansion candidate"))) -> Document root cause and replace ARR | Y9: =IF(W9="Lost",0,(100-T9)*0.35+(1-U9)*100*0.3+V9*2+IF(S9-TODAY()<=Inputs!$B$17,20,0)+IF(W9="High",25,IF(W9="Medium",10,0))) -> 0
A10: C009 | B10: IronGate Security | C10: 46082 | D10: Enterprise | E10: Business Services | F10: EMEA | G10: Nora Patel | H10: 330000 | I10: 370000 | J10: 40000 | K10: 0 | L10: 0 | M10: =MAX(H10-L10-K10,0) -> 330000 | N10: =M10+J10 -> 370000 | O10: =IFERROR(M10/H10,0) -> 1 | P10: =IFERROR(N10/H10,0) -> 1.1212121 | Q10: Active | R10: No Churn | S10: 46066 | T10: 72 | U10: 0.63 | V10: 6 | W10: =IF(Q10="Churned","Lost",IF(OR(T10<Inputs!$B$11,U10<Inputs!$B$13,V10>Inputs!$B$15),"High",IF(OR(T10<Inputs!$B$12,U10<Inputs!$B$14,V10>Inputs!$B$16),"Medium","Low"))) -> Low | X10: =IF(W10="Lost","Document root cause and replace ARR",IF(W10="High","Executive save plan + adoption intervention",IF(W10="Medium","CSM action plan before renewal","Monitor / expansion candidate"))) -> Monitor / expansion candidate | Y10: =IF(W10="Lost",0,(100-T10)*0.35+(1-U10)*100*0.3+V10*2+IF(S10-TODAY()<=Inputs!$B$17,20,0)+IF(W10="High",25,IF(W10="Medium",10,0))) -> 52.9
A11: C010 | B11: Juniper Clinics | C11: 46113 | D11: Mid-Market | E11: Healthcare | F11: North America | G11: Maya Singh | H11: 135000 | I11: 135000 | J11: 0 | K11: 0 | L11: 0 | M11: =MAX(H11-L11-K11,0) -> 135000 | N11: =M11+J11 -> 135000 | O11: =IFERROR(M11/H11,0) -> 1 | P11: =IFERROR(N11/H11,0) -> 1 | Q11: Active | R11: No Churn | S11: 46095 | T11: 81 | U11: 0.74 | V11: 4 | W11: =IF(Q11="Churned","Lost",IF(OR(T11<Inputs!$B$11,U11<Inputs!$B$13,V11>Inputs!$B$15),"High",IF(OR(T11<Inputs!$B$12,U11<Inputs!$B$14,V11>Inputs!$B$16),"Medium","Low"))) -> Low | X11: =IF(W11="Lost","Document root cause and replace ARR",IF(W11="High","Executive save plan + adoption intervention",IF(W11="Medium","CSM action plan before renewal","Monitor / expansion candidate"))) -> Monitor / expansion candidate | Y11: =IF(W11="Lost",0,(100-T11)*0.35+(1-U11)*100*0.3+V11*2+IF(S11-TODAY()<=Inputs!$B$17,20,0)+IF(W11="High",25,IF(W11="Medium",10,0))) -> 42.45
A12: C011 | B12: Keystone Plastics | C12: 46143 | D12: Enterprise | E12: Manufacturing | F12: North America | G12: Jordan Chen | H12: 260000 | I12: 255000 | J12: 0 | K12: 5000 | L12: 0 | M12: =MAX(H12-L12-K12,0) -> 255000 | N12: =M12+J12 -> 255000 | O12: =IFERROR(M12/H12,0) -> 0.98076923 | P12: =IFERROR(N12/H12,0) -> 0.98076923 | Q12: Active | R12: No Churn | S12: 46127 | T12: 66 | U12: 0.56 | V12: 8 | W12: =IF(Q12="Churned","Lost",IF(OR(T12<Inputs!$B$11,U12<Inputs!$B$13,V12>Inputs!$B$15),"High",IF(OR(T12<Inputs!$B$12,U12<Inputs!$B$14,V12>Inputs!$B$16),"Medium","Low"))) -> Medium | X12: =IF(W12="Lost","Document root cause and replace ARR",IF(W12="High","Executive save plan + adoption intervention",IF(W12="Medium","CSM action plan before renewal","Monitor / expansion candidate"))) -> CSM action plan before renewal | Y12: =IF(W12="Lost",0,(100-T12)*0.35+(1-U12)*100*0.3+V12*2+IF(S12-TODAY()<=Inputs!$B$17,20,0)+IF(W12="High",25,IF(W12="Medium",10,0))) -> 71.1
A13: C012 | B13: Lakeview Supply | C13: 46174 | D13: SMB | E13: Distribution | F13: North America | G13: Leo Park | H13: 54000 | I13: 54000 | J13: 0 | K13: 0 | L13: 0 | M13: =MAX(H13-L13-K13,0) -> 54000 | N13: =M13+J13 -> 54000 | O13: =IFERROR(M13/H13,0) -> 1 | P13: =IFERROR(N13/H13,0) -> 1 | Q13: Active | R13: No Churn | S13: 46158 | T13: 69 | U13: 0.57 | V13: 6 | W13: =IF(Q13="Churned","Lost",IF(OR(T13<Inputs!$B$11,U13<Inputs!$B$13,V13>Inputs!$B$15),"High",IF(OR(T13<Inputs!$B$12,U13<Inputs!$B$14,V13>Inputs!$B$16),"Medium","Low"))) -> Medium | X13: =IF(W13="Lost","Document root cause and replace ARR",IF(W13="High","Executive save plan + adoption intervention",IF(W13="Medium","CSM action plan before renewal","Monitor / expansion candidate"))) -> CSM action plan before renewal | Y13: =IF(W13="Lost",0,(100-T13)*0.35+(1-U13)*100*0.3+V13*2+IF(S13-TODAY()<=Inputs!$B$17,20,0)+IF(W13="High",25,IF(W13="Medium",10,0))) -> 65.75
... A37: C036 | B37: Kingsley Components | C37: 46174 | D37: Mid-Market | E37: Manufacturing | F37: North America | G37: Jordan Chen | H37: 160000 | I37: 160000 | J37: 0 | K37: 0 | L37: 0 | M37: =MAX(H37-L37-K37,0) -> 160000 | N37: =M37+J37 -> 160000 | O37: =IFERROR(M37/H37,0) -> 1 | P37: =IFERROR(N37/H37,0) -> 1 | Q37: Active | R37: No Churn | S37: 46170 | T37: 74 | U37: 0.68 | V37: 4 | W37: =IF(Q37="Churned","Lost",IF(OR(T37<Inputs!$B$11,U37<Inputs!$B$13,V37>Inputs!$B$15),"High",IF(OR(T37<Inputs!$B$12,U37<Inputs!$B$14,V37>Inputs!$B$16),"Medium","Low"))) -> Low | X37: =IF(W37="Lost","Document root cause and replace ARR",IF(W37="High","Executive save plan + adoption intervention",IF(W37="Medium","CSM action plan before renewal","Monitor / expansion candidate"))) -> Monitor / expansion candidate | Y37: =IF(W37="Lost",0,(100-T37)*0.35+(1-U37)*100*0.3+V37*2+IF(S37-TODAY()<=Inputs!$B$17,20,0)+IF(W37="High",25,IF(W37="Medium",10,0))) -> 46.7

Sheet Cohort_Retention
A1: Cohort Retention Analysis
A2: ARR, logo, GRR, and NRR by customer cohort.
A4: Cohort | B4: Customer Count | C4: Beginning ARR | D4: Ending ARR | E4: Expansion | F4: Contraction | G4: Churned ARR | H4: Gross Retained ARR | I4: Net Retained ARR | J4: Logo Retention % | K4: GRR % | L4: NRR %
A5: 46023 | B5: =COUNTIFS(Customer_MRR_Data!$C:$C,A5) -> 6 | C5: =SUMIFS(Customer_MRR_Data!$H:$H,Customer_MRR_Data!$C:$C,A5) -> 1173000 | D5: =SUMIFS(Customer_MRR_Data!$I:$I,Customer_MRR_Data!$C:$C,A5) -> 1244000 | E5: =SUMIFS(Customer_MRR_Data!$J:$J,Customer_MRR_Data!$C:$C,A5) -> 72000 | F5: =SUMIFS(Customer_MRR_Data!$K:$K,Customer_MRR_Data!$C:$C,A5) -> 1000 | G5: =SUMIFS(Customer_MRR_Data!$L:$L,Customer_MRR_Data!$C:$C,A5) -> 0 | H5: =SUMIFS(Customer_MRR_Data!$M:$M,Customer_MRR_Data!$C:$C,A5) -> 1172000 | I5: =SUMIFS(Customer_MRR_Data!$N:$N,Customer_MRR_Data!$C:$C,A5) -> 1244000 | J5: =IFERROR(COUNTIFS(Customer_MRR_Data!$C:$C,A5,Customer_MRR_Data!$Q:$Q,"Active")/B5,0) -> 1 | K5: =IFERROR(H5/C5,0) -> 0.99914749 | L5: =IFERROR(I5/C5,0) -> 1.0605286
A6: 46054 | B6: =COUNTIFS(Customer_MRR_Data!$C:$C,A6) -> 6 | C6: =SUMIFS(Customer_MRR_Data!$H:$H,Customer_MRR_Data!$C:$C,A6) -> 1019000 | D6: =SUMIFS(Customer_MRR_Data!$I:$I,Customer_MRR_Data!$C:$C,A6) -> 691000 | E6: =SUMIFS(Customer_MRR_Data!$J:$J,Customer_MRR_Data!$C:$C,A6) -> 29000 | F6: =SUMIFS(Customer_MRR_Data!$K:$K,Customer_MRR_Data!$C:$C,A6) -> 15000 | G6: =SUMIFS(Customer_MRR_Data!$L:$L,Customer_MRR_Data!$C:$C,A6) -> 342000 | H6: =SUMIFS(Customer_MRR_Data!$M:$M,Customer_MRR_Data!$C:$C,A6) -> 662000 | I6: =SUMIFS(Customer_MRR_Data!$N:$N,Customer_MRR_Data!$C:$C,A6) -> 691000 | J6: =IFERROR(COUNTIFS(Customer_MRR_Data!$C:$C,A6,Customer_MRR_Data!$Q:$Q,"Active")/B6,0) -> 0.5 | K6: =IFERROR(H6/C6,0) -> 0.64965653 | L6: =IFERROR(I6/C6,0) -> 0.6781158
A7: 46082 | B7: =COUNTIFS(Customer_MRR_Data!$C:$C,A7) -> 6 | C7: =SUMIFS(Customer_MRR_Data!$H:$H,Customer_MRR_Data!$C:$C,A7) -> 1040000 | D7: =SUMIFS(Customer_MRR_Data!$I:$I,Customer_MRR_Data!$C:$C,A7) -> 1042000 | E7: =SUMIFS(Customer_MRR_Data!$J:$J,Customer_MRR_Data!$C:$C,A7) -> 62000 | F7: =SUMIFS(Customer_MRR_Data!$K:$K,Customer_MRR_Data!$C:$C,A7) -> 13000 | G7: =SUMIFS(Customer_MRR_Data!$L:$L,Customer_MRR_Data!$C:$C,A7) -> 47000 | H7: =SUMIFS(Customer_MRR_Data!$M:$M,Customer_MRR_Data!$C:$C,A7) -> 980000 | I7: =SUMIFS(Customer_MRR_Data!$N:$N,Customer_MRR_Data!$C:$C,A7) -> 1042000 | J7: =IFERROR(COUNTIFS(Customer_MRR_Data!$C:$C,A7,Customer_MRR_Data!$Q:$Q,"Active")/B7,0) -> 0.83333333 | K7: =IFERROR(H7/C7,0) -> 0.94230769 | L7: =IFERROR(I7/C7,0) -> 1.0019231
A8: 46113 | B8: =COUNTIFS(Customer_MRR_Data!$C:$C,A8) -> 6 | C8: =SUMIFS(Customer_MRR_Data!$H:$H,Customer_MRR_Data!$C:$C,A8) -> 1061000 | D8: =SUMIFS(Customer_MRR_Data!$I:$I,Customer_MRR_Data!$C:$C,A8) -> 1003000 | E8: =SUMIFS(Customer_MRR_Data!$J:$J,Customer_MRR_Data!$C:$C,A8) -> 12000 | F8: =SUMIFS(Customer_MRR_Data!$K:$K,Customer_MRR_Data!$C:$C,A8) -> 22000 | G8: =SUMIFS(Customer_MRR_Data!$L:$L,Customer_MRR_Data!$C:$C,A8) -> 48000 | H8: =SUMIFS(Customer_MRR_Data!$M:$M,Customer_MRR_Data!$C:$C,A8) -> 991000 | I8: =SUMIFS(Customer_MRR_Data!$N:$N,Customer_MRR_Data!$C:$C,A8) -> 1003000 | J8: =IFERROR(COUNTIFS(Customer_MRR_Data!$C:$C,A8,Customer_MRR_Data!$Q:$Q,"Active")/B8,0) -> 0.83333333 | K8: =IFERROR(H8/C8,0) -> 0.93402451 | L8: =IFERROR(I8/C8,0) -> 0.94533459
A9: 46143 | B9: =COUNTIFS(Customer_MRR_Data!$C:$C,A9) -> 6 | C9: =SUMIFS(Customer_MRR_Data!$H:$H,Customer_MRR_Data!$C:$C,A9) -> 1343000 | D9: =SUMIFS(Customer_MRR_Data!$I:$I,Customer_MRR_Data!$C:$C,A9) -> 1098000 | E9: =SUMIFS(Customer_MRR_Data!$J:$J,Customer_MRR_Data!$C:$C,A9) -> 40000 | F9: =SUMIFS(Customer_MRR_Data!$K:$K,Customer_MRR_Data!$C:$C,A9) -> 15000 | G9: =SUMIFS(Customer_MRR_Data!$L:$L,Customer_MRR_Data!$C:$C,A9) -> 270000 | H9: =SUMIFS(Customer_MRR_Data!$M:$M,Customer_MRR_Data!$C:$C,A9) -> 1058000 | I9: =SUMIFS(Customer_MRR_Data!$N:$N,Customer_MRR_Data!$C:$C,A9) -> 1098000 | J9: =IFERROR(COUNTIFS(Customer_MRR_Data!$C:$C,A9,Customer_MRR_Data!$Q:$Q,"Active")/B9,0) -> 0.83333333 | K9: =IFERROR(H9/C9,0) -> 0.78778853 | L9: =IFERROR(I9/C9,0) -> 0.8175726
A10: 46174 | B10: =COUNTIFS(Customer_MRR_Data!$C:$C,A10) -> 6 | C10: =SUMIFS(Customer_MRR_Data!$H:$H,Customer_MRR_Data!$C:$C,A10) -> 759000 | D10: =SUMIFS(Customer_MRR_Data!$I:$I,Customer_MRR_Data!$C:$C,A10) -> 748000 | E10: =SUMIFS(Customer_MRR_Data!$J:$J,Customer_MRR_Data!$C:$C,A10) -> 1000 | F10: =SUMIFS(Customer_MRR_Data!$K:$K,Customer_MRR_Data!$C:$C,A10) -> 12000 | G10: =SUMIFS(Customer_MRR_Data!$L:$L,Customer_MRR_Data!$C:$C,A10) -> 0 | H10: =SUMIFS(Customer_MRR_Data!$M:$M,Customer_MRR_Data!$C:$C,A10) -> 747000 | I10: =SUMIFS(Customer_MRR_Data!$N:$N,Customer_MRR_Data!$C:$C,A10) -> 748000 | J10: =IFERROR(COUNTIFS(Customer_MRR_Data!$C:$C,A10,Customer_MRR_Data!$Q:$Q,"Active")/B10,0) -> 1 | K10: =IFERROR(H10/C10,0) -> 0.98418972 | L10: =IFERROR(I10/C10,0) -> 0.98550725
A11: Total | B11: =SUM(B5:B10) -> 36 | C11: =SUM(C5:C10) -> 6395000 | D11: =SUM(D5:D10) -> 5826000 | E11: =SUM(E5:E10) -> 216000 | F11: =SUM(F5:F10) -> 78000 | G11: =SUM(G5:G10) -> 707000 | H11: =SUM(H5:H10) -> 5610000 | I11: =SUM(I5:I10) -> 5826000 | J11: =COUNTIFS(Customer_MRR_Data!$Q:$Q,"Active")/COUNTA(Customer_MRR_Data!$A$2:$A$37) -> 0.83333333 | K11: =H11/C11 -> 0.87724785 | L11: =I11/C11 -> 0.91102424

Sheet NRR_Bridge
A1: NRR Bridge
A2: Beginning ARR to ending ARR via expansion, contraction, and churn.
A4: Bridge Item | B4: Amount ($) | C4: % of Beginning ARR
A5: Beginning ARR | B5: =SUM(Customer_MRR_Data!$H:$H) -> 6395000 | C5: =B5/$B$5 -> 1
A6: Expansion | B6: =SUM(Customer_MRR_Data!$J:$J) -> 216000 | C6: =B6/$B$5 -> 0.033776388
A7: Contraction | B7: =-SUM(Customer_MRR_Data!$K:$K) -> -78000 | C7: =B7/$B$5 -> -0.012197029
A8: Churned ARR | B8: =-SUM(Customer_MRR_Data!$L:$L) -> -707000 | C8: =B8/$B$5 -> -0.11055512
A9: Ending ARR | B9: =SUM(Customer_MRR_Data!$I:$I) -> 5826000 | C9: =B9/$B$5 -> 0.91102424
A10: Net Revenue Retention | B10: =B9/B5 -> 0.91102424
A11: Gross Revenue Retention | B11: =SUM(Customer_MRR_Data!$M:$M)/B5 -> 0.87724785

Sheet Churn_Analysis
A1: Churn & Contraction Analysis
A2: Root causes and segment-level retention performance.
A4: Churn Reason Summary
A5: Churn Reason | B5: Customers | C5: Churned ARR | D5: % of Churned ARR | E5: Recommended Management Action | F5: Priority
A6: Poor onboarding | B6: =COUNTIFS(Customer_MRR_Data!$R:$R,A6) -> 1 | C6: =SUMIFS(Customer_MRR_Data!$L:$L,Customer_MRR_Data!$R:$R,A6) -> 48000 | D6: =IFERROR(C6/SUM(Customer_MRR_Data!$L:$L),0) -> 0.067892504 | E6: Redesign onboarding journey | F6: =IF(D6>=25%,"High",IF(D6>=10%,"Medium","Low")) -> Low
A7: Price / value mismatch | B7: =COUNTIFS(Customer_MRR_Data!$R:$R,A7) -> 1 | C7: =SUMIFS(Customer_MRR_Data!$L:$L,Customer_MRR_Data!$R:$R,A7) -> 175000 | D7: =IFERROR(C7/SUM(Customer_MRR_Data!$L:$L),0) -> 0.24752475 | E7: Reassess packaging / value proof | F7: =IF(D7>=25%,"High",IF(D7>=10%,"Medium","Low")) -> Medium
A8: Budget cut | B8: =COUNTIFS(Customer_MRR_Data!$R:$R,A8) -> 1 | C8: =SUMIFS(Customer_MRR_Data!$L:$L,Customer_MRR_Data!$R:$R,A8) -> 42000 | D8: =IFERROR(C8/SUM(Customer_MRR_Data!$L:$L),0) -> 0.059405941 | E8: Segment budget-risk customers | F8: =IF(D8>=25%,"High",IF(D8>=10%,"Medium","Low")) -> Low
A9: Service issue | B9: =COUNTIFS(Customer_MRR_Data!$R:$R,A9) -> 1 | C9: =SUMIFS(Customer_MRR_Data!$L:$L,Customer_MRR_Data!$R:$R,A9) -> 125000 | D9: =IFERROR(C9/SUM(Customer_MRR_Data!$L:$L),0) -> 0.17680339 | E9: Escalate service recovery | F9: =IF(D9>=25%,"High",IF(D9>=10%,"Medium","Low")) -> Medium
A10: Competitor loss | B10: =COUNTIFS(Customer_MRR_Data!$R:$R,A10) -> 1 | C10: =SUMIFS(Customer_MRR_Data!$L:$L,Customer_MRR_Data!$R:$R,A10) -> 47000 | D10: =IFERROR(C10/SUM(Customer_MRR_Data!$L:$L),0) -> 0.066478076 | E10: Competitive win-back review | F10: =IF(D10>=25%,"High",IF(D10>=10%,"Medium","Low")) -> Low
A11: M&A consolidation | B11: =COUNTIFS(Customer_MRR_Data!$R:$R,A11) -> 1 | C11: =SUMIFS(Customer_MRR_Data!$L:$L,Customer_MRR_Data!$R:$R,A11) -> 270000 | D11: =IFERROR(C11/SUM(Customer_MRR_Data!$L:$L),0) -> 0.38189533 | E11: Track consolidation-driven losses | F11: =IF(D11>=25%,"High",IF(D11>=10%,"Medium","Low")) -> High
A14: Segment Retention Summary
A15: Segment | B15: Beginning ARR | C15: Ending ARR | D15: Expansion | E15: Contraction | F15: Churned ARR | G15: GRR % | H15: NRR %
A16: Enterprise | B16: =SUMIFS(Customer_MRR_Data!$H:$H,Customer_MRR_Data!$D:$D,A16) -> 4030000 | C16: =SUMIFS(Customer_MRR_Data!$I:$I,Customer_MRR_Data!$D:$D,A16) -> 3892000 | D16: =SUMIFS(Customer_MRR_Data!$J:$J,Customer_MRR_Data!$D:$D,A16) -> 174000 | E16: =SUMIFS(Customer_MRR_Data!$K:$K,Customer_MRR_Data!$D:$D,A16) -> 42000 | F16: =SUMIFS(Customer_MRR_Data!$L:$L,Customer_MRR_Data!$D:$D,A16) -> 270000 | G16: =IFERROR((B16-E16-F16)/B16,0) -> 0.92258065 | H16: =IFERROR((B16-E16-F16+D16)/B16,0) -> 0.96575682
A17: Mid-Market | B17: =SUMIFS(Customer_MRR_Data!$H:$H,Customer_MRR_Data!$D:$D,A17) -> 1840000 | C17: =SUMIFS(Customer_MRR_Data!$I:$I,Customer_MRR_Data!$D:$D,A17) -> 1544000 | D17: =SUMIFS(Customer_MRR_Data!$J:$J,Customer_MRR_Data!$D:$D,A17) -> 37000 | E17: =SUMIFS(Customer_MRR_Data!$K:$K,Customer_MRR_Data!$D:$D,A17) -> 33000 | F17: =SUMIFS(Customer_MRR_Data!$L:$L,Customer_MRR_Data!$D:$D,A17) -> 300000 | G17: =IFERROR((B17-E17-F17)/B17,0) -> 0.81902174 | H17: =IFERROR((B17-E17-F17+D17)/B17,0) -> 0.83913043
A18: SMB | B18: =SUMIFS(Customer_MRR_Data!$H:$H,Customer_MRR_Data!$D:$D,A18) -> 525000 | C18: =SUMIFS(Customer_MRR_Data!$I:$I,Customer_MRR_Data!$D:$D,A18) -> 390000 | D18: =SUMIFS(Customer_MRR_Data!$J:$J,Customer_MRR_Data!$D:$D,A18) -> 5000 | E18: =SUMIFS(Customer_MRR_Data!$K:$K,Customer_MRR_Data!$D:$D,A18) -> 3000 | F18: =SUMIFS(Customer_MRR_Data!$L:$L,Customer_MRR_Data!$D:$D,A18) -> 137000 | G18: =IFERROR((B18-E18-F18)/B18,0) -> 0.73333333 | H18: =IFERROR((B18-E18-F18+D18)/B18,0) -> 0.74285714

Sheet Renewal_Risk
A1: Renewal Risk Register
A2: Top at-risk accounts by health, usage, support load, and renewal timing.
A4: Rank | B4: Customer | C4: Segment | D4: CSM | E4: Renewal Date | F4: Health Score | G4: Usage % | H4: ARR at Risk | I4: Risk | J4: Recommended Action
A5: 1 | B5: =INDEX(Customer_MRR_Data!$B:$B,MATCH(LARGE(Customer_MRR_Data!$Y:$Y,A5),Customer_MRR_Data!$Y:$Y,0)) -> Apex Claims | C5: =INDEX(Customer_MRR_Data!$D:$D,MATCH($B5,Customer_MRR_Data!$B:$B,0)) -> Mid-Market | D5: =INDEX(Customer_MRR_Data!$G:$G,MATCH($B5,Customer_MRR_Data!$B:$B,0)) -> Maya Singh | E5: =INDEX(Customer_MRR_Data!$S:$S,MATCH($B5,Customer_MRR_Data!$B:$B,0)) -> 46231 | F5: =INDEX(Customer_MRR_Data!$T:$T,MATCH($B5,Customer_MRR_Data!$B:$B,0)) -> 52 | G5: =INDEX(Customer_MRR_Data!$U:$U,MATCH($B5,Customer_MRR_Data!$B:$B,0)) -> 0.41 | H5: =INDEX(Customer_MRR_Data!$H:$H,MATCH($B5,Customer_MRR_Data!$B:$B,0)) -> 132000 | I5: =INDEX(Customer_MRR_Data!$W:$W,MATCH($B5,Customer_MRR_Data!$B:$B,0)) -> High | J5: =INDEX(Customer_MRR_Data!$X:$X,MATCH($B5,Customer_MRR_Data!$B:$B,0)) -> Executive save plan + adoption intervention
A6: 2 | B6: =INDEX(Customer_MRR_Data!$B:$B,MATCH(LARGE(Customer_MRR_Data!$Y:$Y,A6),Customer_MRR_Data!$Y:$Y,0)) -> Horizon Parts | C6: =INDEX(Customer_MRR_Data!$D:$D,MATCH($B6,Customer_MRR_Data!$B:$B,0)) -> Mid-Market | D6: =INDEX(Customer_MRR_Data!$G:$G,MATCH($B6,Customer_MRR_Data!$B:$B,0)) -> Nora Patel | E6: =INDEX(Customer_MRR_Data!$S:$S,MATCH($B6,Customer_MRR_Data!$B:$B,0)) -> 46081 | F6: =INDEX(Customer_MRR_Data!$T:$T,MATCH($B6,Customer_MRR_Data!$B:$B,0)) -> 55 | G6: =INDEX(Customer_MRR_Data!$U:$U,MATCH($B6,Customer_MRR_Data!$B:$B,0)) -> 0.42 | H6: =INDEX(Customer_MRR_Data!$H:$H,MATCH($B6,Customer_MRR_Data!$B:$B,0)) -> 142000 | I6: =INDEX(Customer_MRR_Data!$W:$W,MATCH($B6,Customer_MRR_Data!$B:$B,0)) -> High | J6: =INDEX(Customer_MRR_Data!$X:$X,MATCH($B6,Customer_MRR_Data!$B:$B,0)) -> Executive save plan + adoption intervention
A7: 3 | B7: =INDEX(Customer_MRR_Data!$B:$B,MATCH(LARGE(Customer_MRR_Data!$Y:$Y,A7),Customer_MRR_Data!$Y:$Y,0)) -> Cedar Logistics | C7: =INDEX(Customer_MRR_Data!$D:$D,MATCH($B7,Customer_MRR_Data!$B:$B,0)) -> Enterprise | D7: =INDEX(Customer_MRR_Data!$G:$G,MATCH($B7,Customer_MRR_Data!$B:$B,0)) -> Jordan Chen | E7: =INDEX(Customer_MRR_Data!$S:$S,MATCH($B7,Customer_MRR_Data!$B:$B,0)) -> 46241 | F7: =INDEX(Customer_MRR_Data!$T:$T,MATCH($B7,Customer_MRR_Data!$B:$B,0)) -> 61 | G7: =INDEX(Customer_MRR_Data!$U:$U,MATCH($B7,Customer_MRR_Data!$B:$B,0)) -> 0.49 | H7: =INDEX(Customer_MRR_Data!$H:$H,MATCH($B7,Customer_MRR_Data!$B:$B,0)) -> 310000 | I7: =INDEX(Customer_MRR_Data!$W:$W,MATCH($B7,Customer_MRR_Data!$B:$B,0)) -> High | J7: =INDEX(Customer_MRR_Data!$X:$X,MATCH($B7,Customer_MRR_Data!$B:$B,0)) -> Executive save plan + adoption intervention
A8: 4 | B8: =INDEX(Customer_MRR_Data!$B:$B,MATCH(LARGE(Customer_MRR_Data!$Y:$Y,A8),Customer_MRR_Data!$Y:$Y,0)) -> Pioneer Freight | C8: =INDEX(Customer_MRR_Data!$D:$D,MATCH($B8,Customer_MRR_Data!$B:$B,0)) -> Enterprise | D8: =INDEX(Customer_MRR_Data!$G:$G,MATCH($B8,Customer_MRR_Data!$B:$B,0)) -> Nora Patel | E8: =INDEX(Customer_MRR_Data!$S:$S,MATCH($B8,Customer_MRR_Data!$B:$B,0)) -> 46285 | F8: =INDEX(Customer_MRR_Data!$T:$T,MATCH($B8,Customer_MRR_Data!$B:$B,0)) -> 54 | G8: =INDEX(Customer_MRR_Data!$U:$U,MATCH($B8,Customer_MRR_Data!$B:$B,0)) -> 0.39 | H8: =INDEX(Customer_MRR_Data!$H:$H,MATCH($B8,Customer_MRR_Data!$B:$B,0)) -> 340000 | I8: =INDEX(Customer_MRR_Data!$W:$W,MATCH($B8,Customer_MRR_Data!$B:$B,0)) -> High | J8: =INDEX(Customer_MRR_Data!$X:$X,MATCH($B8,Customer_MRR_Data!$B:$B,0)) -> Executive save plan + adoption intervention
A9: 5 | B9: =INDEX(Customer_MRR_Data!$B:$B,MATCH(LARGE(Customer_MRR_Data!$Y:$Y,A9),Customer_MRR_Data!$Y:$Y,0)) -> Union Billing | C9: =INDEX(Customer_MRR_Data!$D:$D,MATCH($B9,Customer_MRR_Data!$B:$B,0)) -> SMB | D9: =INDEX(Customer_MRR_Data!$G:$G,MATCH($B9,Customer_MRR_Data!$B:$B,0)) -> Leo Park | E9: =INDEX(Customer_MRR_Data!$S:$S,MATCH($B9,Customer_MRR_Data!$B:$B,0)) -> 46078 | F9: =INDEX(Customer_MRR_Data!$T:$T,MATCH($B9,Customer_MRR_Data!$B:$B,0)) -> 59 | G9: =INDEX(Customer_MRR_Data!$U:$U,MATCH($B9,Customer_MRR_Data!$B:$B,0)) -> 0.46 | H9: =INDEX(Customer_MRR_Data!$H:$H,MATCH($B9,Customer_MRR_Data!$B:$B,0)) -> 66000 | I9: =INDEX(Customer_MRR_Data!$W:$W,MATCH($B9,Customer_MRR_Data!$B:$B,0)) -> Medium | J9: =INDEX(Customer_MRR_Data!$X:$X,MATCH($B9,Customer_MRR_Data!$B:$B,0)) -> CSM action plan before renewal
A10: 6 | B10: =INDEX(Customer_MRR_Data!$B:$B,MATCH(LARGE(Customer_MRR_Data!$Y:$Y,A10),Customer_MRR_Data!$Y:$Y,0)) -> BlueRiver Health | C10: =INDEX(Customer_MRR_Data!$D:$D,MATCH($B10,Customer_MRR_Data!$B:$B,0)) -> Mid-Market | D10: =INDEX(Customer_MRR_Data!$G:$G,MATCH($B10,Customer_MRR_Data!$B:$B,0)) -> Maya Singh | E10: =INDEX(Customer_MRR_Data!$S:$S,MATCH($B10,Customer_MRR_Data!$B:$B,0)) -> 46209 | F10: =INDEX(Customer_MRR_Data!$T:$T,MATCH($B10,Customer_MRR_Data!$B:$B,0)) -> 68 | G10: =INDEX(Customer_MRR_Data!$U:$U,MATCH($B10,Customer_MRR_Data!$B:$B,0)) -> 0.58 | H10: =INDEX(Customer_MRR_Data!$H:$H,MATCH($B10,Customer_MRR_Data!$B:$B,0)) -> 155000 | I10: =INDEX(Customer_MRR_Data!$W:$W,MATCH($B10,Customer_MRR_Data!$B:$B,0)) -> Medium | J10: =INDEX(Customer_MRR_Data!$X:$X,MATCH($B10,Customer_MRR_Data!$B:$B,0)) -> CSM action plan before renewal
A11: 7 | B11: =INDEX(Customer_MRR_Data!$B:$B,MATCH(LARGE(Customer_MRR_Data!$Y:$Y,A11),Customer_MRR_Data!$Y:$Y,0)) -> Keystone Plastics | C11: =INDEX(Customer_MRR_Data!$D:$D,MATCH($B11,Customer_MRR_Data!$B:$B,0)) -> Enterprise | D11: =INDEX(Customer_MRR_Data!$G:$G,MATCH($B11,Customer_MRR_Data!$B:$B,0)) -> Jordan Chen | E11: =INDEX(Customer_MRR_Data!$S:$S,MATCH($B11,Customer_MRR_Data!$B:$B,0)) -> 46127 | F11: =INDEX(Customer_MRR_Data!$T:$T,MATCH($B11,Customer_MRR_Data!$B:$B,0)) -> 66 | G11: =INDEX(Customer_MRR_Data!$U:$U,MATCH($B11,Customer_MRR_Data!$B:$B,0)) -> 0.56 | H11: =INDEX(Customer_MRR_Data!$H:$H,MATCH($B11,Customer_MRR_Data!$B:$B,0)) -> 260000 | I11: =INDEX(Customer_MRR_Data!$W:$W,MATCH($B11,Customer_MRR_Data!$B:$B,0)) -> Medium | J11: =INDEX(Customer_MRR_Data!$X:$X,MATCH($B11,Customer_MRR_Data!$B:$B,0)) -> CSM action plan before renewal
A12: 8 | B12: =INDEX(Customer_MRR_Data!$B:$B,MATCH(LARGE(Customer_MRR_Data!$Y:$Y,A12),Customer_MRR_Data!$Y:$Y,0)) -> Yardline Medical | C12: =INDEX(Customer_MRR_Data!$D:$D,MATCH($B12,Customer_MRR_Data!$B:$B,0)) -> SMB | D12: =INDEX(Customer_MRR_Data!$G:$G,MATCH($B12,Customer_MRR_Data!$B:$B,0)) -> Leo Park | E12: =INDEX(Customer_MRR_Data!$S:$S,MATCH($B12,Customer_MRR_Data!$B:$B,0)) -> 46170 | F12: =INDEX(Customer_MRR_Data!$T:$T,MATCH($B12,Customer_MRR_Data!$B:$B,0)) -> 64 | G12: =INDEX(Customer_MRR_Data!$U:$U,MATCH($B12,Customer_MRR_Data!$B:$B,0)) -> 0.55 | H12: =INDEX(Customer_MRR_Data!$H:$H,MATCH($B12,Customer_MRR_Data!$B:$B,0)) -> 52000 | I12: =INDEX(Customer_MRR_Data!$W:$W,MATCH($B12,Customer_MRR_Data!$B:$B,0)) -> Medium | J12: =INDEX(Customer_MRR_Data!$X:$X,MATCH($B12,Customer_MRR_Data!$B:$B,0)) -> CSM action plan before renewal
A13: 9 | B13: =INDEX(Customer_MRR_Data!$B:$B,MATCH(LARGE(Customer_MRR_Data!$Y:$Y,A13),Customer_MRR_Data!$Y:$Y,0)) -> Ivy Claims | C13: =INDEX(Customer_MRR_Data!$D:$D,MATCH($B13,Customer_MRR_Data!$B:$B,0)) -> SMB | D13: =INDEX(Customer_MRR_Data!$G:$G,MATCH($B13,Customer_MRR_Data!$B:$B,0)) -> Leo Park | E13: =INDEX(Customer_MRR_Data!$S:$S,MATCH($B13,Customer_MRR_Data!$B:$B,0)) -> 46109 | F13: =INDEX(Customer_MRR_Data!$T:$T,MATCH($B13,Customer_MRR_Data!$B:$B,0)) -> 67 | G13: =INDEX(Customer_MRR_Data!$U:$U,MATCH($B13,Customer_MRR_Data!$B:$B,0)) -> 0.54 | H13: =INDEX(Customer_MRR_Data!$H:$H,MATCH($B13,Customer_MRR_Data!$B:$B,0)) -> 45000 | I13: =INDEX(Customer_MRR_Data!$W:$W,MATCH($B13,Customer_MRR_Data!$B:$B,0)) -> Medium | J13: =INDEX(Customer_MRR_Data!$X:$X,MATCH($B13,Customer_MRR_Data!$B:$B,0)) -> CSM action plan before renewal
A14: 10 | B14: =INDEX(Customer_MRR_Data!$B:$B,MATCH(LARGE(Customer_MRR_Data!$Y:$Y,A14),Customer_MRR_Data!$Y:$Y,0)) -> Lakeview Supply | C14: =INDEX(Customer_MRR_Data!$D:$D,MATCH($B14,Customer_MRR_Data!$B:$B,0)) -> SMB | D14: =INDEX(Customer_MRR_Data!$G:$G,MATCH($B14,Customer_MRR_Data!$B:$B,0)) -> Leo Park | E14: =INDEX(Customer_MRR_Data!$S:$S,MATCH($B14,Customer_MRR_Data!$B:$B,0)) -> 46158 | F14: =INDEX(Customer_MRR_Data!$T:$T,MATCH($B14,Customer_MRR_Data!$B:$B,0)) -> 69 | G14: =INDEX(Customer_MRR_Data!$U:$U,MATCH($B14,Customer_MRR_Data!$B:$B,0)) -> 0.57 | H14: =INDEX(Customer_MRR_Data!$H:$H,MATCH($B14,Customer_MRR_Data!$B:$B,0)) -> 54000 | I14: =INDEX(Customer_MRR_Data!$W:$W,MATCH($B14,Customer_MRR_Data!$B:$B,0)) -> Medium | J14: =INDEX(Customer_MRR_Data!$X:$X,MATCH($B14,Customer_MRR_Data!$B:$B,0)) -> CSM action plan before renewal
A15: 11 | B15: =INDEX(Customer_MRR_Data!$B:$B,MATCH(LARGE(Customer_MRR_Data!$Y:$Y,A15),Customer_MRR_Data!$Y:$Y,0)) -> Granite Payroll | C15: =INDEX(Customer_MRR_Data!$D:$D,MATCH($B15,Customer_MRR_Data!$B:$B,0)) -> SMB | D15: =INDEX(Customer_MRR_Data!$G:$G,MATCH($B15,Customer_MRR_Data!$B:$B,0)) -> Leo Park | E15: =INDEX(Customer_MRR_Data!$S:$S,MATCH($B15,Customer_MRR_Data!$B:$B,0)) -> 46367 | F15: =INDEX(Customer_MRR_Data!$T:$T,MATCH($B15,Customer_MRR_Data!$B:$B,0)) -> 57 | G15: =INDEX(Customer_MRR_Data!$U:$U,MATCH($B15,Customer_MRR_Data!$B:$B,0)) -> 0.44 | H15: =INDEX(Customer_MRR_Data!$H:$H,MATCH($B15,Customer_MRR_Data!$B:$B,0)) -> 62000 | I15: =INDEX(Customer_MRR_Data!$W:$W,MATCH($B15,Customer_MRR_Data!$B:$B,0)) -> Medium | J15: =INDEX(Customer_MRR_Data!$X:$X,MATCH($B15,Customer_MRR_Data!$B:$B,0)) -> CSM action plan before renewal
A16: 12 | B16: =INDEX(Customer_MRR_Data!$B:$B,MATCH(LARGE(Customer_MRR_Data!$Y:$Y,A16),Customer_MRR_Data!$Y:$Y,0)) -> Evergreen Fleet | C16: =INDEX(Customer_MRR_Data!$D:$D,MATCH($B16,Customer_MRR_Data!$B:$B,0)) -> Mid-Market | D16: =INDEX(Customer_MRR_Data!$G:$G,MATCH($B16,Customer_MRR_Data!$B:$B,0)) -> Nora Patel | E16: =INDEX(Customer_MRR_Data!$S:$S,MATCH($B16,Customer_MRR_Data!$B:$B,0)) -> 46354 | F16: =INDEX(Customer_MRR_Data!$T:$T,MATCH($B16,Customer_MRR_Data!$B:$B,0)) -> 60 | G16: =INDEX(Customer_MRR_Data!$U:$U,MATCH($B16,Customer_MRR_Data!$B:$B,0)) -> 0.48 | H16: =INDEX(Customer_MRR_Data!$H:$H,MATCH($B16,Customer_MRR_Data!$B:$B,0)) -> 150000 | I16: =INDEX(Customer_MRR_Data!$W:$W,MATCH($B16,Customer_MRR_Data!$B:$B,0)) -> Medium | J16: =INDEX(Customer_MRR_Data!$X:$X,MATCH($B16,Customer_MRR_Data!$B:$B,0)) -> CSM action plan before renewal

Sheet Scenarios
A1: NRR Improvement Scenarios
A2: Scenario logic for retention/expansion improvement and financial impact.
A4: Scenario | B4: NRR Improvement | C4: GRR Improvement | D4: Incremental Ending ARR | E4: Contribution Margin | F4: Incremental EBITDA | G4: Exit Multiple | H4: Enterprise Value Impact
A5: Conservative | B5: 0.02 | C5: 0.01 | D5: =SUM(Customer_MRR_Data!$H:$H)*B5 -> 127900 | E5: =Inputs!$B$9 -> 0.7 | F5: =D5*E5 -> 89530 | G5: =Inputs!$B$10 -> 12 | H5: =F5*G5 -> 1074360
A6: Base | B6: 0.04 | C6: 0.02 | D6: =SUM(Customer_MRR_Data!$H:$H)*B6 -> 255800 | E6: =Inputs!$B$9 -> 0.7 | F6: =D6*E6 -> 179060 | G6: =Inputs!$B$10 -> 12 | H6: =F6*G6 -> 2148720
A7: Upside | B7: 0.06 | C7: 0.03 | D7: =SUM(Customer_MRR_Data!$H:$H)*B7 -> 383700 | E7: =Inputs!$B$9 -> 0.7 | F7: =D7*E7 -> 268590 | G7: =Inputs!$B$10 -> 12 | H7: =F7*G7 -> 3223080

Sheet EBITDA_Impact
A1: EBITDA & Enterprise Value Impact
A2: How retention improvement converts to EBITDA and valuation impact.
A4: Metric | B4: Current | C4: Target | D4: Delta
A5: Beginning ARR | B5: =SUM(Customer_MRR_Data!$H:$H) -> 6395000 | C5: =B5 -> 6395000 | D5: =C5-B5 -> 0
A6: Ending ARR | B6: =SUM(Customer_MRR_Data!$I:$I) -> 5826000 | C6: =B5*Inputs!$B$7 -> 6906600 | D6: =C6-B6 -> 1080600
A7: GRR | B7: =SUM(Customer_MRR_Data!$M:$M)/SUM(Customer_MRR_Data!$H:$H) -> 0.87724785 | C7: =Inputs!$B$8 -> 0.92 | D7: =C7-B7 -> 0.04275215
A8: NRR | B8: =SUM(Customer_MRR_Data!$N:$N)/SUM(Customer_MRR_Data!$H:$H) -> 0.91102424 | C8: =Inputs!$B$7 -> 1.08 | D8: =C8-B8 -> 0.16897576
A9: Incremental ARR from NRR Lift | B9: =0 -> 0 | C9: =SUM(Customer_MRR_Data!$H:$H)*(C8-B8) -> 1080600 | D9: =C9-B9 -> 1080600
A10: Contribution Margin | B10: =Inputs!$B$9 -> 0.7 | C10: =Inputs!$B$9 -> 0.7 | D10: =C10-B10 -> 0
A11: Incremental EBITDA | B11: =0 -> 0 | C11: =C9*C10 -> 756420 | D11: =C11-B11 -> 756420
A12: Exit Multiple | B12: =Inputs!$B$10 -> 12 | C12: =Inputs!$B$10 -> 12 | D12: =C12-B12 -> 0
A13: Enterprise Value Impact | B13: =0 -> 0 | C13: =C11*C12 -> 9077040 | D13: =C13-B13 -> 9077040

Sheet Sources
A1: Sources & Assumptions
A2: Plain-English assumptions and source posture.
A4: Item | B4: Source / Basis | C4: Notes
A5: Sample customer data | B5: Illustrative Ops2EBITDA synthetic dataset | C5: Replace with CRM, billing, customer success, and support exports.
A6: Retention formulas | B6: Standard SaaS / recurring revenue metrics | C6: GRR = gross retained ARR / beginning ARR; NRR = net retained ARR / beginning ARR.
A7: Contribution margin | B7: User input on Inputs sheet | C7: Use incremental contribution margin, not gross margin, where possible.
A8: Exit multiple | B8: User input on Inputs sheet | C8: Use company-specific valuation assumptions or sponsor underwriting case.
A9: Risk scoring | B9: Illustrative logic based on health score, usage, support tickets, and renewal timing | C9: Calibrate to actual churn predictors and business model.
