Workbook

Sheet Dashboard
B1: Ops2EBITDA
B2: Procurement Spend Cube & Savings Tracker
B4: EXECUTIVE PROCUREMENT SNAPSHOT
B5: =EBITDA_Validation!C6 -> 6975760 | D5: =EBITDA_Validation!C7 -> 3502330 | F5: =EBITDA_Validation!C8 -> 302827 | H5: =EBITDA_Validation!C11 -> 212187.72 | J5: =EBITDA_Validation!C12 -> 2121877.2
B8: Total Spend | D8: Addressable Spend | F8: Identified Savings | H8: Validated EBITDA | J8: EV Impact
B10: TOP CATEGORY OPPORTUNITIES | I10: SAVINGS PIPELINE STATUS
B11: Category | C11: Total Spend | D11: Addressable Spend | E11: Maverick Spend | F11: Savings Opportunity | G11: Priority | I11: Status | J11: Gross Savings | K11: Run-Rate EBITDA
B12: Freight & Logistics | C12: =SUMIFS(Spend_Data!$H:$H,Spend_Data!$D:$D,B12) -> 1347530 | D12: =SUMIFS(Spend_Data!$H:$H,Spend_Data!$D:$D,B12,Spend_Data!$K:$K,"Yes") -> 1347530 | E12: =SUMIFS(Spend_Data!$H:$H,Spend_Data!$D:$D,B12,Spend_Data!$N:$N,"Yes") -> 860720 | F12: =SUMIFS(Spend_Data!$P:$P,Spend_Data!$D:$D,B12) -> 107802.4 | G12: =IF(F12>=50000,"High",IF(F12>=15000,"Medium","Low")) -> High | I12: Not Started | J12: =SUMIFS(Savings_Pipeline!$H:$H,Savings_Pipeline!$K:$K,I12) -> 75430.2 | K12: =SUMIFS(Savings_Pipeline!$J:$J,Savings_Pipeline!$K:$K,I12) -> 60344.16
B13: IT Software | C13: =SUMIFS(Spend_Data!$H:$H,Spend_Data!$D:$D,B13) -> 421720 | D13: =SUMIFS(Spend_Data!$H:$H,Spend_Data!$D:$D,B13,Spend_Data!$K:$K,"Yes") -> 421720 | E13: =SUMIFS(Spend_Data!$H:$H,Spend_Data!$D:$D,B13,Spend_Data!$N:$N,"Yes") -> 277970 | F13: =SUMIFS(Spend_Data!$P:$P,Spend_Data!$D:$D,B13) -> 50606.4 | G13: =IF(F13>=50000,"High",IF(F13>=15000,"Medium","Low")) -> High | I13: In Progress | J13: =SUMIFS(Savings_Pipeline!$H:$H,Savings_Pipeline!$K:$K,I13) -> 161395.95 | K13: =SUMIFS(Savings_Pipeline!$J:$J,Savings_Pipeline!$K:$K,I13) -> 129116.76
B14: Packaging | C14: =SUMIFS(Spend_Data!$H:$H,Spend_Data!$D:$D,B14) -> 556150 | D14: =SUMIFS(Spend_Data!$H:$H,Spend_Data!$D:$D,B14,Spend_Data!$K:$K,"Yes") -> 556150 | E14: =SUMIFS(Spend_Data!$H:$H,Spend_Data!$D:$D,B14,Spend_Data!$N:$N,"Yes") -> 317290 | F14: =SUMIFS(Spend_Data!$P:$P,Spend_Data!$D:$D,B14) -> 33369 | G14: =IF(F14>=50000,"High",IF(F14>=15000,"Medium","Low")) -> Medium | I14: At Risk | J14: =SUMIFS(Savings_Pipeline!$H:$H,Savings_Pipeline!$K:$K,I14) -> 0 | K14: =SUMIFS(Savings_Pipeline!$J:$J,Savings_Pipeline!$K:$K,I14) -> 0
B15: Telecom | C15: =SUMIFS(Spend_Data!$H:$H,Spend_Data!$D:$D,B15) -> 189390 | D15: =SUMIFS(Spend_Data!$H:$H,Spend_Data!$D:$D,B15,Spend_Data!$K:$K,"Yes") -> 189390 | E15: =SUMIFS(Spend_Data!$H:$H,Spend_Data!$D:$D,B15,Spend_Data!$N:$N,"Yes") -> 128200 | F15: =SUMIFS(Spend_Data!$P:$P,Spend_Data!$D:$D,B15) -> 28408.5 | G15: =IF(F15>=50000,"High",IF(F15>=15000,"Medium","Low")) -> Medium | I15: Complete | J15: =SUMIFS(Savings_Pipeline!$H:$H,Savings_Pipeline!$K:$K,I15) -> 28408.5 | K15: =SUMIFS(Savings_Pipeline!$J:$J,Savings_Pipeline!$K:$K,I15) -> 22726.8
B16: Raw Materials | C16: =SUMIFS(Spend_Data!$H:$H,Spend_Data!$D:$D,B16) -> 1824420 | D16: =SUMIFS(Spend_Data!$H:$H,Spend_Data!$D:$D,B16,Spend_Data!$K:$K,"Yes") -> 561930 | E16: =SUMIFS(Spend_Data!$H:$H,Spend_Data!$D:$D,B16,Spend_Data!$N:$N,"Yes") -> 666330 | F16: =SUMIFS(Spend_Data!$P:$P,Spend_Data!$D:$D,B16) -> 28096.5 | G16: =IF(F16>=50000,"High",IF(F16>=15000,"Medium","Low")) -> Medium
B17: Facilities | C17: =SUMIFS(Spend_Data!$H:$H,Spend_Data!$D:$D,B17) -> 275820 | D17: =SUMIFS(Spend_Data!$H:$H,Spend_Data!$D:$D,B17,Spend_Data!$K:$K,"Yes") -> 275820 | E17: =SUMIFS(Spend_Data!$H:$H,Spend_Data!$D:$D,B17,Spend_Data!$N:$N,"Yes") -> 183980 | F17: =SUMIFS(Spend_Data!$P:$P,Spend_Data!$D:$D,B17) -> 27582 | G17: =IF(F17>=50000,"High",IF(F17>=15000,"Medium","Low")) -> Medium

Sheet Instructions
A1: How to Use This Model
A2: Procurement spend cube and savings tracker workflow.
A4: Step | B4: Action | C4: Notes
A5: 1 | B5: Replace sample data in Spend_Data | C5: Paste AP/PO export fields into columns A:M. Keep derived formula columns N:R.
A6: 2 | B6: Update assumptions in Inputs | C6: Adjust EBITDA multiple, realization rate, consolidation capture, and category savings rates.
A7: 3 | B7: Review Spend_Cube | C7: Use category, site, and vendor cuts to identify concentration, maverick spend, and savings opportunity.
A8: 4 | B8: Prioritize Vendor_Consolidation | C8: Focus on categories with high tail spend, many vendors, and meaningful estimated savings.
A9: 5 | B9: Build Savings_Pipeline | C9: Convert opportunities into owned initiatives with status, dates, and run-rate EBITDA impact.
A10: 6 | B10: Validate EBITDA | C10: Use EBITDA_Validation to separate gross opportunity from realized run-rate impact and EV impact.
A11: 7 | B11: Use Dashboard for executive readout | C11: Summarize the opportunity set, savings pipeline, and impact story for management or board discussion.

Sheet Inputs
A1: Ops2EBITDA Procurement Spend Cube & Savings Tracker
A2: Editable model assumptions and category savings benchmarks.
A4: Assumption | B4: Value | C4: Notes
A5: EBITDA Multiple | B5: 10 | C5: Used to translate run-rate savings into enterprise value impact
A6: Benefit Realization Rate | B6: 0.8 | C6: Portion of identified savings expected to hit EBITDA
A7: Maverick Spend Savings Rate | B7: 0.1 | C7: Default savings rate on non-contract / non-preferred spend
A8: Vendor Consolidation Capture | B8: 0.6 | C8: Percent of tail spend that can be consolidated into preferred vendors
A9: Minimum Addressable Spend Threshold | B9: 50000 | C9: Used to filter small opportunities
A10: Run-Rate Conversion Months | B10: 12 | C10: Months used for annualized EBITDA impact
A12: CATEGORY BENCHMARKS
A13: Category | B13: Spend Type | C13: Default Savings Rate | D13: Primary Lever | E13: Addressability Notes
A14: Freight & Logistics | B14: Direct | C14: 0.08 | D14: Carrier rebid / route optimization | E14: Addressable if not core supply risk
A15: Raw Materials | B15: Direct | C15: 0.05 | D15: Supplier negotiation / should-cost | E15: Addressable if not core supply risk
A16: Packaging | B16: Direct | C16: 0.06 | D16: Specification standardization | E16: Addressable if not core supply risk
A17: IT Software | B17: Indirect | C17: 0.12 | D17: License rationalization / vendor consolidation | E17: Addressable if not core supply risk
A18: Telecom | B18: Indirect | C18: 0.15 | D18: Plan consolidation / contract rebid | E18: Addressable if not core supply risk
A19: Facilities | B19: Indirect | C19: 0.1 | D19: Scope standardization / site consolidation | E19: Addressable if not core supply risk
A20: Professional Services | B20: Indirect | C20: 0.09 | D20: Demand management / panel rates | E20: Validate carefully; may be relationship or quality constrained
A21: Temp Labor | B21: Indirect | C21: 0.07 | D21: Vendor consolidation / mark-up reduction | E21: Validate carefully; may be relationship or quality constrained
A22: Office Supplies | B22: Indirect | C22: 0.18 | D22: Catalog control / preferred vendor | E22: Addressable if not core supply risk
A23: MRO | B23: Direct | C23: 0.06 | D23: SKU rationalization / preferred suppliers | E23: Validate carefully; may be relationship or quality constrained

Sheet Spend_Data
A1: Spend Data
A2: Sample invoice-level third-party spend data. Replace sample rows with AP/PO export data.
A4: Invoice ID | B4: Invoice Date | C4: Vendor | D4: Category | E4: Spend Type | F4: Site | G4: Business Unit | H4: Spend | I4: Under Contract? | J4: Preferred Vendor? | K4: Addressable? | L4: Default Savings Rate | M4: Owner | N4: Maverick? | O4: Tail Vendor? | P4: Savings Opportunity | Q4: Savings Type | R4: Priority
A5: 1 | B5: 45991 | C5: BoxWorks | D5: Packaging | E5: Direct | F5: Chicago | G5: Field Operations | H5: 9450 | I5: Yes | J5: Yes | K5: Yes | L5: 0.06 | M5: COO | N5: =IF(OR(I5="No",J5="No"),"Yes","No") -> No | O5: =IF(COUNTIFS($C:$C,C5)<5,"Yes","No") -> No | P5: =IF(K5="Yes",H5*L5,0) -> 567 | Q5: =IF(N5="Yes","Maverick / non-preferred",IF(O5="Yes","Tail consolidation",IF(K5="Yes","Category sourcing","Non-addressable"))) -> Category sourcing | R5: =IF(P5>=10000,"High",IF(P5>=3000,"Medium","Low")) -> Low
A6: 2 | B6: 45940 | C6: Summit Polymers | D6: Raw Materials | E6: Direct | F6: Atlanta | G6: Manufacturing | H6: 25130 | I6: Yes | J6: Yes | K6: No | L6: 0.05 | M6: COO | N6: =IF(OR(I6="No",J6="No"),"Yes","No") -> No | O6: =IF(COUNTIFS($C:$C,C6)<5,"Yes","No") -> No | P6: =IF(K6="Yes",H6*L6,0) -> 0 | Q6: =IF(N6="Yes","Maverick / non-preferred",IF(O6="Yes","Tail consolidation",IF(K6="Yes","Category sourcing","Non-addressable"))) -> Non-addressable | R6: =IF(P6>=10000,"High",IF(P6>=3000,"Medium","Low")) -> Low
A7: 3 | B7: 45715 | C7: Regional LTL | D7: Freight & Logistics | E7: Direct | F7: Chicago | G7: Corporate | H7: 20730 | I7: No | J7: No | K7: Yes | L7: 0.08 | M7: COO | N7: =IF(OR(I7="No",J7="No"),"Yes","No") -> Yes | O7: =IF(COUNTIFS($C:$C,C7)<5,"Yes","No") -> No | P7: =IF(K7="Yes",H7*L7,0) -> 1658.4 | Q7: =IF(N7="Yes","Maverick / non-preferred",IF(O7="Yes","Tail consolidation",IF(K7="Yes","Category sourcing","Non-addressable"))) -> Maverick / non-preferred | R7: =IF(P7>=10000,"High",IF(P7>=3000,"Medium","Low")) -> Low
A8: 4 | B8: 45991 | C8: PartsPlus | D8: MRO | E8: Direct | F8: Atlanta | G8: Corporate | H8: 3320 | I8: Yes | J8: Yes | K8: No | L8: 0.06 | M8: COO | N8: =IF(OR(I8="No",J8="No"),"Yes","No") -> No | O8: =IF(COUNTIFS($C:$C,C8)<5,"Yes","No") -> No | P8: =IF(K8="Yes",H8*L8,0) -> 0 | Q8: =IF(N8="Yes","Maverick / non-preferred",IF(O8="Yes","Tail consolidation",IF(K8="Yes","Category sourcing","Non-addressable"))) -> Non-addressable | R8: =IF(P8>=10000,"High",IF(P8>=3000,"Medium","Low")) -> Low
A9: 5 | B9: 45674 | C9: MobileWorks | D9: Telecom | E9: Indirect | F9: Dallas | G9: Field Operations | H9: 1450 | I9: No | J9: No | K9: Yes | L9: 0.15 | M9: CIO | N9: =IF(OR(I9="No",J9="No"),"Yes","No") -> Yes | O9: =IF(COUNTIFS($C:$C,C9)<5,"Yes","No") -> No | P9: =IF(K9="Yes",H9*L9,0) -> 217.5 | Q9: =IF(N9="Yes","Maverick / non-preferred",IF(O9="Yes","Tail consolidation",IF(K9="Yes","Category sourcing","Non-addressable"))) -> Maverick / non-preferred | R9: =IF(P9>=10000,"High",IF(P9>=3000,"Medium","Low")) -> Low
A10: 6 | B10: 45752 | C10: MobileWorks | D10: Telecom | E10: Indirect | F10: Columbus | G10: Field Operations | H10: 870 | I10: No | J10: No | K10: Yes | L10: 0.15 | M10: CIO | N10: =IF(OR(I10="No",J10="No"),"Yes","No") -> Yes | O10: =IF(COUNTIFS($C:$C,C10)<5,"Yes","No") -> No | P10: =IF(K10="Yes",H10*L10,0) -> 130.5 | Q10: =IF(N10="Yes","Maverick / non-preferred",IF(O10="Yes","Tail consolidation",IF(K10="Yes","Category sourcing","Non-addressable"))) -> Maverick / non-preferred | R10: =IF(P10>=10000,"High",IF(P10>=3000,"Medium","Low")) -> Low
A11: 7 | B11: 45936 | C11: FacilityOne | D11: Facilities | E11: Indirect | F11: Columbus | G11: Manufacturing | H11: 4200 | I11: Yes | J11: Yes | K11: Yes | L11: 0.1 | M11: COO | N11: =IF(OR(I11="No",J11="No"),"Yes","No") -> No | O11: =IF(COUNTIFS($C:$C,C11)<5,"Yes","No") -> No | P11: =IF(K11="Yes",H11*L11,0) -> 420 | Q11: =IF(N11="Yes","Maverick / non-preferred",IF(O11="Yes","Tail consolidation",IF(K11="Yes","Category sourcing","Non-addressable"))) -> Category sourcing | R11: =IF(P11>=10000,"High",IF(P11>=3000,"Medium","Low")) -> Low
A12: 8 | B12: 45879 | C12: Workplace Mart | D12: Office Supplies | E12: Indirect | F12: Chicago | G12: Manufacturing | H12: 9430 | I12: No | J12: No | K12: Yes | L12: 0.18 | M12: CFO | N12: =IF(OR(I12="No",J12="No"),"Yes","No") -> Yes | O12: =IF(COUNTIFS($C:$C,C12)<5,"Yes","No") -> No | P12: =IF(K12="Yes",H12*L12,0) -> 1697.4 | Q12: =IF(N12="Yes","Maverick / non-preferred",IF(O12="Yes","Tail consolidation",IF(K12="Yes","Category sourcing","Non-addressable"))) -> Maverick / non-preferred | R12: =IF(P12>=10000,"High",IF(P12>=3000,"Medium","Low")) -> Low
A13: 9 | B13: 45757 | C13: NorthLine Freight | D13: Freight & Logistics | E13: Direct | F13: Columbus | G13: Distribution | H13: 24310 | I13: Yes | J13: Yes | K13: Yes | L13: 0.08 | M13: COO | N13: =IF(OR(I13="No",J13="No"),"Yes","No") -> No | O13: =IF(COUNTIFS($C:$C,C13)<5,"Yes","No") -> No | P13: =IF(K13="Yes",H13*L13,0) -> 1944.8 | Q13: =IF(N13="Yes","Maverick / non-preferred",IF(O13="Yes","Tail consolidation",IF(K13="Yes","Category sourcing","Non-addressable"))) -> Category sourcing | R13: =IF(P13>=10000,"High",IF(P13>=3000,"Medium","Low")) -> Low
A14: 10 | B14: 45755 | C14: Workplace Mart | D14: Office Supplies | E14: Indirect | F14: Atlanta | G14: Distribution | H14: 2480 | I14: No | J14: No | K14: Yes | L14: 0.18 | M14: CFO | N14: =IF(OR(I14="No",J14="No"),"Yes","No") -> Yes | O14: =IF(COUNTIFS($C:$C,C14)<5,"Yes","No") -> No | P14: =IF(K14="Yes",H14*L14,0) -> 446.4 | Q14: =IF(N14="Yes","Maverick / non-preferred",IF(O14="Yes","Tail consolidation",IF(K14="Yes","Category sourcing","Non-addressable"))) -> Maverick / non-preferred | R14: =IF(P14>=10000,"High",IF(P14>=3000,"Medium","Low")) -> Low
A15: 11 | B15: 45757 | C15: Prime Components | D15: Raw Materials | E15: Direct | F15: Dallas | G15: Distribution | H15: 56220 | I15: No | J15: No | K15: No | L15: 0.05 | M15: COO | N15: =IF(OR(I15="No",J15="No"),"Yes","No") -> Yes | O15: =IF(COUNTIFS($C:$C,C15)<5,"Yes","No") -> No | P15: =IF(K15="Yes",H15*L15,0) -> 0 | Q15: =IF(N15="Yes","Maverick / non-preferred",IF(O15="Yes","Tail consolidation",IF(K15="Yes","Category sourcing","Non-addressable"))) -> Maverick / non-preferred | R15: =IF(P15>=10000,"High",IF(P15>=3000,"Medium","Low")) -> Low
A16: 12 | B16: 45957 | C16: ToolWorks | D16: MRO | E16: Direct | F16: Chicago | G16: Manufacturing | H16: 9960 | I16: No | J16: No | K16: No | L16: 0.06 | M16: COO | N16: =IF(OR(I16="No",J16="No"),"Yes","No") -> Yes | O16: =IF(COUNTIFS($C:$C,C16)<5,"Yes","No") -> No | P16: =IF(K16="Yes",H16*L16,0) -> 0 | Q16: =IF(N16="Yes","Maverick / non-preferred",IF(O16="Yes","Tail consolidation",IF(K16="Yes","Category sourcing","Non-addressable"))) -> Maverick / non-preferred | R16: =IF(P16>=10000,"High",IF(P16>=3000,"Medium","Low")) -> Low
... A304: 300 | B304: 45968 | C304: SecureWrap | D304: Packaging | E304: Direct | F304: Atlanta | G304: Field Operations | H304: 48550 | I304: No | J304: No | K304: Yes | L304: 0.06 | M304: COO | N304: =IF(OR(I304="No",J304="No"),"Yes","No") -> Yes | O304: =IF(COUNTIFS($C:$C,C304)<5,"Yes","No") -> No | P304: =IF(K304="Yes",H304*L304,0) -> 2913 | Q304: =IF(N304="Yes","Maverick / non-preferred",IF(O304="Yes","Tail consolidation",IF(K304="Yes","Category sourcing","Non-addressable"))) -> Maverick / non-preferred | R304: =IF(P304>=10000,"High",IF(P304>=3000,"Medium","Low")) -> Low

Sheet Spend_Cube
A1: Spend Cube
A2: Vendor, category, and site cuts to isolate addressable spend and opportunity concentration.
A4: CATEGORY CUT | J4: TOP VENDOR CUT
A5: Category | B5: Total Spend | C5: Addressable Spend | D5: Maverick Spend | E5: # Vendors | F5: Savings Opportunity | G5: % of Total Spend | H5: Avg Savings Rate | J5: Vendor | K5: Total Spend | L5: Addressable Spend | M5: Maverick Spend | N5: Savings Opportunity | O5: Preferred? | P5: Primary Category
A6: Freight & Logistics | B6: =SUMIFS(Spend_Data!$H:$H,Spend_Data!$D:$D,A6) -> 1347530 | C6: =SUMIFS(Spend_Data!$H:$H,Spend_Data!$D:$D,A6,Spend_Data!$K:$K,"Yes") -> 1347530 | D6: =SUMIFS(Spend_Data!$H:$H,Spend_Data!$D:$D,A6,Spend_Data!$N:$N,"Yes") -> 860720 | E6: 5 | F6: =SUMIFS(Spend_Data!$P:$P,Spend_Data!$D:$D,A6) -> 107802.4 | G6: =B6/SUM($B$6:$B$15) -> 0.19317322 | H6: =IFERROR(F6/C6,0) -> 0.08 | J6: Summit Polymers | K6: =SUMIFS(Spend_Data!$H:$H,Spend_Data!$C:$C,J6) -> 715090 | L6: =SUMIFS(Spend_Data!$H:$H,Spend_Data!$C:$C,J6,Spend_Data!$K:$K,"Yes") -> 301130 | M6: =SUMIFS(Spend_Data!$H:$H,Spend_Data!$C:$C,J6,Spend_Data!$N:$N,"Yes") -> 0 | N6: =SUMIFS(Spend_Data!$P:$P,Spend_Data!$C:$C,J6) -> 15056.5 | O6: =IF(COUNTIFS(Spend_Data!$C:$C,J6,Spend_Data!$J:$J,"Yes")>0,"Yes","No") -> Yes | P6: =INDEX(Spend_Data!$D:$D,MATCH(J6,Spend_Data!$C:$C,0)) -> Raw Materials
A7: Raw Materials | B7: =SUMIFS(Spend_Data!$H:$H,Spend_Data!$D:$D,A7) -> 1824420 | C7: =SUMIFS(Spend_Data!$H:$H,Spend_Data!$D:$D,A7,Spend_Data!$K:$K,"Yes") -> 561930 | D7: =SUMIFS(Spend_Data!$H:$H,Spend_Data!$D:$D,A7,Spend_Data!$N:$N,"Yes") -> 666330 | E7: 5 | F7: =SUMIFS(Spend_Data!$P:$P,Spend_Data!$D:$D,A7) -> 28096.5 | G7: =B7/SUM($B$6:$B$15) -> 0.26153709 | H7: =IFERROR(F7/C7,0) -> 0.05 | J7: BrandNorth | K7: =SUMIFS(Spend_Data!$H:$H,Spend_Data!$C:$C,J7) -> 490700 | L7: =SUMIFS(Spend_Data!$H:$H,Spend_Data!$C:$C,J7,Spend_Data!$K:$K,"Yes") -> 0 | M7: =SUMIFS(Spend_Data!$H:$H,Spend_Data!$C:$C,J7,Spend_Data!$N:$N,"Yes") -> 490700 | N7: =SUMIFS(Spend_Data!$P:$P,Spend_Data!$C:$C,J7) -> 0 | O7: =IF(COUNTIFS(Spend_Data!$C:$C,J7,Spend_Data!$J:$J,"Yes")>0,"Yes","No") -> No | P7: =INDEX(Spend_Data!$D:$D,MATCH(J7,Spend_Data!$C:$C,0)) -> Professional Services
A8: Packaging | B8: =SUMIFS(Spend_Data!$H:$H,Spend_Data!$D:$D,A8) -> 556150 | C8: =SUMIFS(Spend_Data!$H:$H,Spend_Data!$D:$D,A8,Spend_Data!$K:$K,"Yes") -> 556150 | D8: =SUMIFS(Spend_Data!$H:$H,Spend_Data!$D:$D,A8,Spend_Data!$N:$N,"Yes") -> 317290 | E8: 5 | F8: =SUMIFS(Spend_Data!$P:$P,Spend_Data!$D:$D,A8) -> 33369 | G8: =B8/SUM($B$6:$B$15) -> 0.07972608 | H8: =IFERROR(F8/C8,0) -> 0.06 | J8: CoreMetals | K8: =SUMIFS(Spend_Data!$H:$H,Spend_Data!$C:$C,J8) -> 443000 | L8: =SUMIFS(Spend_Data!$H:$H,Spend_Data!$C:$C,J8,Spend_Data!$K:$K,"Yes") -> 89540 | M8: =SUMIFS(Spend_Data!$H:$H,Spend_Data!$C:$C,J8,Spend_Data!$N:$N,"Yes") -> 0 | N8: =SUMIFS(Spend_Data!$P:$P,Spend_Data!$C:$C,J8) -> 4477 | O8: =IF(COUNTIFS(Spend_Data!$C:$C,J8,Spend_Data!$J:$J,"Yes")>0,"Yes","No") -> Yes | P8: =INDEX(Spend_Data!$D:$D,MATCH(J8,Spend_Data!$C:$C,0)) -> Raw Materials
A9: IT Software | B9: =SUMIFS(Spend_Data!$H:$H,Spend_Data!$D:$D,A9) -> 421720 | C9: =SUMIFS(Spend_Data!$H:$H,Spend_Data!$D:$D,A9,Spend_Data!$K:$K,"Yes") -> 421720 | D9: =SUMIFS(Spend_Data!$H:$H,Spend_Data!$D:$D,A9,Spend_Data!$N:$N,"Yes") -> 277970 | E9: 5 | F9: =SUMIFS(Spend_Data!$P:$P,Spend_Data!$D:$D,A9) -> 50606.4 | G9: =B9/SUM($B$6:$B$15) -> 0.060455062 | H9: =IFERROR(F9/C9,0) -> 0.12 | J9: ShipMax | K9: =SUMIFS(Spend_Data!$H:$H,Spend_Data!$C:$C,J9) -> 332940 | L9: =SUMIFS(Spend_Data!$H:$H,Spend_Data!$C:$C,J9,Spend_Data!$K:$K,"Yes") -> 332940 | M9: =SUMIFS(Spend_Data!$H:$H,Spend_Data!$C:$C,J9,Spend_Data!$N:$N,"Yes") -> 27550 | N9: =SUMIFS(Spend_Data!$P:$P,Spend_Data!$C:$C,J9) -> 26635.2 | O9: =IF(COUNTIFS(Spend_Data!$C:$C,J9,Spend_Data!$J:$J,"Yes")>0,"Yes","No") -> Yes | P9: =INDEX(Spend_Data!$D:$D,MATCH(J9,Spend_Data!$C:$C,0)) -> Freight & Logistics
A10: Telecom | B10: =SUMIFS(Spend_Data!$H:$H,Spend_Data!$D:$D,A10) -> 189390 | C10: =SUMIFS(Spend_Data!$H:$H,Spend_Data!$D:$D,A10,Spend_Data!$K:$K,"Yes") -> 189390 | D10: =SUMIFS(Spend_Data!$H:$H,Spend_Data!$D:$D,A10,Spend_Data!$N:$N,"Yes") -> 128200 | E10: 4 | F10: =SUMIFS(Spend_Data!$P:$P,Spend_Data!$D:$D,A10) -> 28408.5 | G10: =B10/SUM($B$6:$B$15) -> 0.02714973 | H10: =IFERROR(F10/C10,0) -> 0.15 | J10: LaborFlex | K10: =SUMIFS(Spend_Data!$H:$H,Spend_Data!$C:$C,J10) -> 307200 | L10: =SUMIFS(Spend_Data!$H:$H,Spend_Data!$C:$C,J10,Spend_Data!$K:$K,"Yes") -> 0 | M10: =SUMIFS(Spend_Data!$H:$H,Spend_Data!$C:$C,J10,Spend_Data!$N:$N,"Yes") -> 0 | N10: =SUMIFS(Spend_Data!$P:$P,Spend_Data!$C:$C,J10) -> 0 | O10: =IF(COUNTIFS(Spend_Data!$C:$C,J10,Spend_Data!$J:$J,"Yes")>0,"Yes","No") -> Yes | P10: =INDEX(Spend_Data!$D:$D,MATCH(J10,Spend_Data!$C:$C,0)) -> Temp Labor
A11: Facilities | B11: =SUMIFS(Spend_Data!$H:$H,Spend_Data!$D:$D,A11) -> 275820 | C11: =SUMIFS(Spend_Data!$H:$H,Spend_Data!$D:$D,A11,Spend_Data!$K:$K,"Yes") -> 275820 | D11: =SUMIFS(Spend_Data!$H:$H,Spend_Data!$D:$D,A11,Spend_Data!$N:$N,"Yes") -> 183980 | E11: 5 | F11: =SUMIFS(Spend_Data!$P:$P,Spend_Data!$D:$D,A11) -> 27582 | G11: =B11/SUM($B$6:$B$15) -> 0.039539778 | H11: =IFERROR(F11/C11,0) -> 0.1 | J11: Regional LTL | K11: =SUMIFS(Spend_Data!$H:$H,Spend_Data!$C:$C,J11) -> 274550 | L11: =SUMIFS(Spend_Data!$H:$H,Spend_Data!$C:$C,J11,Spend_Data!$K:$K,"Yes") -> 274550 | M11: =SUMIFS(Spend_Data!$H:$H,Spend_Data!$C:$C,J11,Spend_Data!$N:$N,"Yes") -> 274550 | N11: =SUMIFS(Spend_Data!$P:$P,Spend_Data!$C:$C,J11) -> 21964 | O11: =IF(COUNTIFS(Spend_Data!$C:$C,J11,Spend_Data!$J:$J,"Yes")>0,"Yes","No") -> No | P11: =INDEX(Spend_Data!$D:$D,MATCH(J11,Spend_Data!$C:$C,0)) -> Freight & Logistics
A12: Professional Services | B12: =SUMIFS(Spend_Data!$H:$H,Spend_Data!$D:$D,A12) -> 1118320 | C12: =SUMIFS(Spend_Data!$H:$H,Spend_Data!$D:$D,A12,Spend_Data!$K:$K,"Yes") -> 0 | D12: =SUMIFS(Spend_Data!$H:$H,Spend_Data!$D:$D,A12,Spend_Data!$N:$N,"Yes") -> 1013850 | E12: 5 | F12: =SUMIFS(Spend_Data!$P:$P,Spend_Data!$D:$D,A12) -> 0 | G12: =B12/SUM($B$6:$B$15) -> 0.16031515 | H12: =IFERROR(F12/C12,0) -> 0 | J12: RoadPro Logistics | K12: =SUMIFS(Spend_Data!$H:$H,Spend_Data!$C:$C,J12) -> 271350 | L12: =SUMIFS(Spend_Data!$H:$H,Spend_Data!$C:$C,J12,Spend_Data!$K:$K,"Yes") -> 271350 | M12: =SUMIFS(Spend_Data!$H:$H,Spend_Data!$C:$C,J12,Spend_Data!$N:$N,"Yes") -> 271350 | N12: =SUMIFS(Spend_Data!$P:$P,Spend_Data!$C:$C,J12) -> 21708 | O12: =IF(COUNTIFS(Spend_Data!$C:$C,J12,Spend_Data!$J:$J,"Yes")>0,"Yes","No") -> No | P12: =INDEX(Spend_Data!$D:$D,MATCH(J12,Spend_Data!$C:$C,0)) -> Freight & Logistics
A13: Temp Labor | B13: =SUMIFS(Spend_Data!$H:$H,Spend_Data!$D:$D,A13) -> 724250 | C13: =SUMIFS(Spend_Data!$H:$H,Spend_Data!$D:$D,A13,Spend_Data!$K:$K,"Yes") -> 0 | D13: =SUMIFS(Spend_Data!$H:$H,Spend_Data!$D:$D,A13,Spend_Data!$N:$N,"Yes") -> 417050 | E13: 4 | F13: =SUMIFS(Spend_Data!$P:$P,Spend_Data!$D:$D,A13) -> 0 | G13: =B13/SUM($B$6:$B$15) -> 0.10382381 | H13: =IFERROR(F13/C13,0) -> 0 | J13: Prime Components | K13: =SUMIFS(Spend_Data!$H:$H,Spend_Data!$C:$C,J13) -> 269790 | L13: =SUMIFS(Spend_Data!$H:$H,Spend_Data!$C:$C,J13,Spend_Data!$K:$K,"Yes") -> 32470 | M13: =SUMIFS(Spend_Data!$H:$H,Spend_Data!$C:$C,J13,Spend_Data!$N:$N,"Yes") -> 269790 | N13: =SUMIFS(Spend_Data!$P:$P,Spend_Data!$C:$C,J13) -> 1623.5 | O13: =IF(COUNTIFS(Spend_Data!$C:$C,J13,Spend_Data!$J:$J,"Yes")>0,"Yes","No") -> No | P13: =INDEX(Spend_Data!$D:$D,MATCH(J13,Spend_Data!$C:$C,0)) -> Raw Materials
A14: Office Supplies | B14: =SUMIFS(Spend_Data!$H:$H,Spend_Data!$D:$D,A14) -> 149790 | C14: =SUMIFS(Spend_Data!$H:$H,Spend_Data!$D:$D,A14,Spend_Data!$K:$K,"Yes") -> 149790 | D14: =SUMIFS(Spend_Data!$H:$H,Spend_Data!$D:$D,A14,Spend_Data!$N:$N,"Yes") -> 109430 | E14: 4 | F14: =SUMIFS(Spend_Data!$P:$P,Spend_Data!$D:$D,A14) -> 26962.2 | G14: =B14/SUM($B$6:$B$15) -> 0.021472929 | H14: =IFERROR(F14/C14,0) -> 0.18 | J14: ShiftPro | K14: =SUMIFS(Spend_Data!$H:$H,Spend_Data!$C:$C,J14) -> 266530 | L14: =SUMIFS(Spend_Data!$H:$H,Spend_Data!$C:$C,J14,Spend_Data!$K:$K,"Yes") -> 0 | M14: =SUMIFS(Spend_Data!$H:$H,Spend_Data!$C:$C,J14,Spend_Data!$N:$N,"Yes") -> 266530 | N14: =SUMIFS(Spend_Data!$P:$P,Spend_Data!$C:$C,J14) -> 0 | O14: =IF(COUNTIFS(Spend_Data!$C:$C,J14,Spend_Data!$J:$J,"Yes")>0,"Yes","No") -> No | P14: =INDEX(Spend_Data!$D:$D,MATCH(J14,Spend_Data!$C:$C,0)) -> Temp Labor
A15: MRO | B15: =SUMIFS(Spend_Data!$H:$H,Spend_Data!$D:$D,A15) -> 368370 | C15: =SUMIFS(Spend_Data!$H:$H,Spend_Data!$D:$D,A15,Spend_Data!$K:$K,"Yes") -> 0 | D15: =SUMIFS(Spend_Data!$H:$H,Spend_Data!$D:$D,A15,Spend_Data!$N:$N,"Yes") -> 172190 | E15: 5 | F15: =SUMIFS(Spend_Data!$P:$P,Spend_Data!$D:$D,A15) -> 0 | G15: =B15/SUM($B$6:$B$15) -> 0.052807149 | H15: =IFERROR(F15/C15,0) -> 0 | J15: FastLane Carriers | K15: =SUMIFS(Spend_Data!$H:$H,Spend_Data!$C:$C,J15) -> 254010 | L15: =SUMIFS(Spend_Data!$H:$H,Spend_Data!$C:$C,J15,Spend_Data!$K:$K,"Yes") -> 254010 | M15: =SUMIFS(Spend_Data!$H:$H,Spend_Data!$C:$C,J15,Spend_Data!$N:$N,"Yes") -> 254010 | N15: =SUMIFS(Spend_Data!$P:$P,Spend_Data!$C:$C,J15) -> 20320.8 | O15: =IF(COUNTIFS(Spend_Data!$C:$C,J15,Spend_Data!$J:$J,"Yes")>0,"Yes","No") -> No | P15: =INDEX(Spend_Data!$D:$D,MATCH(J15,Spend_Data!$C:$C,0)) -> Freight & Logistics
J16: LegalWorks | K16: =SUMIFS(Spend_Data!$H:$H,Spend_Data!$C:$C,J16) -> 244360 | L16: =SUMIFS(Spend_Data!$H:$H,Spend_Data!$C:$C,J16,Spend_Data!$K:$K,"Yes") -> 0 | M16: =SUMIFS(Spend_Data!$H:$H,Spend_Data!$C:$C,J16,Spend_Data!$N:$N,"Yes") -> 244360 | N16: =SUMIFS(Spend_Data!$P:$P,Spend_Data!$C:$C,J16) -> 0 | O16: =IF(COUNTIFS(Spend_Data!$C:$C,J16,Spend_Data!$J:$J,"Yes")>0,"Yes","No") -> No | P16: =INDEX(Spend_Data!$D:$D,MATCH(J16,Spend_Data!$C:$C,0)) -> Professional Services
J17: United Materials | K17: =SUMIFS(Spend_Data!$H:$H,Spend_Data!$C:$C,J17) -> 225350 | L17: =SUMIFS(Spend_Data!$H:$H,Spend_Data!$C:$C,J17,Spend_Data!$K:$K,"Yes") -> 104540 | M17: =SUMIFS(Spend_Data!$H:$H,Spend_Data!$C:$C,J17,Spend_Data!$N:$N,"Yes") -> 225350 | N17: =SUMIFS(Spend_Data!$P:$P,Spend_Data!$C:$C,J17) -> 5227 | O17: =IF(COUNTIFS(Spend_Data!$C:$C,J17,Spend_Data!$J:$J,"Yes")>0,"Yes","No") -> No | P17: =INDEX(Spend_Data!$D:$D,MATCH(J17,Spend_Data!$C:$C,0)) -> Raw Materials
A18: SITE CUT | J18: NorthLine Freight | K18: =SUMIFS(Spend_Data!$H:$H,Spend_Data!$C:$C,J18) -> 214680 | L18: =SUMIFS(Spend_Data!$H:$H,Spend_Data!$C:$C,J18,Spend_Data!$K:$K,"Yes") -> 214680 | M18: =SUMIFS(Spend_Data!$H:$H,Spend_Data!$C:$C,J18,Spend_Data!$N:$N,"Yes") -> 33260 | N18: =SUMIFS(Spend_Data!$P:$P,Spend_Data!$C:$C,J18) -> 17174.4 | O18: =IF(COUNTIFS(Spend_Data!$C:$C,J18,Spend_Data!$J:$J,"Yes")>0,"Yes","No") -> Yes | P18: =INDEX(Spend_Data!$D:$D,MATCH(J18,Spend_Data!$C:$C,0)) -> Freight & Logistics
A19: Site | B19: Total Spend | C19: Addressable Spend | D19: Maverick Spend | E19: Savings Opportunity | F19: % of Total Spend | J19: Allied Inputs | K19: =SUMIFS(Spend_Data!$H:$H,Spend_Data!$C:$C,J19) -> 171190 | L19: =SUMIFS(Spend_Data!$H:$H,Spend_Data!$C:$C,J19,Spend_Data!$K:$K,"Yes") -> 34250 | M19: =SUMIFS(Spend_Data!$H:$H,Spend_Data!$C:$C,J19,Spend_Data!$N:$N,"Yes") -> 171190 | N19: =SUMIFS(Spend_Data!$P:$P,Spend_Data!$C:$C,J19) -> 1712.5 | O19: =IF(COUNTIFS(Spend_Data!$C:$C,J19,Spend_Data!$J:$J,"Yes")>0,"Yes","No") -> No | P19: =INDEX(Spend_Data!$D:$D,MATCH(J19,Spend_Data!$C:$C,0)) -> Raw Materials
A20: Chicago | B20: =SUMIFS(Spend_Data!$H:$H,Spend_Data!$F:$F,A20) -> 1639390 | C20: =SUMIFS(Spend_Data!$H:$H,Spend_Data!$F:$F,A20,Spend_Data!$K:$K,"Yes") -> 663290 | D20: =SUMIFS(Spend_Data!$H:$H,Spend_Data!$F:$F,A20,Spend_Data!$N:$N,"Yes") -> 757400 | E20: =SUMIFS(Spend_Data!$P:$P,Spend_Data!$F:$F,A20) -> 58079.4 | F20: =B20/SUM($B$20:$B$24) -> 0.23501239 | J20: BoxWorks | K20: =SUMIFS(Spend_Data!$H:$H,Spend_Data!$C:$C,J20) -> 163280 | L20: =SUMIFS(Spend_Data!$H:$H,Spend_Data!$C:$C,J20,Spend_Data!$K:$K,"Yes") -> 163280 | M20: =SUMIFS(Spend_Data!$H:$H,Spend_Data!$C:$C,J20,Spend_Data!$N:$N,"Yes") -> 0 | N20: =SUMIFS(Spend_Data!$P:$P,Spend_Data!$C:$C,J20) -> 9796.8 | O20: =IF(COUNTIFS(Spend_Data!$C:$C,J20,Spend_Data!$J:$J,"Yes")>0,"Yes","No") -> Yes | P20: =INDEX(Spend_Data!$D:$D,MATCH(J20,Spend_Data!$C:$C,0)) -> Packaging
A21: Dallas | B21: =SUMIFS(Spend_Data!$H:$H,Spend_Data!$F:$F,A21) -> 1105350 | C21: =SUMIFS(Spend_Data!$H:$H,Spend_Data!$F:$F,A21,Spend_Data!$K:$K,"Yes") -> 514430 | D21: =SUMIFS(Spend_Data!$H:$H,Spend_Data!$F:$F,A21,Spend_Data!$N:$N,"Yes") -> 706780 | E21: =SUMIFS(Spend_Data!$P:$P,Spend_Data!$F:$F,A21) -> 48824.9 | F21: =B21/SUM($B$20:$B$24) -> 0.15845585
A22: Atlanta | B22: =SUMIFS(Spend_Data!$H:$H,Spend_Data!$F:$F,A22) -> 1363050 | C22: =SUMIFS(Spend_Data!$H:$H,Spend_Data!$F:$F,A22,Spend_Data!$K:$K,"Yes") -> 978550 | D22: =SUMIFS(Spend_Data!$H:$H,Spend_Data!$F:$F,A22,Spend_Data!$N:$N,"Yes") -> 1040740 | E22: =SUMIFS(Spend_Data!$P:$P,Spend_Data!$F:$F,A22) -> 79474.2 | F22: =B22/SUM($B$20:$B$24) -> 0.19539806
A23: Phoenix | B23: =SUMIFS(Spend_Data!$H:$H,Spend_Data!$F:$F,A23) -> 1272650 | C23: =SUMIFS(Spend_Data!$H:$H,Spend_Data!$F:$F,A23,Spend_Data!$K:$K,"Yes") -> 596600 | D23: =SUMIFS(Spend_Data!$H:$H,Spend_Data!$F:$F,A23,Spend_Data!$N:$N,"Yes") -> 708510 | E23: =SUMIFS(Spend_Data!$P:$P,Spend_Data!$F:$F,A23) -> 57118.2 | F23: =B23/SUM($B$20:$B$24) -> 0.1824389
A24: Columbus | B24: =SUMIFS(Spend_Data!$H:$H,Spend_Data!$F:$F,A24) -> 1595320 | C24: =SUMIFS(Spend_Data!$H:$H,Spend_Data!$F:$F,A24,Spend_Data!$K:$K,"Yes") -> 749460 | D24: =SUMIFS(Spend_Data!$H:$H,Spend_Data!$F:$F,A24,Spend_Data!$N:$N,"Yes") -> 933580 | E24: =SUMIFS(Spend_Data!$P:$P,Spend_Data!$F:$F,A24) -> 59330.3 | F24: =B24/SUM($B$20:$B$24) -> 0.22869479

Sheet Vendor_Consolidation
A1: Vendor Consolidation
A2: Identify fragmented categories, tail spend, and preferred-vendor migration opportunities.
A4: Category | B4: Total Vendors | C4: Preferred Vendors | D4: Tail Vendors | E4: Tail Spend | F4: Preferred Spend | G4: Non-Preferred Spend | H4: Consolidation Capture | I4: Estimated Savings | J4: Priority | K4: Recommended Action
A5: Freight & Logistics | B5: 5 | C5: 2 | D5: 3 | E5: =SUMIFS(Spend_Data!$H:$H,Spend_Data!$D:$D,A5,Spend_Data!$O:$O,"Yes") -> 0 | F5: =SUMIFS(Spend_Data!$H:$H,Spend_Data!$D:$D,A5,Spend_Data!$J:$J,"Yes") -> 547620 | G5: =SUMIFS(Spend_Data!$H:$H,Spend_Data!$D:$D,A5,Spend_Data!$J:$J,"No") -> 799910 | H5: =Inputs!$B$8 -> 0.6 | I5: =E5*H5*_xlfn.XLOOKUP(A5,Inputs!$A$14:$A$23,Inputs!$C$14:$C$23,0) -> 0 | J5: =IF(I5>=50000,"High",IF(I5>=15000,"Medium","Low")) -> Low | K5: =IF(J5="High","Rebid / migrate to preferred panel",IF(J5="Medium","Consolidate tail vendors","Monitor / negotiate at renewal")) -> Monitor / negotiate at renewal
A6: Raw Materials | B6: 5 | C6: 2 | D6: 3 | E6: =SUMIFS(Spend_Data!$H:$H,Spend_Data!$D:$D,A6,Spend_Data!$O:$O,"Yes") -> 396540 | F6: =SUMIFS(Spend_Data!$H:$H,Spend_Data!$D:$D,A6,Spend_Data!$J:$J,"Yes") -> 1158090 | G6: =SUMIFS(Spend_Data!$H:$H,Spend_Data!$D:$D,A6,Spend_Data!$J:$J,"No") -> 666330 | H6: =Inputs!$B$8 -> 0.6 | I6: =E6*H6*_xlfn.XLOOKUP(A6,Inputs!$A$14:$A$23,Inputs!$C$14:$C$23,0) -> 11896.2 | J6: =IF(I6>=50000,"High",IF(I6>=15000,"Medium","Low")) -> Low | K6: =IF(J6="High","Rebid / migrate to preferred panel",IF(J6="Medium","Consolidate tail vendors","Monitor / negotiate at renewal")) -> Monitor / negotiate at renewal
A7: Packaging | B7: 5 | C7: 2 | D7: 3 | E7: =SUMIFS(Spend_Data!$H:$H,Spend_Data!$D:$D,A7,Spend_Data!$O:$O,"Yes") -> 139930 | F7: =SUMIFS(Spend_Data!$H:$H,Spend_Data!$D:$D,A7,Spend_Data!$J:$J,"Yes") -> 255720 | G7: =SUMIFS(Spend_Data!$H:$H,Spend_Data!$D:$D,A7,Spend_Data!$J:$J,"No") -> 300430 | H7: =Inputs!$B$8 -> 0.6 | I7: =E7*H7*_xlfn.XLOOKUP(A7,Inputs!$A$14:$A$23,Inputs!$C$14:$C$23,0) -> 5037.48 | J7: =IF(I7>=50000,"High",IF(I7>=15000,"Medium","Low")) -> Low | K7: =IF(J7="High","Rebid / migrate to preferred panel",IF(J7="Medium","Consolidate tail vendors","Monitor / negotiate at renewal")) -> Monitor / negotiate at renewal
A8: IT Software | B8: 5 | C8: 2 | D8: 3 | E8: =SUMIFS(Spend_Data!$H:$H,Spend_Data!$D:$D,A8,Spend_Data!$O:$O,"Yes") -> 105640 | F8: =SUMIFS(Spend_Data!$H:$H,Spend_Data!$D:$D,A8,Spend_Data!$J:$J,"Yes") -> 152230 | G8: =SUMIFS(Spend_Data!$H:$H,Spend_Data!$D:$D,A8,Spend_Data!$J:$J,"No") -> 269490 | H8: =Inputs!$B$8 -> 0.6 | I8: =E8*H8*_xlfn.XLOOKUP(A8,Inputs!$A$14:$A$23,Inputs!$C$14:$C$23,0) -> 7606.08 | J8: =IF(I8>=50000,"High",IF(I8>=15000,"Medium","Low")) -> Low | K8: =IF(J8="High","Rebid / migrate to preferred panel",IF(J8="Medium","Consolidate tail vendors","Monitor / negotiate at renewal")) -> Monitor / negotiate at renewal
A9: Telecom | B9: 4 | C9: 1 | D9: 3 | E9: =SUMIFS(Spend_Data!$H:$H,Spend_Data!$D:$D,A9,Spend_Data!$O:$O,"Yes") -> 34030 | F9: =SUMIFS(Spend_Data!$H:$H,Spend_Data!$D:$D,A9,Spend_Data!$J:$J,"Yes") -> 61190 | G9: =SUMIFS(Spend_Data!$H:$H,Spend_Data!$D:$D,A9,Spend_Data!$J:$J,"No") -> 128200 | H9: =Inputs!$B$8 -> 0.6 | I9: =E9*H9*_xlfn.XLOOKUP(A9,Inputs!$A$14:$A$23,Inputs!$C$14:$C$23,0) -> 3062.7 | J9: =IF(I9>=50000,"High",IF(I9>=15000,"Medium","Low")) -> Low | K9: =IF(J9="High","Rebid / migrate to preferred panel",IF(J9="Medium","Consolidate tail vendors","Monitor / negotiate at renewal")) -> Monitor / negotiate at renewal
A10: Facilities | B10: 5 | C10: 2 | D10: 3 | E10: =SUMIFS(Spend_Data!$H:$H,Spend_Data!$D:$D,A10,Spend_Data!$O:$O,"Yes") -> 116400 | F10: =SUMIFS(Spend_Data!$H:$H,Spend_Data!$D:$D,A10,Spend_Data!$J:$J,"Yes") -> 105610 | G10: =SUMIFS(Spend_Data!$H:$H,Spend_Data!$D:$D,A10,Spend_Data!$J:$J,"No") -> 170210 | H10: =Inputs!$B$8 -> 0.6 | I10: =E10*H10*_xlfn.XLOOKUP(A10,Inputs!$A$14:$A$23,Inputs!$C$14:$C$23,0) -> 6984 | J10: =IF(I10>=50000,"High",IF(I10>=15000,"Medium","Low")) -> Low | K10: =IF(J10="High","Rebid / migrate to preferred panel",IF(J10="Medium","Consolidate tail vendors","Monitor / negotiate at renewal")) -> Monitor / negotiate at renewal
A11: Professional Services | B11: 5 | C11: 1 | D11: 4 | E11: =SUMIFS(Spend_Data!$H:$H,Spend_Data!$D:$D,A11,Spend_Data!$O:$O,"Yes") -> 162990 | F11: =SUMIFS(Spend_Data!$H:$H,Spend_Data!$D:$D,A11,Spend_Data!$J:$J,"Yes") -> 104470 | G11: =SUMIFS(Spend_Data!$H:$H,Spend_Data!$D:$D,A11,Spend_Data!$J:$J,"No") -> 1013850 | H11: =Inputs!$B$8 -> 0.6 | I11: =E11*H11*_xlfn.XLOOKUP(A11,Inputs!$A$14:$A$23,Inputs!$C$14:$C$23,0) -> 8801.46 | J11: =IF(I11>=50000,"High",IF(I11>=15000,"Medium","Low")) -> Low | K11: =IF(J11="High","Rebid / migrate to preferred panel",IF(J11="Medium","Consolidate tail vendors","Monitor / negotiate at renewal")) -> Monitor / negotiate at renewal
A12: Temp Labor | B12: 4 | C12: 1 | D12: 3 | E12: =SUMIFS(Spend_Data!$H:$H,Spend_Data!$D:$D,A12,Spend_Data!$O:$O,"Yes") -> 26390 | F12: =SUMIFS(Spend_Data!$H:$H,Spend_Data!$D:$D,A12,Spend_Data!$J:$J,"Yes") -> 307200 | G12: =SUMIFS(Spend_Data!$H:$H,Spend_Data!$D:$D,A12,Spend_Data!$J:$J,"No") -> 417050 | H12: =Inputs!$B$8 -> 0.6 | I12: =E12*H12*_xlfn.XLOOKUP(A12,Inputs!$A$14:$A$23,Inputs!$C$14:$C$23,0) -> 1108.38 | J12: =IF(I12>=50000,"High",IF(I12>=15000,"Medium","Low")) -> Low | K12: =IF(J12="High","Rebid / migrate to preferred panel",IF(J12="Medium","Consolidate tail vendors","Monitor / negotiate at renewal")) -> Monitor / negotiate at renewal
A13: Office Supplies | B13: 4 | C13: 1 | D13: 3 | E13: =SUMIFS(Spend_Data!$H:$H,Spend_Data!$D:$D,A13,Spend_Data!$O:$O,"Yes") -> 17750 | F13: =SUMIFS(Spend_Data!$H:$H,Spend_Data!$D:$D,A13,Spend_Data!$J:$J,"Yes") -> 41680 | G13: =SUMIFS(Spend_Data!$H:$H,Spend_Data!$D:$D,A13,Spend_Data!$J:$J,"No") -> 108110 | H13: =Inputs!$B$8 -> 0.6 | I13: =E13*H13*_xlfn.XLOOKUP(A13,Inputs!$A$14:$A$23,Inputs!$C$14:$C$23,0) -> 1917 | J13: =IF(I13>=50000,"High",IF(I13>=15000,"Medium","Low")) -> Low | K13: =IF(J13="High","Rebid / migrate to preferred panel",IF(J13="Medium","Consolidate tail vendors","Monitor / negotiate at renewal")) -> Monitor / negotiate at renewal
A14: MRO | B14: 5 | C14: 2 | D14: 3 | E14: =SUMIFS(Spend_Data!$H:$H,Spend_Data!$D:$D,A14,Spend_Data!$O:$O,"Yes") -> 4930 | F14: =SUMIFS(Spend_Data!$H:$H,Spend_Data!$D:$D,A14,Spend_Data!$J:$J,"Yes") -> 211360 | G14: =SUMIFS(Spend_Data!$H:$H,Spend_Data!$D:$D,A14,Spend_Data!$J:$J,"No") -> 157010 | H14: =Inputs!$B$8 -> 0.6 | I14: =E14*H14*_xlfn.XLOOKUP(A14,Inputs!$A$14:$A$23,Inputs!$C$14:$C$23,0) -> 177.48 | J14: =IF(I14>=50000,"High",IF(I14>=15000,"Medium","Low")) -> Low | K14: =IF(J14="High","Rebid / migrate to preferred panel",IF(J14="Medium","Consolidate tail vendors","Monitor / negotiate at renewal")) -> Monitor / negotiate at renewal

Sheet Savings_Pipeline
A1: Savings Pipeline
A2: Opportunity register for sourcing, consolidation, maverick spend control, and benefit capture.
A4: ID | B4: Opportunity | C4: Category | D4: Owner | E4: Lever | F4: Baseline Spend | G4: Savings Rate | H4: Gross Savings | I4: Realization % | J4: Run-Rate EBITDA | K4: Status | L4: Target Date
A5: 1 | B5: Rebid top freight lanes | C5: Freight & Logistics | D5: COO | E5: Carrier rebid | F5: =SUMIFS(Spend_Data!$H:$H,Spend_Data!$D:$D,C5,Spend_Data!$K:$K,"Yes") -> 1347530 | G5: 0.075 | H5: =F5*G5 -> 101064.75 | I5: =Inputs!$B$6 -> 0.8 | J5: =H5*I5 -> 80851.8 | K5: In Progress | L5: 46203
A6: 2 | B6: Consolidate IT software licenses | C6: IT Software | D6: CIO | E6: License rationalization | F6: =SUMIFS(Spend_Data!$H:$H,Spend_Data!$D:$D,C6,Spend_Data!$K:$K,"Yes") -> 421720 | G6: 0.12 | H6: =F6*G6 -> 50606.4 | I6: =Inputs!$B$6 -> 0.8 | J6: =H6*I6 -> 40485.12 | K6: Not Started | L6: 46234
A7: 3 | B7: Migrate office supplies to catalog | C7: Office Supplies | D7: CFO | E7: Preferred vendor control | F7: =SUMIFS(Spend_Data!$H:$H,Spend_Data!$D:$D,C7,Spend_Data!$K:$K,"Yes") -> 149790 | G7: 0.18 | H7: =F7*G7 -> 26962.2 | I7: =Inputs!$B$6 -> 0.8 | J7: =H7*I7 -> 21569.76 | K7: In Progress | L7: 46188
A8: 4 | B8: Facilities vendor panel | C8: Facilities | D8: COO | E8: Vendor consolidation | F8: =SUMIFS(Spend_Data!$H:$H,Spend_Data!$D:$D,C8,Spend_Data!$K:$K,"Yes") -> 275820 | G8: 0.09 | H8: =F8*G8 -> 24823.8 | I8: =Inputs!$B$6 -> 0.8 | J8: =H8*I8 -> 19859.04 | K8: Not Started | L8: 46265
A9: 5 | B9: Telecom plan normalization | C9: Telecom | D9: CIO | E9: Contract rebid | F9: =SUMIFS(Spend_Data!$H:$H,Spend_Data!$D:$D,C9,Spend_Data!$K:$K,"Yes") -> 189390 | G9: 0.15 | H9: =F9*G9 -> 28408.5 | I9: =Inputs!$B$6 -> 0.8 | J9: =H9*I9 -> 22726.8 | K9: Complete | L9: 46173
A10: 6 | B10: Packaging spec standardization | C10: Packaging | D10: COO | E10: Specification rationalization | F10: =SUMIFS(Spend_Data!$H:$H,Spend_Data!$D:$D,C10,Spend_Data!$K:$K,"Yes") -> 556150 | G10: 0.06 | H10: =F10*G10 -> 33369 | I10: =Inputs!$B$6 -> 0.8 | J10: =H10*I10 -> 26695.2 | K10: In Progress | L10: 46295
A11: 7 | B11: Professional services demand controls | C11: Professional Services | D11: CFO | E11: Demand management | F11: =SUMIFS(Spend_Data!$H:$H,Spend_Data!$D:$D,C11,Spend_Data!$K:$K,"Yes") -> 0 | G11: 0.07 | H11: =F11*G11 -> 0 | I11: =Inputs!$B$6 -> 0.8 | J11: =H11*I11 -> 0 | K11: At Risk | L11: 46326
A12: 8 | B12: Temp labor vendor markup reset | C12: Temp Labor | D12: CHRO | E12: Rate negotiation | F12: =SUMIFS(Spend_Data!$H:$H,Spend_Data!$D:$D,C12,Spend_Data!$K:$K,"Yes") -> 0 | G12: 0.065 | H12: =F12*G12 -> 0 | I12: =Inputs!$B$6 -> 0.8 | J12: =H12*I12 -> 0 | K12: Not Started | L12: 46280

Sheet EBITDA_Validation
A1: EBITDA Validation
A2: Bridge identified procurement opportunities into validated run-rate EBITDA and enterprise value.
A4: SUMMARY | E4: EBITDA BRIDGE
A5: Metric | B5: Formula / Source | C5: Value | E5: Bridge Item | F5: Amount
A6: Total Third-Party Spend | B6: Spend_Data total spend | C6: =SUM(Spend_Data!$H:$H) -> 6975760 | E6: Identified Gross Savings | F6: =C9 -> 265234.65
A7: Addressable Spend | B7: Spend marked addressable | C7: =SUMIFS(Spend_Data!$H:$H,Spend_Data!$K:$K,"Yes") -> 3502330 | E7: Realization Discount | F7: =-(C9-C11) -> -53046.93
A8: Identified Gross Savings | B8: Spend_Data savings opportunity | C8: =SUM(Spend_Data!$P:$P) -> 302827 | E8: Validated Run-Rate EBITDA | F8: =C11 -> 212187.72
A9: Pipeline Gross Savings | B9: Savings_Pipeline gross savings | C9: =SUM(Savings_Pipeline!$H$5:$H$12) -> 265234.65 | E9: Enterprise Value Impact | F9: =C12 -> 2121877.2
A10: Realization Rate | B10: Inputs assumption | C10: =Inputs!$B$6 -> 0.8
A11: Validated Run-Rate EBITDA | B11: Pipeline gross savings × realization rate | C11: =SUM(Savings_Pipeline!$J$5:$J$12) -> 212187.72
A12: Enterprise Value Impact | B12: Run-rate EBITDA × EBITDA multiple | C12: =C11*Inputs!$B$5 -> 2121877.2
