Workbook

Sheet Dashboard
A1: Ops2EBITDA · Sales Productivity & Pipeline Coverage Model
A2: Diagnose pipeline coverage, rep productivity, stage conversion, territory capacity, and bookings-to-EBITDA upside.
A4: Current Open Pipeline ($mm) | D4: Weighted Pipeline ($mm) | G4: Required Coverage (x) | J4: Net EBITDA Upside ($mm)
A5: =Forecast_Scenarios!C4 -> 25.36 | D5: =Forecast_Scenarios!C5 -> 8.053 | G5: =Inputs!$B$7 -> 3 | J5: =EBITDA_Impact!D11 -> 0.33063648
A9: Priority Rep / Pipeline View | H9: Scenario Summary
A10: Rep | B10: Quota ($mm) | C10: Open Pipeline ($mm) | D10: Coverage (x) | E10: Win Rate | F10: Flag | H10: Metric | I10: Conservative | J10: Base | K10: Upside | L10: Notes
A11: =Rep_Productivity!A5 -> Alex Morgan | B11: =Rep_Productivity!C5 -> 2 | C11: =Rep_Productivity!E5 -> 2.96 | D11: =Rep_Productivity!I5 -> 1.48 | E11: =Rep_Productivity!N5 -> 0.66666667 | F11: =Rep_Productivity!O5 -> Coverage Gap | H11: Forecast Bookings ($mm) | I11: =Forecast_Scenarios!B13 -> 6.32732 | J11: =Forecast_Scenarios!C13 -> 7.250424 | K11: =Forecast_Scenarios!D13 -> 8.196352 | L11: Modelled from pipeline, win rate, hygiene, velocity
A12: =Rep_Productivity!A6 -> Brooke Chen | B12: =Rep_Productivity!C6 -> 2.2 | C12: =Rep_Productivity!E6 -> 2.68 | D12: =Rep_Productivity!I6 -> 1.2181818 | E12: =Rep_Productivity!N6 -> 0 | F12: =Rep_Productivity!O6 -> Coverage Gap | H12: Bookings Gap / Surplus ($mm) | I12: =Forecast_Scenarios!B14 -> -5.67268 | J12: =Forecast_Scenarios!C14 -> -4.749576 | K12: =Forecast_Scenarios!D14 -> -3.803648 | L12: Positive = above target
A13: =Rep_Productivity!A7 -> Chris Patel | B13: =Rep_Productivity!C7 -> 1.8 | C13: =Rep_Productivity!E7 -> 6 | D13: =Rep_Productivity!I7 -> 3.3333333 | E13: =Rep_Productivity!N7 -> 1 | F13: =Rep_Productivity!O7 -> On Track | H13: Incremental Bookings ($mm) | I13: =Forecast_Scenarios!B15 -> 0.24092 | J13: =Forecast_Scenarios!C15 -> 1.164024 | K13: =Forecast_Scenarios!D15 -> 2.109952 | L13: Versus baseline conversion
A14: =Rep_Productivity!A8 -> Dana Lewis | B14: =Rep_Productivity!C8 -> 2.1 | C14: =Rep_Productivity!E8 -> 1.46 | D14: =Rep_Productivity!I8 -> 0.6952381 | E14: =Rep_Productivity!N8 -> 0 | F14: =Rep_Productivity!O8 -> Coverage Gap | H14: Incremental EBITDA ($mm) | I14: =Forecast_Scenarios!B16 -> 0.06071184 | J14: =Forecast_Scenarios!C16 -> 0.36666756 | K14: =Forecast_Scenarios!D16 -> 0.75325286 | L14: Uses contribution margin
A15: =Rep_Productivity!A9 -> Evan Ross | B15: =Rep_Productivity!C9 -> 1.7 | C15: =Rep_Productivity!E9 -> 2.21 | D15: =Rep_Productivity!I9 -> 1.3 | E15: =Rep_Productivity!N9 -> 0.5 | F15: =Rep_Productivity!O9 -> Coverage Gap | H15: EV Impact ($mm) | I15: =I14*Inputs!$B$9 -> 0.69818616 | J15: =J14*Inputs!$B$9 -> 4.2166769 | K15: =K14*Inputs!$B$9 -> 8.6624079 | L15: EBITDA impact × exit multiple
A16: =Rep_Productivity!A10 -> Frances Kim | B16: =Rep_Productivity!C10 -> 2.3 | C16: =Rep_Productivity!E10 -> 2.19 | D16: =Rep_Productivity!I10 -> 0.95217391 | E16: =Rep_Productivity!N10 -> 0.25 | F16: =Rep_Productivity!O10 -> Coverage Gap
A17: =Rep_Productivity!A11 -> Gabe Wright | B17: =Rep_Productivity!C11 -> 1.9 | C17: =Rep_Productivity!E11 -> 3.91 | D17: =Rep_Productivity!I11 -> 2.0578947 | E17: =Rep_Productivity!N11 -> 0 | F17: =Rep_Productivity!O11 -> Coverage Gap
A18: =Rep_Productivity!A12 -> Harper Stone | B18: =Rep_Productivity!C12 -> 2 | C18: =Rep_Productivity!E12 -> 3.95 | D18: =Rep_Productivity!I12 -> 1.975 | E18: =Rep_Productivity!N12 -> 0.33333333 | F18: =Rep_Productivity!O12 -> Coverage Gap

Sheet Instructions
A1: How to Use This Model
A3: Step | B3: Action
A4: 1 | B4: Update Inputs sheet for quarter dates, bookings target, required coverage, contribution margin, exit multiple, and scenario assumptions.
A5: 2 | B5: Replace sample opportunity-level data in Pipeline_Data with CRM export fields: rep, stage, close date, deal value, days in stage, source, and forecast category.
A6: 3 | B6: Review Rep_Productivity to identify coverage gaps, quota gaps, low win rates, and overloaded territories.
A7: 4 | B7: Review Stage_Conversion to identify aging bottlenecks and stale opportunities by funnel stage.
A8: 5 | B8: Use Territory_Capacity to size productivity upside from admin reduction, territory rebalance, and better opportunity load.
A9: 6 | B9: Use Forecast_Scenarios and EBITDA_Impact to translate productivity levers into bookings, EBITDA, and enterprise value impact.
A10: 7 | B10: Use Dashboard for an executive view suitable for management discussion or board update prep.
A12: Modeling Notes
A13: This model uses sample data for demonstration. Replace the sample pipeline with CRM opportunity data.
A14: Hardcoded inputs use blue font and yellow fill. Formula outputs use black or linked green where possible.
A15: The model intentionally separates raw pipeline, rep productivity, stage conversion, capacity, scenarios, and EBITDA impact.
A16: The objective is to identify where seller output is constrained: coverage, conversion, velocity, stale pipeline, admin load, or territory design.

Sheet Inputs
A1: Ops2EBITDA · Sales Productivity & Pipeline Coverage Model
A3: Core Assumption | B3: Input | D3: Stage | E3: Probability | F3: Target Max Days | H3: Rep | I3: Quarter Quota ($mm) | J3: Region
A4: Fiscal Quarter Start | B4: 46023 | D4: Prospecting | E4: 0.1 | F4: 21 | H4: Alex Morgan | I4: 2 | J4: East
A5: Fiscal Quarter End | B5: 46112 | D5: Qualification | E5: 0.2 | F5: 21 | H5: Brooke Chen | I5: 2.2 | J5: West
A6: Quarter Bookings Target ($mm) | B6: 12 | D6: Discovery | E6: 0.3 | F6: 28 | H6: Chris Patel | I6: 1.8 | J6: Central
A7: Required Pipeline Coverage (Unweighted x) | B7: 3 | D7: Proposal | E7: 0.45 | F7: 30 | H7: Dana Lewis | I7: 2.1 | J7: East
A8: Contribution Margin % | B8: 0.42 | D8: Negotiation | E8: 0.65 | F8: 21 | H8: Evan Ross | I8: 1.7 | J8: West
A9: Exit EBITDA Multiple | B9: 11.5 | D9: Verbal / Commit | E9: 0.85 | F9: 14 | H9: Frances Kim | I9: 2.3 | J9: Central
A10: Avg Loaded Rep Cost ($000) | B10: 185 | D10: Closed Won | E10: 1 | F10: 999 | H10: Gabe Wright | I10: 1.9 | J10: National
A11: Baseline Win Rate % | B11: 0.24 | D11: Closed Lost | E11: 0 | F11: 999 | H11: Harper Stone | I11: 2 | J11: National
A12: Target Win Rate % | B12: 0.28
A14: Scenario Assumption | B14: Conservative | C14: Base | D14: Upside
A15: Win Rate Improvement (bps) | B15: 100 | C15: 300 | D15: 500
A16: Admin Time Reduction % | B16: 0.05 | C16: 0.1 | D16: 0.15
A17: Stage Velocity Improvement % | B17: 0.03 | C17: 0.07 | D17: 0.1
A18: Pipeline Hygiene Removal % | B18: 0.05 | C18: 0.08 | D18: 0.12
A19: Incremental Quota Capacity % | B19: 0.02 | C19: 0.05 | D19: 0.08
A20: Confidence / Realization % | B20: 0.6 | C20: 0.75 | D20: 0.85

Sheet Pipeline_Data
A1: Pipeline Data
A2: Opportunity-level CRM pipeline with stage, probability, aging, and priority scoring
A4: Opp ID | B4: Customer | C4: Segment | D4: Region | E4: Sales Rep | F4: Stage | G4: Expected Close Date | H4: Deal Value ($mm) | I4: Probability | J4: Weighted Pipeline ($mm) | K4: Days in Stage | L4: Stage Max Days | M4: Age Flag | N4: In Quarter? | O4: Forecast Category | P4: Source | Q4: Priority
A5: OPP-1001 | B5: Horizon Tech | C5: Enterprise | D5: Central | E5: Chris Patel | F5: Discovery | G5: 46078 | H5: 1.38 | I5: =IFERROR(VLOOKUP(F5,Inputs!$D$4:$E$11,2,FALSE),0) -> 0.3 | J5: =H5*I5 -> 0.414 | K5: 51 | L5: =IFERROR(VLOOKUP(F5,Inputs!$D$4:$F$11,3,FALSE),0) -> 28 | M5: =IF(K5>L5,"Aged","Healthy") -> Aged | N5: =IF(AND(G5>=Inputs!$B$4,G5<=Inputs!$B$5),"In Quarter","Out Quarter") -> In Quarter | O5: Commit | P5: Inbound | Q5: =IF(OR(M5="Aged",J5>=0.4),"High",IF(J5>=0.2,"Medium","Low")) -> High
A6: OPP-1002 | B6: Atlas Packaging | C6: SMB | D6: National | E6: Gabe Wright | F6: Prospecting | G6: 46081 | H6: 1.28 | I6: =IFERROR(VLOOKUP(F6,Inputs!$D$4:$E$11,2,FALSE),0) -> 0.1 | J6: =H6*I6 -> 0.128 | K6: 20 | L6: =IFERROR(VLOOKUP(F6,Inputs!$D$4:$F$11,3,FALSE),0) -> 21 | M6: =IF(K6>L6,"Aged","Healthy") -> Healthy | N6: =IF(AND(G6>=Inputs!$B$4,G6<=Inputs!$B$5),"In Quarter","Out Quarter") -> In Quarter | O6: Commit | P6: Event | Q6: =IF(OR(M6="Aged",J6>=0.4),"High",IF(J6>=0.2,"Medium","Low")) -> Low
A7: OPP-1003 | B7: Monarch Labs | C7: Enterprise | D7: National | E7: Gabe Wright | F7: Closed Lost | G7: 46034 | H7: 1.67 | I7: =IFERROR(VLOOKUP(F7,Inputs!$D$4:$E$11,2,FALSE),0) -> 0 | J7: =H7*I7 -> 0 | K7: 42 | L7: =IFERROR(VLOOKUP(F7,Inputs!$D$4:$F$11,3,FALSE),0) -> 999 | M7: =IF(K7>L7,"Aged","Healthy") -> Healthy | N7: =IF(AND(G7>=Inputs!$B$4,G7<=Inputs!$B$5),"In Quarter","Out Quarter") -> In Quarter | O7: Closed | P7: Event | Q7: =IF(OR(M7="Aged",J7>=0.4),"High",IF(J7>=0.2,"Medium","Low")) -> Low
A8: OPP-1004 | B8: Vector Manufacturing | C8: Enterprise | D8: West | E8: Evan Ross | F8: Prospecting | G8: 46099 | H8: 0.71 | I8: =IFERROR(VLOOKUP(F8,Inputs!$D$4:$E$11,2,FALSE),0) -> 0.1 | J8: =H8*I8 -> 0.071 | K8: 29 | L8: =IFERROR(VLOOKUP(F8,Inputs!$D$4:$F$11,3,FALSE),0) -> 21 | M8: =IF(K8>L8,"Aged","Healthy") -> Aged | N8: =IF(AND(G8>=Inputs!$B$4,G8<=Inputs!$B$5),"In Quarter","Out Quarter") -> In Quarter | O8: Commit | P8: Outbound | Q8: =IF(OR(M8="Aged",J8>=0.4),"High",IF(J8>=0.2,"Medium","Low")) -> High
A9: OPP-1005 | B9: Ironwood Systems | C9: SMB | D9: East | E9: Dana Lewis | F9: Proposal | G9: 46091 | H9: 0.6 | I9: =IFERROR(VLOOKUP(F9,Inputs!$D$4:$E$11,2,FALSE),0) -> 0.45 | J9: =H9*I9 -> 0.27 | K9: 45 | L9: =IFERROR(VLOOKUP(F9,Inputs!$D$4:$F$11,3,FALSE),0) -> 30 | M9: =IF(K9>L9,"Aged","Healthy") -> Aged | N9: =IF(AND(G9>=Inputs!$B$4,G9<=Inputs!$B$5),"In Quarter","Out Quarter") -> In Quarter | O9: Best Case | P9: Partner | Q9: =IF(OR(M9="Aged",J9>=0.4),"High",IF(J9>=0.2,"Medium","Low")) -> High
A10: OPP-1006 | B10: Granite Clinics | C10: SMB | D10: Central | E10: Chris Patel | F10: Discovery | G10: 46117 | H10: 1.17 | I10: =IFERROR(VLOOKUP(F10,Inputs!$D$4:$E$11,2,FALSE),0) -> 0.3 | J10: =H10*I10 -> 0.351 | K10: 68 | L10: =IFERROR(VLOOKUP(F10,Inputs!$D$4:$F$11,3,FALSE),0) -> 28 | M10: =IF(K10>L10,"Aged","Healthy") -> Aged | N10: =IF(AND(G10>=Inputs!$B$4,G10<=Inputs!$B$5),"In Quarter","Out Quarter") -> Out Quarter | O10: Best Case | P10: Partner | Q10: =IF(OR(M10="Aged",J10>=0.4),"High",IF(J10>=0.2,"Medium","Low")) -> High
A11: OPP-1007 | B11: Riverbend Logistics | C11: Mid-Market | D11: West | E11: Brooke Chen | F11: Proposal | G11: 46043 | H11: 0.47 | I11: =IFERROR(VLOOKUP(F11,Inputs!$D$4:$E$11,2,FALSE),0) -> 0.45 | J11: =H11*I11 -> 0.2115 | K11: 48 | L11: =IFERROR(VLOOKUP(F11,Inputs!$D$4:$F$11,3,FALSE),0) -> 30 | M11: =IF(K11>L11,"Aged","Healthy") -> Aged | N11: =IF(AND(G11>=Inputs!$B$4,G11<=Inputs!$B$5),"In Quarter","Out Quarter") -> In Quarter | O11: Best Case | P11: Outbound | Q11: =IF(OR(M11="Aged",J11>=0.4),"High",IF(J11>=0.2,"Medium","Low")) -> High
A12: OPP-1008 | B12: Granite Clinics | C12: SMB | D12: West | E12: Brooke Chen | F12: Closed Lost | G12: 46125 | H12: 0.51 | I12: =IFERROR(VLOOKUP(F12,Inputs!$D$4:$E$11,2,FALSE),0) -> 0 | J12: =H12*I12 -> 0 | K12: 45 | L12: =IFERROR(VLOOKUP(F12,Inputs!$D$4:$F$11,3,FALSE),0) -> 999 | M12: =IF(K12>L12,"Aged","Healthy") -> Healthy | N12: =IF(AND(G12>=Inputs!$B$4,G12<=Inputs!$B$5),"In Quarter","Out Quarter") -> Out Quarter | O12: Closed | P12: Partner | Q12: =IF(OR(M12="Aged",J12>=0.4),"High",IF(J12>=0.2,"Medium","Low")) -> Low
A13: OPP-1009 | B13: Cobalt Industrial | C13: Enterprise | D13: National | E13: Harper Stone | F13: Proposal | G13: 46036 | H13: 0.73 | I13: =IFERROR(VLOOKUP(F13,Inputs!$D$4:$E$11,2,FALSE),0) -> 0.45 | J13: =H13*I13 -> 0.3285 | K13: 65 | L13: =IFERROR(VLOOKUP(F13,Inputs!$D$4:$F$11,3,FALSE),0) -> 30 | M13: =IF(K13>L13,"Aged","Healthy") -> Aged | N13: =IF(AND(G13>=Inputs!$B$4,G13<=Inputs!$B$5),"In Quarter","Out Quarter") -> In Quarter | O13: Commit | P13: Partner | Q13: =IF(OR(M13="Aged",J13>=0.4),"High",IF(J13>=0.2,"Medium","Low")) -> High
A14: OPP-1010 | B14: Apex Health | C14: Mid-Market | D14: National | E14: Harper Stone | F14: Negotiation | G14: 46064 | H14: 0.63 | I14: =IFERROR(VLOOKUP(F14,Inputs!$D$4:$E$11,2,FALSE),0) -> 0.65 | J14: =H14*I14 -> 0.4095 | K14: 49 | L14: =IFERROR(VLOOKUP(F14,Inputs!$D$4:$F$11,3,FALSE),0) -> 21 | M14: =IF(K14>L14,"Aged","Healthy") -> Aged | N14: =IF(AND(G14>=Inputs!$B$4,G14<=Inputs!$B$5),"In Quarter","Out Quarter") -> In Quarter | O14: Best Case | P14: Inbound | Q14: =IF(OR(M14="Aged",J14>=0.4),"High",IF(J14>=0.2,"Medium","Low")) -> High
A15: OPP-1011 | B15: Crescent Retail | C15: Mid-Market | D15: National | E15: Harper Stone | F15: Negotiation | G15: 46035 | H15: 0.25 | I15: =IFERROR(VLOOKUP(F15,Inputs!$D$4:$E$11,2,FALSE),0) -> 0.65 | J15: =H15*I15 -> 0.1625 | K15: 36 | L15: =IFERROR(VLOOKUP(F15,Inputs!$D$4:$F$11,3,FALSE),0) -> 21 | M15: =IF(K15>L15,"Aged","Healthy") -> Aged | N15: =IF(AND(G15>=Inputs!$B$4,G15<=Inputs!$B$5),"In Quarter","Out Quarter") -> In Quarter | O15: Best Case | P15: Outbound | Q15: =IF(OR(M15="Aged",J15>=0.4),"High",IF(J15>=0.2,"Medium","Low")) -> High
A16: OPP-1012 | B16: Falcon Components | C16: Mid-Market | D16: National | E16: Gabe Wright | F16: Qualification | G16: 46098 | H16: 0.29 | I16: =IFERROR(VLOOKUP(F16,Inputs!$D$4:$E$11,2,FALSE),0) -> 0.2 | J16: =H16*I16 -> 0.058 | K16: 60 | L16: =IFERROR(VLOOKUP(F16,Inputs!$D$4:$F$11,3,FALSE),0) -> 21 | M16: =IF(K16>L16,"Aged","Healthy") -> Aged | N16: =IF(AND(G16>=Inputs!$B$4,G16<=Inputs!$B$5),"In Quarter","Out Quarter") -> In Quarter | O16: Commit | P16: Expansion | Q16: =IF(OR(M16="Aged",J16>=0.4),"High",IF(J16>=0.2,"Medium","Low")) -> High
... A89: OPP-1085 | B89: Vector Manufacturing | C89: SMB | D89: East | E89: Dana Lewis | F89: Closed Lost | G89: 46091 | H89: 0.11 | I89: =IFERROR(VLOOKUP(F89,Inputs!$D$4:$E$11,2,FALSE),0) -> 0 | J89: =H89*I89 -> 0 | K89: 58 | L89: =IFERROR(VLOOKUP(F89,Inputs!$D$4:$F$11,3,FALSE),0) -> 999 | M89: =IF(K89>L89,"Aged","Healthy") -> Healthy | N89: =IF(AND(G89>=Inputs!$B$4,G89<=Inputs!$B$5),"In Quarter","Out Quarter") -> In Quarter | O89: Closed | P89: Expansion | Q89: =IF(OR(M89="Aged",J89>=0.4),"High",IF(J89>=0.2,"Medium","Low")) -> Low

Sheet Rep_Productivity
A1: Rep Productivity
A2: Quota attainment, pipeline coverage, win rates, and productivity flags by rep
A4: Rep | B4: Region | C4: Quarter Quota ($mm) | D4: Closed Won ($mm) | E4: Open Pipeline ($mm) | F4: Weighted Pipeline ($mm) | G4: Opp Count | H4: Avg Open Deal ($mm) | I4: Unweighted Coverage (x) | J4: Weighted Coverage (x) | K4: Quota Attainment % | L4: Won Deals | M4: Lost Deals | N4: Win Rate % | O4: Productivity Flag | Q4: Required Coverage
A5: Alex Morgan | B5: =VLOOKUP(A5,Inputs!$H$4:$J$11,3,FALSE) -> East | C5: =VLOOKUP(A5,Inputs!$H$4:$I$11,2,FALSE) -> 2 | D5: =SUMIFS(Pipeline_Data!$H:$H,Pipeline_Data!$E:$E,A5,Pipeline_Data!$F:$F,"Closed Won",Pipeline_Data!$N:$N,"In Quarter") -> 1.22 | E5: =SUMIFS(Pipeline_Data!$H:$H,Pipeline_Data!$E:$E,A5,Pipeline_Data!$F:$F,"<>Closed Won",Pipeline_Data!$F:$F,"<>Closed Lost",Pipeline_Data!$N:$N,"In Quarter") -> 2.96 | F5: =SUMIFS(Pipeline_Data!$J:$J,Pipeline_Data!$E:$E,A5,Pipeline_Data!$F:$F,"<>Closed Won",Pipeline_Data!$F:$F,"<>Closed Lost",Pipeline_Data!$N:$N,"In Quarter") -> 0.506 | G5: =COUNTIFS(Pipeline_Data!$E:$E,A5,Pipeline_Data!$F:$F,"<>Closed Won",Pipeline_Data!$F:$F,"<>Closed Lost") -> 7 | H5: =IF(G5=0,0,E5/G5) -> 0.42285714 | I5: =IF(C5=0,0,E5/C5) -> 1.48 | J5: =IF(C5=0,0,F5/C5) -> 0.253 | K5: =IF(C5=0,0,D5/C5) -> 0.61 | L5: =COUNTIFS(Pipeline_Data!$E:$E,A5,Pipeline_Data!$F:$F,"Closed Won") -> 2 | M5: =COUNTIFS(Pipeline_Data!$E:$E,A5,Pipeline_Data!$F:$F,"Closed Lost") -> 1 | N5: =IF((L5+M5)=0,0,L5/(L5+M5)) -> 0.66666667 | O5: =IF(I5<Inputs!$B$7,"Coverage Gap",IF(N5<Inputs!$B$11,"Win Rate Gap",IF(K5<0.5,"Quota Gap","On Track"))) -> Coverage Gap | Q5: =Inputs!$B$7 -> 3
A6: Brooke Chen | B6: =VLOOKUP(A6,Inputs!$H$4:$J$11,3,FALSE) -> West | C6: =VLOOKUP(A6,Inputs!$H$4:$I$11,2,FALSE) -> 2.2 | D6: =SUMIFS(Pipeline_Data!$H:$H,Pipeline_Data!$E:$E,A6,Pipeline_Data!$F:$F,"Closed Won",Pipeline_Data!$N:$N,"In Quarter") -> 0 | E6: =SUMIFS(Pipeline_Data!$H:$H,Pipeline_Data!$E:$E,A6,Pipeline_Data!$F:$F,"<>Closed Won",Pipeline_Data!$F:$F,"<>Closed Lost",Pipeline_Data!$N:$N,"In Quarter") -> 2.68 | F6: =SUMIFS(Pipeline_Data!$J:$J,Pipeline_Data!$E:$E,A6,Pipeline_Data!$F:$F,"<>Closed Won",Pipeline_Data!$F:$F,"<>Closed Lost",Pipeline_Data!$N:$N,"In Quarter") -> 0.8415 | G6: =COUNTIFS(Pipeline_Data!$E:$E,A6,Pipeline_Data!$F:$F,"<>Closed Won",Pipeline_Data!$F:$F,"<>Closed Lost") -> 7 | H6: =IF(G6=0,0,E6/G6) -> 0.38285714 | I6: =IF(C6=0,0,E6/C6) -> 1.2181818 | J6: =IF(C6=0,0,F6/C6) -> 0.3825 | K6: =IF(C6=0,0,D6/C6) -> 0 | L6: =COUNTIFS(Pipeline_Data!$E:$E,A6,Pipeline_Data!$F:$F,"Closed Won") -> 0 | M6: =COUNTIFS(Pipeline_Data!$E:$E,A6,Pipeline_Data!$F:$F,"Closed Lost") -> 2 | N6: =IF((L6+M6)=0,0,L6/(L6+M6)) -> 0 | O6: =IF(I6<Inputs!$B$7,"Coverage Gap",IF(N6<Inputs!$B$11,"Win Rate Gap",IF(K6<0.5,"Quota Gap","On Track"))) -> Coverage Gap | Q6: =Inputs!$B$7 -> 3
A7: Chris Patel | B7: =VLOOKUP(A7,Inputs!$H$4:$J$11,3,FALSE) -> Central | C7: =VLOOKUP(A7,Inputs!$H$4:$I$11,2,FALSE) -> 1.8 | D7: =SUMIFS(Pipeline_Data!$H:$H,Pipeline_Data!$E:$E,A7,Pipeline_Data!$F:$F,"Closed Won",Pipeline_Data!$N:$N,"In Quarter") -> 1.07 | E7: =SUMIFS(Pipeline_Data!$H:$H,Pipeline_Data!$E:$E,A7,Pipeline_Data!$F:$F,"<>Closed Won",Pipeline_Data!$F:$F,"<>Closed Lost",Pipeline_Data!$N:$N,"In Quarter") -> 6 | F7: =SUMIFS(Pipeline_Data!$J:$J,Pipeline_Data!$E:$E,A7,Pipeline_Data!$F:$F,"<>Closed Won",Pipeline_Data!$F:$F,"<>Closed Lost",Pipeline_Data!$N:$N,"In Quarter") -> 1.956 | G7: =COUNTIFS(Pipeline_Data!$E:$E,A7,Pipeline_Data!$F:$F,"<>Closed Won",Pipeline_Data!$F:$F,"<>Closed Lost") -> 12 | H7: =IF(G7=0,0,E7/G7) -> 0.5 | I7: =IF(C7=0,0,E7/C7) -> 3.3333333 | J7: =IF(C7=0,0,F7/C7) -> 1.0866667 | K7: =IF(C7=0,0,D7/C7) -> 0.59444444 | L7: =COUNTIFS(Pipeline_Data!$E:$E,A7,Pipeline_Data!$F:$F,"Closed Won") -> 2 | M7: =COUNTIFS(Pipeline_Data!$E:$E,A7,Pipeline_Data!$F:$F,"Closed Lost") -> 0 | N7: =IF((L7+M7)=0,0,L7/(L7+M7)) -> 1 | O7: =IF(I7<Inputs!$B$7,"Coverage Gap",IF(N7<Inputs!$B$11,"Win Rate Gap",IF(K7<0.5,"Quota Gap","On Track"))) -> On Track | Q7: =Inputs!$B$7 -> 3
A8: Dana Lewis | B8: =VLOOKUP(A8,Inputs!$H$4:$J$11,3,FALSE) -> East | C8: =VLOOKUP(A8,Inputs!$H$4:$I$11,2,FALSE) -> 2.1 | D8: =SUMIFS(Pipeline_Data!$H:$H,Pipeline_Data!$E:$E,A8,Pipeline_Data!$F:$F,"Closed Won",Pipeline_Data!$N:$N,"In Quarter") -> 0 | E8: =SUMIFS(Pipeline_Data!$H:$H,Pipeline_Data!$E:$E,A8,Pipeline_Data!$F:$F,"<>Closed Won",Pipeline_Data!$F:$F,"<>Closed Lost",Pipeline_Data!$N:$N,"In Quarter") -> 1.46 | F8: =SUMIFS(Pipeline_Data!$J:$J,Pipeline_Data!$E:$E,A8,Pipeline_Data!$F:$F,"<>Closed Won",Pipeline_Data!$F:$F,"<>Closed Lost",Pipeline_Data!$N:$N,"In Quarter") -> 0.6715 | G8: =COUNTIFS(Pipeline_Data!$E:$E,A8,Pipeline_Data!$F:$F,"<>Closed Won",Pipeline_Data!$F:$F,"<>Closed Lost") -> 7 | H8: =IF(G8=0,0,E8/G8) -> 0.20857143 | I8: =IF(C8=0,0,E8/C8) -> 0.6952381 | J8: =IF(C8=0,0,F8/C8) -> 0.3197619 | K8: =IF(C8=0,0,D8/C8) -> 0 | L8: =COUNTIFS(Pipeline_Data!$E:$E,A8,Pipeline_Data!$F:$F,"Closed Won") -> 0 | M8: =COUNTIFS(Pipeline_Data!$E:$E,A8,Pipeline_Data!$F:$F,"Closed Lost") -> 2 | N8: =IF((L8+M8)=0,0,L8/(L8+M8)) -> 0 | O8: =IF(I8<Inputs!$B$7,"Coverage Gap",IF(N8<Inputs!$B$11,"Win Rate Gap",IF(K8<0.5,"Quota Gap","On Track"))) -> Coverage Gap | Q8: =Inputs!$B$7 -> 3
A9: Evan Ross | B9: =VLOOKUP(A9,Inputs!$H$4:$J$11,3,FALSE) -> West | C9: =VLOOKUP(A9,Inputs!$H$4:$I$11,2,FALSE) -> 1.7 | D9: =SUMIFS(Pipeline_Data!$H:$H,Pipeline_Data!$E:$E,A9,Pipeline_Data!$F:$F,"Closed Won",Pipeline_Data!$N:$N,"In Quarter") -> 0.89 | E9: =SUMIFS(Pipeline_Data!$H:$H,Pipeline_Data!$E:$E,A9,Pipeline_Data!$F:$F,"<>Closed Won",Pipeline_Data!$F:$F,"<>Closed Lost",Pipeline_Data!$N:$N,"In Quarter") -> 2.21 | F9: =SUMIFS(Pipeline_Data!$J:$J,Pipeline_Data!$E:$E,A9,Pipeline_Data!$F:$F,"<>Closed Won",Pipeline_Data!$F:$F,"<>Closed Lost",Pipeline_Data!$N:$N,"In Quarter") -> 0.6635 | G9: =COUNTIFS(Pipeline_Data!$E:$E,A9,Pipeline_Data!$F:$F,"<>Closed Won",Pipeline_Data!$F:$F,"<>Closed Lost") -> 5 | H9: =IF(G9=0,0,E9/G9) -> 0.442 | I9: =IF(C9=0,0,E9/C9) -> 1.3 | J9: =IF(C9=0,0,F9/C9) -> 0.39029412 | K9: =IF(C9=0,0,D9/C9) -> 0.52352941 | L9: =COUNTIFS(Pipeline_Data!$E:$E,A9,Pipeline_Data!$F:$F,"Closed Won") -> 2 | M9: =COUNTIFS(Pipeline_Data!$E:$E,A9,Pipeline_Data!$F:$F,"Closed Lost") -> 2 | N9: =IF((L9+M9)=0,0,L9/(L9+M9)) -> 0.5 | O9: =IF(I9<Inputs!$B$7,"Coverage Gap",IF(N9<Inputs!$B$11,"Win Rate Gap",IF(K9<0.5,"Quota Gap","On Track"))) -> Coverage Gap | Q9: =Inputs!$B$7 -> 3
A10: Frances Kim | B10: =VLOOKUP(A10,Inputs!$H$4:$J$11,3,FALSE) -> Central | C10: =VLOOKUP(A10,Inputs!$H$4:$I$11,2,FALSE) -> 2.3 | D10: =SUMIFS(Pipeline_Data!$H:$H,Pipeline_Data!$E:$E,A10,Pipeline_Data!$F:$F,"Closed Won",Pipeline_Data!$N:$N,"In Quarter") -> 0.46 | E10: =SUMIFS(Pipeline_Data!$H:$H,Pipeline_Data!$E:$E,A10,Pipeline_Data!$F:$F,"<>Closed Won",Pipeline_Data!$F:$F,"<>Closed Lost",Pipeline_Data!$N:$N,"In Quarter") -> 2.19 | F10: =SUMIFS(Pipeline_Data!$J:$J,Pipeline_Data!$E:$E,A10,Pipeline_Data!$F:$F,"<>Closed Won",Pipeline_Data!$F:$F,"<>Closed Lost",Pipeline_Data!$N:$N,"In Quarter") -> 0.813 | G10: =COUNTIFS(Pipeline_Data!$E:$E,A10,Pipeline_Data!$F:$F,"<>Closed Won",Pipeline_Data!$F:$F,"<>Closed Lost") -> 5 | H10: =IF(G10=0,0,E10/G10) -> 0.438 | I10: =IF(C10=0,0,E10/C10) -> 0.95217391 | J10: =IF(C10=0,0,F10/C10) -> 0.35347826 | K10: =IF(C10=0,0,D10/C10) -> 0.2 | L10: =COUNTIFS(Pipeline_Data!$E:$E,A10,Pipeline_Data!$F:$F,"Closed Won") -> 1 | M10: =COUNTIFS(Pipeline_Data!$E:$E,A10,Pipeline_Data!$F:$F,"Closed Lost") -> 3 | N10: =IF((L10+M10)=0,0,L10/(L10+M10)) -> 0.25 | O10: =IF(I10<Inputs!$B$7,"Coverage Gap",IF(N10<Inputs!$B$11,"Win Rate Gap",IF(K10<0.5,"Quota Gap","On Track"))) -> Coverage Gap | Q10: =Inputs!$B$7 -> 3
A11: Gabe Wright | B11: =VLOOKUP(A11,Inputs!$H$4:$J$11,3,FALSE) -> National | C11: =VLOOKUP(A11,Inputs!$H$4:$I$11,2,FALSE) -> 1.9 | D11: =SUMIFS(Pipeline_Data!$H:$H,Pipeline_Data!$E:$E,A11,Pipeline_Data!$F:$F,"Closed Won",Pipeline_Data!$N:$N,"In Quarter") -> 0 | E11: =SUMIFS(Pipeline_Data!$H:$H,Pipeline_Data!$E:$E,A11,Pipeline_Data!$F:$F,"<>Closed Won",Pipeline_Data!$F:$F,"<>Closed Lost",Pipeline_Data!$N:$N,"In Quarter") -> 3.91 | F11: =SUMIFS(Pipeline_Data!$J:$J,Pipeline_Data!$E:$E,A11,Pipeline_Data!$F:$F,"<>Closed Won",Pipeline_Data!$F:$F,"<>Closed Lost",Pipeline_Data!$N:$N,"In Quarter") -> 1.02 | G11: =COUNTIFS(Pipeline_Data!$E:$E,A11,Pipeline_Data!$F:$F,"<>Closed Won",Pipeline_Data!$F:$F,"<>Closed Lost") -> 9 | H11: =IF(G11=0,0,E11/G11) -> 0.43444444 | I11: =IF(C11=0,0,E11/C11) -> 2.0578947 | J11: =IF(C11=0,0,F11/C11) -> 0.53684211 | K11: =IF(C11=0,0,D11/C11) -> 0 | L11: =COUNTIFS(Pipeline_Data!$E:$E,A11,Pipeline_Data!$F:$F,"Closed Won") -> 0 | M11: =COUNTIFS(Pipeline_Data!$E:$E,A11,Pipeline_Data!$F:$F,"Closed Lost") -> 3 | N11: =IF((L11+M11)=0,0,L11/(L11+M11)) -> 0 | O11: =IF(I11<Inputs!$B$7,"Coverage Gap",IF(N11<Inputs!$B$11,"Win Rate Gap",IF(K11<0.5,"Quota Gap","On Track"))) -> Coverage Gap | Q11: =Inputs!$B$7 -> 3
A12: Harper Stone | B12: =VLOOKUP(A12,Inputs!$H$4:$J$11,3,FALSE) -> National | C12: =VLOOKUP(A12,Inputs!$H$4:$I$11,2,FALSE) -> 2 | D12: =SUMIFS(Pipeline_Data!$H:$H,Pipeline_Data!$E:$E,A12,Pipeline_Data!$F:$F,"Closed Won",Pipeline_Data!$N:$N,"In Quarter") -> 0.68 | E12: =SUMIFS(Pipeline_Data!$H:$H,Pipeline_Data!$E:$E,A12,Pipeline_Data!$F:$F,"<>Closed Won",Pipeline_Data!$F:$F,"<>Closed Lost",Pipeline_Data!$N:$N,"In Quarter") -> 3.95 | F12: =SUMIFS(Pipeline_Data!$J:$J,Pipeline_Data!$E:$E,A12,Pipeline_Data!$F:$F,"<>Closed Won",Pipeline_Data!$F:$F,"<>Closed Lost",Pipeline_Data!$N:$N,"In Quarter") -> 1.5815 | G12: =COUNTIFS(Pipeline_Data!$E:$E,A12,Pipeline_Data!$F:$F,"<>Closed Won",Pipeline_Data!$F:$F,"<>Closed Lost") -> 10 | H12: =IF(G12=0,0,E12/G12) -> 0.395 | I12: =IF(C12=0,0,E12/C12) -> 1.975 | J12: =IF(C12=0,0,F12/C12) -> 0.79075 | K12: =IF(C12=0,0,D12/C12) -> 0.34 | L12: =COUNTIFS(Pipeline_Data!$E:$E,A12,Pipeline_Data!$F:$F,"Closed Won") -> 1 | M12: =COUNTIFS(Pipeline_Data!$E:$E,A12,Pipeline_Data!$F:$F,"Closed Lost") -> 2 | N12: =IF((L12+M12)=0,0,L12/(L12+M12)) -> 0.33333333 | O12: =IF(I12<Inputs!$B$7,"Coverage Gap",IF(N12<Inputs!$B$11,"Win Rate Gap",IF(K12<0.5,"Quota Gap","On Track"))) -> Coverage Gap | Q12: =Inputs!$B$7 -> 3

Sheet Stage_Conversion
A1: Stage Conversion
A2: Pipeline stage analysis with conversion probabilities, aging metrics, and bottleneck identification
A4: Stage | B4: Probability | C4: Target Max Days | D4: Opp Count | E4: Unweighted Pipeline ($mm) | F4: Weighted Pipeline ($mm) | G4: Avg Days in Stage | H4: Aged Opps | I4: Aged Value ($mm) | J4: Bottleneck Flag | K4: Recommended Action
A5: Prospecting | B5: =IFERROR(VLOOKUP(A5,Inputs!$D$4:$F$11,2,FALSE),0) -> 0.1 | C5: =IFERROR(VLOOKUP(A5,Inputs!$D$4:$F$11,3,FALSE),0) -> 21 | D5: =COUNTIF(Pipeline_Data!$F:$F,A5) -> 9 | E5: =SUMIF(Pipeline_Data!$F:$F,A5,Pipeline_Data!$H:$H) -> 6.17 | F5: =SUMIF(Pipeline_Data!$F:$F,A5,Pipeline_Data!$J:$J) -> 0.617 | G5: =IFERROR(SUMIF(Pipeline_Data!$F:$F,A5,Pipeline_Data!$K:$K)/D5,0) -> 40.777778 | H5: =COUNTIFS(Pipeline_Data!$F:$F,A5,Pipeline_Data!$M:$M,"Aged") -> 7 | I5: =SUMIFS(Pipeline_Data!$H:$H,Pipeline_Data!$F:$F,A5,Pipeline_Data!$M:$M,"Aged") -> 3.66 | J5: =IF(AND(D5>0,G5>C5),"Velocity Bottleneck",IF(H5>2,"Aging Risk","Normal")) -> Velocity Bottleneck | K5: =IF(J5="Velocity Bottleneck","Run stage exit review",IF(J5="Aging Risk","Clean stale opportunities","Maintain cadence")) -> Run stage exit review
A6: Qualification | B6: =IFERROR(VLOOKUP(A6,Inputs!$D$4:$F$11,2,FALSE),0) -> 0.2 | C6: =IFERROR(VLOOKUP(A6,Inputs!$D$4:$F$11,3,FALSE),0) -> 21 | D6: =COUNTIF(Pipeline_Data!$F:$F,A6) -> 17 | E6: =SUMIF(Pipeline_Data!$F:$F,A6,Pipeline_Data!$H:$H) -> 7.66 | F6: =SUMIF(Pipeline_Data!$F:$F,A6,Pipeline_Data!$J:$J) -> 1.532 | G6: =IFERROR(SUMIF(Pipeline_Data!$F:$F,A6,Pipeline_Data!$K:$K)/D6,0) -> 40.823529 | H6: =COUNTIFS(Pipeline_Data!$F:$F,A6,Pipeline_Data!$M:$M,"Aged") -> 14 | I6: =SUMIFS(Pipeline_Data!$H:$H,Pipeline_Data!$F:$F,A6,Pipeline_Data!$M:$M,"Aged") -> 6.83 | J6: =IF(AND(D6>0,G6>C6),"Velocity Bottleneck",IF(H6>2,"Aging Risk","Normal")) -> Velocity Bottleneck | K6: =IF(J6="Velocity Bottleneck","Run stage exit review",IF(J6="Aging Risk","Clean stale opportunities","Maintain cadence")) -> Run stage exit review
A7: Discovery | B7: =IFERROR(VLOOKUP(A7,Inputs!$D$4:$F$11,2,FALSE),0) -> 0.3 | C7: =IFERROR(VLOOKUP(A7,Inputs!$D$4:$F$11,3,FALSE),0) -> 28 | D7: =COUNTIF(Pipeline_Data!$F:$F,A7) -> 9 | E7: =SUMIF(Pipeline_Data!$F:$F,A7,Pipeline_Data!$H:$H) -> 6.36 | F7: =SUMIF(Pipeline_Data!$F:$F,A7,Pipeline_Data!$J:$J) -> 1.908 | G7: =IFERROR(SUMIF(Pipeline_Data!$F:$F,A7,Pipeline_Data!$K:$K)/D7,0) -> 54.444444 | H7: =COUNTIFS(Pipeline_Data!$F:$F,A7,Pipeline_Data!$M:$M,"Aged") -> 8 | I7: =SUMIFS(Pipeline_Data!$H:$H,Pipeline_Data!$F:$F,A7,Pipeline_Data!$M:$M,"Aged") -> 6.03 | J7: =IF(AND(D7>0,G7>C7),"Velocity Bottleneck",IF(H7>2,"Aging Risk","Normal")) -> Velocity Bottleneck | K7: =IF(J7="Velocity Bottleneck","Run stage exit review",IF(J7="Aging Risk","Clean stale opportunities","Maintain cadence")) -> Run stage exit review
A8: Proposal | B8: =IFERROR(VLOOKUP(A8,Inputs!$D$4:$F$11,2,FALSE),0) -> 0.45 | C8: =IFERROR(VLOOKUP(A8,Inputs!$D$4:$F$11,3,FALSE),0) -> 30 | D8: =COUNTIF(Pipeline_Data!$F:$F,A8) -> 15 | E8: =SUMIF(Pipeline_Data!$F:$F,A8,Pipeline_Data!$H:$H) -> 7.79 | F8: =SUMIF(Pipeline_Data!$F:$F,A8,Pipeline_Data!$J:$J) -> 3.5055 | G8: =IFERROR(SUMIF(Pipeline_Data!$F:$F,A8,Pipeline_Data!$K:$K)/D8,0) -> 38.4 | H8: =COUNTIFS(Pipeline_Data!$F:$F,A8,Pipeline_Data!$M:$M,"Aged") -> 8 | I8: =SUMIFS(Pipeline_Data!$H:$H,Pipeline_Data!$F:$F,A8,Pipeline_Data!$M:$M,"Aged") -> 5.25 | J8: =IF(AND(D8>0,G8>C8),"Velocity Bottleneck",IF(H8>2,"Aging Risk","Normal")) -> Velocity Bottleneck | K8: =IF(J8="Velocity Bottleneck","Run stage exit review",IF(J8="Aging Risk","Clean stale opportunities","Maintain cadence")) -> Run stage exit review
A9: Negotiation | B9: =IFERROR(VLOOKUP(A9,Inputs!$D$4:$F$11,2,FALSE),0) -> 0.65 | C9: =IFERROR(VLOOKUP(A9,Inputs!$D$4:$F$11,3,FALSE),0) -> 21 | D9: =COUNTIF(Pipeline_Data!$F:$F,A9) -> 11 | E9: =SUMIF(Pipeline_Data!$F:$F,A9,Pipeline_Data!$H:$H) -> 4.44 | F9: =SUMIF(Pipeline_Data!$F:$F,A9,Pipeline_Data!$J:$J) -> 2.886 | G9: =IFERROR(SUMIF(Pipeline_Data!$F:$F,A9,Pipeline_Data!$K:$K)/D9,0) -> 38.272727 | H9: =COUNTIFS(Pipeline_Data!$F:$F,A9,Pipeline_Data!$M:$M,"Aged") -> 9 | I9: =SUMIFS(Pipeline_Data!$H:$H,Pipeline_Data!$F:$F,A9,Pipeline_Data!$M:$M,"Aged") -> 3.22 | J9: =IF(AND(D9>0,G9>C9),"Velocity Bottleneck",IF(H9>2,"Aging Risk","Normal")) -> Velocity Bottleneck | K9: =IF(J9="Velocity Bottleneck","Run stage exit review",IF(J9="Aging Risk","Clean stale opportunities","Maintain cadence")) -> Run stage exit review
A10: Verbal / Commit | B10: =IFERROR(VLOOKUP(A10,Inputs!$D$4:$F$11,2,FALSE),0) -> 0.85 | C10: =IFERROR(VLOOKUP(A10,Inputs!$D$4:$F$11,3,FALSE),0) -> 14 | D10: =COUNTIF(Pipeline_Data!$F:$F,A10) -> 1 | E10: =SUMIF(Pipeline_Data!$F:$F,A10,Pipeline_Data!$H:$H) -> 0.26 | F10: =SUMIF(Pipeline_Data!$F:$F,A10,Pipeline_Data!$J:$J) -> 0.221 | G10: =IFERROR(SUMIF(Pipeline_Data!$F:$F,A10,Pipeline_Data!$K:$K)/D10,0) -> 34 | H10: =COUNTIFS(Pipeline_Data!$F:$F,A10,Pipeline_Data!$M:$M,"Aged") -> 1 | I10: =SUMIFS(Pipeline_Data!$H:$H,Pipeline_Data!$F:$F,A10,Pipeline_Data!$M:$M,"Aged") -> 0.26 | J10: =IF(AND(D10>0,G10>C10),"Velocity Bottleneck",IF(H10>2,"Aging Risk","Normal")) -> Velocity Bottleneck | K10: =IF(J10="Velocity Bottleneck","Run stage exit review",IF(J10="Aging Risk","Clean stale opportunities","Maintain cadence")) -> Run stage exit review
A11: Closed Won | B11: =IFERROR(VLOOKUP(A11,Inputs!$D$4:$F$11,2,FALSE),0) -> 1 | C11: =IFERROR(VLOOKUP(A11,Inputs!$D$4:$F$11,3,FALSE),0) -> 999 | D11: =COUNTIF(Pipeline_Data!$F:$F,A11) -> 8 | E11: =SUMIF(Pipeline_Data!$F:$F,A11,Pipeline_Data!$H:$H) -> 4.32 | F11: =SUMIF(Pipeline_Data!$F:$F,A11,Pipeline_Data!$J:$J) -> 4.32 | G11: =IFERROR(SUMIF(Pipeline_Data!$F:$F,A11,Pipeline_Data!$K:$K)/D11,0) -> 43.875 | H11: =COUNTIFS(Pipeline_Data!$F:$F,A11,Pipeline_Data!$M:$M,"Aged") -> 0 | I11: =SUMIFS(Pipeline_Data!$H:$H,Pipeline_Data!$F:$F,A11,Pipeline_Data!$M:$M,"Aged") -> 0 | J11: =IF(AND(D11>0,G11>C11),"Velocity Bottleneck",IF(H11>2,"Aging Risk","Normal")) -> Normal | K11: =IF(J11="Velocity Bottleneck","Run stage exit review",IF(J11="Aging Risk","Clean stale opportunities","Maintain cadence")) -> Maintain cadence
A12: Closed Lost | B12: =IFERROR(VLOOKUP(A12,Inputs!$D$4:$F$11,2,FALSE),0) -> 0 | C12: =IFERROR(VLOOKUP(A12,Inputs!$D$4:$F$11,3,FALSE),0) -> 999 | D12: =COUNTIF(Pipeline_Data!$F:$F,A12) -> 15 | E12: =SUMIF(Pipeline_Data!$F:$F,A12,Pipeline_Data!$H:$H) -> 11.45 | F12: =SUMIF(Pipeline_Data!$F:$F,A12,Pipeline_Data!$J:$J) -> 0 | G12: =IFERROR(SUMIF(Pipeline_Data!$F:$F,A12,Pipeline_Data!$K:$K)/D12,0) -> 37.266667 | H12: =COUNTIFS(Pipeline_Data!$F:$F,A12,Pipeline_Data!$M:$M,"Aged") -> 0 | I12: =SUMIFS(Pipeline_Data!$H:$H,Pipeline_Data!$F:$F,A12,Pipeline_Data!$M:$M,"Aged") -> 0 | J12: =IF(AND(D12>0,G12>C12),"Velocity Bottleneck",IF(H12>2,"Aging Risk","Normal")) -> Normal | K12: =IF(J12="Velocity Bottleneck","Run stage exit review",IF(J12="Aging Risk","Clean stale opportunities","Maintain cadence")) -> Maintain cadence

Sheet Territory_Capacity
A1: Territory Capacity
A2: Selling time allocation, opportunity capacity gaps, and potential bookings uplift per rep
A4: Rep | B4: Region | C4: FTE | D4: Selling Hours / Week | E4: Admin Hours / Week | F4: Recovered Hours Potential | G4: Current Open Opps | H4: Target Opp Capacity | I4: Capacity Gap | J4: Additional Deals Supported | K4: Avg Open Deal ($mm) | L4: Potential Bookings Uplift ($mm) | M4: Productivity Action
A5: Alex Morgan | B5: =VLOOKUP(A5,Inputs!$H$4:$J$11,3,FALSE) -> East | C5: 1 | D5: 21 | E5: 8 | F5: =E5*Inputs!$C$16 -> 0.8 | G5: =COUNTIFS(Pipeline_Data!$E:$E,A5,Pipeline_Data!$F:$F,"<>Closed Won",Pipeline_Data!$F:$F,"<>Closed Lost") -> 7 | H5: =ROUND(D5/2.5,0) -> 8 | I5: =H5-G5 -> 1 | J5: =MAX(0,ROUND(F5/2.5,0)) -> 0 | K5: =IFERROR(SUMIFS(Pipeline_Data!$H:$H,Pipeline_Data!$E:$E,A5,Pipeline_Data!$F:$F,"<>Closed Won",Pipeline_Data!$F:$F,"<>Closed Lost")/G5,0) -> 0.63285714 | L5: =J5*K5*Inputs!$B$12 -> 0 | M5: =IF(I5<0,"Reduce load / rebalance territory",IF(L5>0.1,"Automate admin / add pipeline","Maintain")) -> Maintain
A6: Brooke Chen | B6: =VLOOKUP(A6,Inputs!$H$4:$J$11,3,FALSE) -> West | C6: 1 | D6: 22 | E6: 16 | F6: =E6*Inputs!$C$16 -> 1.6 | G6: =COUNTIFS(Pipeline_Data!$E:$E,A6,Pipeline_Data!$F:$F,"<>Closed Won",Pipeline_Data!$F:$F,"<>Closed Lost") -> 7 | H6: =ROUND(D6/2.5,0) -> 9 | I6: =H6-G6 -> 2 | J6: =MAX(0,ROUND(F6/2.5,0)) -> 1 | K6: =IFERROR(SUMIFS(Pipeline_Data!$H:$H,Pipeline_Data!$E:$E,A6,Pipeline_Data!$F:$F,"<>Closed Won",Pipeline_Data!$F:$F,"<>Closed Lost")/G6,0) -> 0.49 | L6: =J6*K6*Inputs!$B$12 -> 0.1372 | M6: =IF(I6<0,"Reduce load / rebalance territory",IF(L6>0.1,"Automate admin / add pipeline","Maintain")) -> Automate admin / add pipeline
A7: Chris Patel | B7: =VLOOKUP(A7,Inputs!$H$4:$J$11,3,FALSE) -> Central | C7: 1 | D7: 19 | E7: 11 | F7: =E7*Inputs!$C$16 -> 1.1 | G7: =COUNTIFS(Pipeline_Data!$E:$E,A7,Pipeline_Data!$F:$F,"<>Closed Won",Pipeline_Data!$F:$F,"<>Closed Lost") -> 12 | H7: =ROUND(D7/2.5,0) -> 8 | I7: =H7-G7 -> -4 | J7: =MAX(0,ROUND(F7/2.5,0)) -> 0 | K7: =IFERROR(SUMIFS(Pipeline_Data!$H:$H,Pipeline_Data!$E:$E,A7,Pipeline_Data!$F:$F,"<>Closed Won",Pipeline_Data!$F:$F,"<>Closed Lost")/G7,0) -> 0.6375 | L7: =J7*K7*Inputs!$B$12 -> 0 | M7: =IF(I7<0,"Reduce load / rebalance territory",IF(L7>0.1,"Automate admin / add pipeline","Maintain")) -> Reduce load / rebalance territory
A8: Dana Lewis | B8: =VLOOKUP(A8,Inputs!$H$4:$J$11,3,FALSE) -> East | C8: 1 | D8: 25 | E8: 11 | F8: =E8*Inputs!$C$16 -> 1.1 | G8: =COUNTIFS(Pipeline_Data!$E:$E,A8,Pipeline_Data!$F:$F,"<>Closed Won",Pipeline_Data!$F:$F,"<>Closed Lost") -> 7 | H8: =ROUND(D8/2.5,0) -> 10 | I8: =H8-G8 -> 3 | J8: =MAX(0,ROUND(F8/2.5,0)) -> 0 | K8: =IFERROR(SUMIFS(Pipeline_Data!$H:$H,Pipeline_Data!$E:$E,A8,Pipeline_Data!$F:$F,"<>Closed Won",Pipeline_Data!$F:$F,"<>Closed Lost")/G8,0) -> 0.45428571 | L8: =J8*K8*Inputs!$B$12 -> 0 | M8: =IF(I8<0,"Reduce load / rebalance territory",IF(L8>0.1,"Automate admin / add pipeline","Maintain")) -> Maintain
A9: Evan Ross | B9: =VLOOKUP(A9,Inputs!$H$4:$J$11,3,FALSE) -> West | C9: 1 | D9: 22 | E9: 11 | F9: =E9*Inputs!$C$16 -> 1.1 | G9: =COUNTIFS(Pipeline_Data!$E:$E,A9,Pipeline_Data!$F:$F,"<>Closed Won",Pipeline_Data!$F:$F,"<>Closed Lost") -> 5 | H9: =ROUND(D9/2.5,0) -> 9 | I9: =H9-G9 -> 4 | J9: =MAX(0,ROUND(F9/2.5,0)) -> 0 | K9: =IFERROR(SUMIFS(Pipeline_Data!$H:$H,Pipeline_Data!$E:$E,A9,Pipeline_Data!$F:$F,"<>Closed Won",Pipeline_Data!$F:$F,"<>Closed Lost")/G9,0) -> 0.442 | L9: =J9*K9*Inputs!$B$12 -> 0 | M9: =IF(I9<0,"Reduce load / rebalance territory",IF(L9>0.1,"Automate admin / add pipeline","Maintain")) -> Maintain
A10: Frances Kim | B10: =VLOOKUP(A10,Inputs!$H$4:$J$11,3,FALSE) -> Central | C10: 1 | D10: 21 | E10: 15 | F10: =E10*Inputs!$C$16 -> 1.5 | G10: =COUNTIFS(Pipeline_Data!$E:$E,A10,Pipeline_Data!$F:$F,"<>Closed Won",Pipeline_Data!$F:$F,"<>Closed Lost") -> 5 | H10: =ROUND(D10/2.5,0) -> 8 | I10: =H10-G10 -> 3 | J10: =MAX(0,ROUND(F10/2.5,0)) -> 1 | K10: =IFERROR(SUMIFS(Pipeline_Data!$H:$H,Pipeline_Data!$E:$E,A10,Pipeline_Data!$F:$F,"<>Closed Won",Pipeline_Data!$F:$F,"<>Closed Lost")/G10,0) -> 0.524 | L10: =J10*K10*Inputs!$B$12 -> 0.14672 | M10: =IF(I10<0,"Reduce load / rebalance territory",IF(L10>0.1,"Automate admin / add pipeline","Maintain")) -> Automate admin / add pipeline
A11: Gabe Wright | B11: =VLOOKUP(A11,Inputs!$H$4:$J$11,3,FALSE) -> National | C11: 1 | D11: 21 | E11: 12 | F11: =E11*Inputs!$C$16 -> 1.2 | G11: =COUNTIFS(Pipeline_Data!$E:$E,A11,Pipeline_Data!$F:$F,"<>Closed Won",Pipeline_Data!$F:$F,"<>Closed Lost") -> 9 | H11: =ROUND(D11/2.5,0) -> 8 | I11: =H11-G11 -> -1 | J11: =MAX(0,ROUND(F11/2.5,0)) -> 0 | K11: =IFERROR(SUMIFS(Pipeline_Data!$H:$H,Pipeline_Data!$E:$E,A11,Pipeline_Data!$F:$F,"<>Closed Won",Pipeline_Data!$F:$F,"<>Closed Lost")/G11,0) -> 0.50888889 | L11: =J11*K11*Inputs!$B$12 -> 0 | M11: =IF(I11<0,"Reduce load / rebalance territory",IF(L11>0.1,"Automate admin / add pipeline","Maintain")) -> Reduce load / rebalance territory
A12: Harper Stone | B12: =VLOOKUP(A12,Inputs!$H$4:$J$11,3,FALSE) -> National | C12: 1 | D12: 22 | E12: 9 | F12: =E12*Inputs!$C$16 -> 0.9 | G12: =COUNTIFS(Pipeline_Data!$E:$E,A12,Pipeline_Data!$F:$F,"<>Closed Won",Pipeline_Data!$F:$F,"<>Closed Lost") -> 10 | H12: =ROUND(D12/2.5,0) -> 9 | I12: =H12-G12 -> -1 | J12: =MAX(0,ROUND(F12/2.5,0)) -> 0 | K12: =IFERROR(SUMIFS(Pipeline_Data!$H:$H,Pipeline_Data!$E:$E,A12,Pipeline_Data!$F:$F,"<>Closed Won",Pipeline_Data!$F:$F,"<>Closed Lost")/G12,0) -> 0.458 | L12: =J12*K12*Inputs!$B$12 -> 0 | M12: =IF(I12<0,"Reduce load / rebalance territory",IF(L12>0.1,"Automate admin / add pipeline","Maintain")) -> Reduce load / rebalance territory

Sheet Forecast_Scenarios
A1: Forecast Scenarios
A3: Metric | B3: Conservative | C3: Base | D3: Upside
A4: Current Open Pipeline ($mm) | B4: =SUMIFS(Pipeline_Data!$H:$H,Pipeline_Data!$F:$F,"<>Closed Won",Pipeline_Data!$F:$F,"<>Closed Lost",Pipeline_Data!$N:$N,"In Quarter") -> 25.36 | C4: =SUMIFS(Pipeline_Data!$H:$H,Pipeline_Data!$F:$F,"<>Closed Won",Pipeline_Data!$F:$F,"<>Closed Lost",Pipeline_Data!$N:$N,"In Quarter") -> 25.36 | D4: =SUMIFS(Pipeline_Data!$H:$H,Pipeline_Data!$F:$F,"<>Closed Won",Pipeline_Data!$F:$F,"<>Closed Lost",Pipeline_Data!$N:$N,"In Quarter") -> 25.36
A5: Current Weighted Pipeline ($mm) | B5: =SUMIFS(Pipeline_Data!$J:$J,Pipeline_Data!$F:$F,"<>Closed Won",Pipeline_Data!$F:$F,"<>Closed Lost",Pipeline_Data!$N:$N,"In Quarter") -> 8.053 | C5: =SUMIFS(Pipeline_Data!$J:$J,Pipeline_Data!$F:$F,"<>Closed Won",Pipeline_Data!$F:$F,"<>Closed Lost",Pipeline_Data!$N:$N,"In Quarter") -> 8.053 | D5: =SUMIFS(Pipeline_Data!$J:$J,Pipeline_Data!$F:$F,"<>Closed Won",Pipeline_Data!$F:$F,"<>Closed Lost",Pipeline_Data!$N:$N,"In Quarter") -> 8.053
A6: Current Quarter Target ($mm) | B6: =Inputs!$B$6 -> 12 | C6: =Inputs!$B$6 -> 12 | D6: =Inputs!$B$6 -> 12
A7: Baseline Win Rate | B7: =Inputs!$B$11 -> 0.24 | C7: =Inputs!$B$11 -> 0.24 | D7: =Inputs!$B$11 -> 0.24
A8: Win Rate Improvement | B8: =Inputs!B$15/10000 -> 0.01 | C8: =Inputs!C$15/10000 -> 0.03 | D8: =Inputs!D$15/10000 -> 0.05
A9: Adjusted Win Rate | B9: =B7+B8 -> 0.25 | C9: =C7+C8 -> 0.27 | D9: =D7+D8 -> 0.29
A10: Pipeline Hygiene Removal | B10: =Inputs!B$18 -> 0.05 | C10: =Inputs!C$18 -> 0.08 | D10: =Inputs!D$18 -> 0.12
A11: Net Qualified Pipeline ($mm) | B11: =B4*(1-B10) -> 24.092 | C11: =C4*(1-C10) -> 23.3312 | D11: =D4*(1-D10) -> 22.3168
A12: Velocity / Capacity Uplift ($mm) | B12: =B4*Inputs!B$19*Inputs!B$20 -> 0.30432 | C12: =C4*Inputs!C$19*Inputs!C$20 -> 0.951 | D12: =D4*Inputs!D$19*Inputs!D$20 -> 1.72448
A13: Forecast Bookings ($mm) | B13: =(B11*B9)+B12 -> 6.32732 | C13: =(C11*C9)+C12 -> 7.250424 | D13: =(D11*D9)+D12 -> 8.196352
A14: Bookings Gap / (Surplus) ($mm) | B14: =B13-B6 -> -5.67268 | C14: =C13-C6 -> -4.749576 | D14: =D13-D6 -> -3.803648
A15: Incremental Bookings vs. Baseline ($mm) | B15: =MAX(0,B13-(B4*B7)) -> 0.24092 | C15: =MAX(0,C13-(C4*C7)) -> 1.164024 | D15: =MAX(0,D13-(D4*D7)) -> 2.109952
A16: Incremental EBITDA ($mm) | B16: =B15*Inputs!$B$8*Inputs!B$20 -> 0.06071184 | C16: =C15*Inputs!$B$8*Inputs!C$20 -> 0.36666756 | D16: =D15*Inputs!$B$8*Inputs!D$20 -> 0.75325286

Sheet EBITDA_Impact
A1: EBITDA Impact & Enterprise Value Bridge
A3: Lever | B3: Bookings Uplift ($mm) | C3: Contribution Margin % | D3: EBITDA Impact ($mm) | E3: EV Impact ($mm)
A4: Win Rate Improvement | B4: =Forecast_Scenarios!C15*0.45 -> 0.5238108 | C4: =Inputs!$B$8 -> 0.42 | D4: =B4*C4 -> 0.22000054 | E4: =D4*Inputs!$B$9 -> 2.5300062
A5: Admin Time / Capacity Recovery | B5: =SUM(Territory_Capacity!L5:L12) -> 0.28392 | C5: =Inputs!$B$8 -> 0.42 | D5: =B5*C5 -> 0.1192464 | E5: =D5*Inputs!$B$9 -> 1.3713336
A6: Stage Velocity Improvement | B6: =Forecast_Scenarios!C15*0.25 -> 0.291006 | C6: =Inputs!$B$8 -> 0.42 | D6: =B6*C6 -> 0.12222252 | E6: =D6*Inputs!$B$9 -> 1.405559
A7: Pipeline Hygiene / Forecast Discipline | B7: =Forecast_Scenarios!C15*0.15 -> 0.1746036 | C7: =Inputs!$B$8 -> 0.42 | D7: =B7*C7 -> 0.073333512 | E7: =D7*Inputs!$B$9 -> 0.84333539
A8: Territory Rebalance | B8: =Forecast_Scenarios!C15*0.15 -> 0.1746036 | C8: =Inputs!$B$8 -> 0.42 | D8: =B8*C8 -> 0.073333512 | E8: =D8*Inputs!$B$9 -> 0.84333539
A9: Total Incremental Impact | B9: =SUM(B4:B8) -> 1.447944 | C9: =Inputs!$B$8 -> 0.42 | D9: =B9*C9 -> 0.60813648 | E9: =D9*Inputs!$B$9 -> 6.9935695
A10: Less: Incremental Sales Enablement Cost | B10: =Inputs!$B$10/1000*1.5 -> 0.2775 | D10: =B10 -> 0.2775 | E10: =D10*Inputs!$B$9 -> 3.19125
A11: Net Run-Rate EBITDA Impact | B11: =D9-D10 -> 0.33063648 | D11: =D9-D10 -> 0.33063648 | E11: =D11*Inputs!$B$9 -> 3.8023195

Sheet Sources
A1: Sources, Assumptions, and Methodology Notes
A3: Area | B3: Source / Method | C3: URL / Note | D3: Use in Model | E3: Update Owner
A4: CRM / Pipeline | B4: User-provided CRM opportunity export | C4: Internal CRM export; replace sample data | D4: Pipeline_Data | E4: Sales Ops
A5: Quota / Rep Roster | B5: User-provided sales plan | C5: Internal operating plan | D5: Inputs / Rep_Productivity | E5: Sales Leadership
A6: Stage Probabilities | B6: Management estimate / historical conversion analysis | C6: Replace with historical stage conversion rates where available | D6: Inputs / Forecast | E6: Revenue Ops
A7: Contribution Margin | B7: Finance estimate | C7: Use actual contribution margin by product/service if available | D7: EBITDA_Impact | E7: Finance
A8: Exit Multiple | B8: Management / sponsor underwriting assumption | C8: Use actual underwriting case or current market view | D8: EV impact sizing | E8: Sponsor / CFO
A9: Capacity Assumptions | B9: Management estimate / time study | C9: Replace with time study, CRM activity data, or rep productivity benchmarks | D9: Territory_Capacity | E9: Sales Ops
A10: Model Style | B10: Ops2EBITDA brand system | C10: Ink #161413, Bone #F4EFE6, Paper #FBF8F2, Ochre #B8862F, Sienna #7A2E1F, Stone #928B7E | D10: Visual formatting | E10: Ops2EBITDA
A11: Caveat | B11: Illustrative model | C11: Not financial, legal, or investment advice; validate all assumptions with company data | D11: All sheets | E11: User
